Workbook

Sheet Notes
A1: Notes
A3: HMRC guide to R&D tax credits:
A4: http://www.hmrc.gov.uk/gds/cird/attachments/rdsimpleguide.pdf
A6: Industry funded projects:
A7: - If no risk then large company scheme (RDEC), & only unfunded proportion claimable against R&D tax credits
A8: - If risk (only paid on success) then small company scheme, & only unfunded proportion claimable against R&D tax credits
A10: Under large company scheme subcontracted labour costs are not allowable unless they are carried out by:
A11: - A qualifying body (a charity, an institution of higher education such as a university, a scientific research organisation or a health service body)
A12: - An individual
A13: - A partnership, each member of which is an individual
A15: Under the SME scheme rules sub contracted labour costs are subject to a 65% adjustment and also subject to connected party rules - lower of rate charged by provider or provider's own costs
A16: Note that any materials provided by the sub contractor are not subject to the 65% adjustment but are still subject to the connected party rules
... A38: Benefits in kind provided to R&D workers - e.g. medical insurance cover - are not allowable

Sheet QIA
A1: Qualifying Indirect Activities
A3: Description | B3: Total Cost | D3: R&D
A5: Shared admin / clerical costs:
A6: Payroll | B6: 8500
A7: HR | B7: 4200
A8: Other administration / clerical | B8: 3100
B10: =SUM(B4:B9) -> 15800 | C10: =staff!#ref! -> #NAME? | D10: =B10*C10 -> #NAME?
A12: Dedicated costs:
A13: Admin associated with R&D laboratory leasing | D13: 1200 | G13: NB The actual laboratory leasing cost does not qualify for R&D tax credits
A14: Admin associated with R&D equipment leasing | D14: 800 | G14: NB The actual equipment leasing cost does not qualify for R&D tax credits
A15: Admin associated with R&D equipment maintenance | D15: 600 | G15: NB The actual equipment maintenance cost does not qualify for R&D tax credits
A16: Scientific & technical information services & research | D16: 2400
A17: R&D training | D17: 1800
D20: =SUM(D10:D19) -> #NAME?
A23: HMRC list of qualifying indirect activities:
A24: a. scientific and technical information services, insofar as they are conducted for the purpose of R&D support (such as the preparation of the original report of R&D findings);
A25: b. indirect supporting activities such as maintenance, security, administration and clerical activities, and finance and personnel activities, insofar as undertaken for R&D;
A26: c. ancillary activities essential to the undertaking of R&D (e.g. taking on and paying staff, leasing laboratories and maintaining research and development equipment including computers used for R&D purposes);
A27: d. training required to directly support an R&D project;
A28: e. research by students and researchers carried out at universities;
A29: f. research (including related data collection) to devise new scientific or technological testing, survey, or sampling methods, where this research is not R&D in its own right; and
A30: g. feasibility studies to inform the strategic direction of a specific R&D activity.

Sheet Summary
A1: R&D Tax Credit Claim
A2: NovaTech Solutions Ltd
A3: Tax Reference: 1234567890
A4: Period: 01/01/2024 to 31/12/2024
A6: R&D Periods
A7: Period | B7: From | C7: To | D7: Months
A8: Period 1 | B8: 45292 | C8: 45382 | D8: =IFERROR((DATEDIF(B8, C8, "M")+1), 0) -> 3
A9: Period 2 | B9: 45383 | C9: 45657 | D9: =IFERROR((DATEDIF(B9, C9, "M")+1), 0) -> 9
D10: =SUM(D8:D9) -> 12
A12: R&D Projects
A14: Number | B14: Project Name | C14: Funded? | D14: De Minimis? | E14: Estimate of total R&D Expenditure (%) | F14: Start Date | G14: End Date | Y14: SME
A15: 1 | B15: Automated Document Intelligence Platform | C15: No | D15: No | E15: 0.85 | F15: 45078 | G15: 45657 | Y15: RDEC
A16: 2 | B16: Real-Time Anomaly Detection Engine | C16: No | D16: No | E16: 0.9 | F16: 45292 | G16: 45657 | Y16: De Minimis
A17: 3 | B17: Natural Language Query Interface | C17: No | D17: No | E17: 0.75 | F17: 45352 | G17: 45657
A18: 4 | B18: Predictive Maintenance ML Pipeline | C18: Yes | D18: No | E18: 0.8 | F18: 45170 | G18: 45565
A19: 5 | B19: Privacy-Preserving Data Linkage | C19: No | D19: No | E19: 0.7 | F19: 45444 | G19: 45657 | Y19: Yes
A20: 6 | Y20: No
A21: 7
A22: 8
A23: 9
A24: 10
A25: 11
A26: 12
A28: N.B. The workbook hasn't yet been automated to calculate De Minimis - therefore any de minimis projects will require additional calculations

Sheet Spend by Project
A1: Spend by Project
A3: Cost Category | B3: =IF(Summary!$B$15>0,Summary!$B$15,"") -> Automated Document Intelligence Platform | C3: =IF(Summary!$B$16>0,Summary!$B$16,"") -> Real-Time Anomaly Detection Engine | D3: =IF(Summary!$B$17>0,Summary!$B$17,"") -> Natural Language Query Interface | E3: =IF(Summary!$B$18>0,Summary!$B$18,"") -> Predictive Maintenance ML Pipeline | F3: =IF(Summary!$B$19>0,Summary!$B$19,"") -> Privacy-Preserving Data Linkage | G3: =IF(Summary!$B$20>0,Summary!$B$20,"") | H3: =IF(Summary!$B$21>0,Summary!$B$21,"") | I3: =IF(Summary!$B$22>0,Summary!$B$22,"") | J3: =IF(Summary!$B$23>0,Summary!$B$23,"") | K3: =IF(Summary!$B$24>0,Summary!$B$24,"") | L3: =IF(Summary!$B$25>0,Summary!$B$25,"") | M3: =IF(Summary!$B$26>0,Summary!$B$26,"") | N3: Total | O3: Total | P3: Total
B4: =IF(ISBLANK(Summary!$C$15),"", IF(Summary!$C$15="No", "SME", IF(AND(Summary!$C$15="Yes", Summary!$D$15="Yes"), "De Minimis", "RDEC"))) -> SME | C4: =IF(ISBLANK(Summary!$C$16),"", IF(Summary!$C$16="No", "SME", IF(AND(Summary!$C$16="Yes", Summary!$D$16="Yes"), "De Minimis", "RDEC"))) -> SME | D4: =IF(ISBLANK(Summary!$C$17),"", IF(Summary!$C$17="No", "SME", IF(AND(Summary!$C$17="Yes", Summary!$D$17="Yes"), "De Minimis", "RDEC"))) -> SME | E4: =IF(ISBLANK(Summary!$C$18),"", IF(Summary!$C$18="No", "SME", IF(AND(Summary!$C$18="Yes", Summary!$D$18="Yes"), "De Minimis", "RDEC"))) -> RDEC | F4: =IF(ISBLANK(Summary!$C$19),"", IF(Summary!$C$19="No", "SME", IF(AND(Summary!$C$19="Yes", Summary!$D$19="Yes"), "De Minimis", "RDEC"))) -> SME | G4: =IF(ISBLANK(Summary!$C$20),"", IF(Summary!$C$20="No", "SME", IF(AND(Summary!$C$20="Yes", Summary!$D$20="Yes"), "De Minimis", "RDEC"))) | H4: =IF(ISBLANK(Summary!$C$21),"", IF(Summary!$C$21="No", "SME", IF(AND(Summary!$C$21="Yes", Summary!$D$21="Yes"), "De Minimis", "RDEC"))) | I4: =IF(ISBLANK(Summary!$C$22),"", IF(Summary!$C$22="No", "SME", IF(AND(Summary!$C$22="Yes", Summary!$D$22="Yes"), "De Minimis", "RDEC"))) | J4: =IF(ISBLANK(Summary!$C$23),"", IF(Summary!$C$23="No", "SME", IF(AND(Summary!$C$23="Yes", Summary!$D$23="Yes"), "De Minimis", "RDEC"))) | K4: =IF(ISBLANK(Summary!$C$24),"", IF(Summary!$C$24="No", "SME", IF(AND(Summary!$C$24="Yes", Summary!$D$24="Yes"), "De Minimis", "RDEC"))) | L4: =IF(ISBLANK(Summary!$C$25),"", IF(Summary!$C$25="No", "SME", IF(AND(Summary!$C$25="Yes", Summary!$D$25="Yes"), "De Minimis", "RDEC"))) | M4: =IF(ISBLANK(Summary!$C$26),"", IF(Summary!$C$26="No", "SME", IF(AND(Summary!$C$26="Yes", Summary!$D$26="Yes"), "De Minimis", "RDEC"))) | N4: SME | O4: RDEC
A6: Total:
A7: UK Staff Salaries | B7: =+B26+B43 -> 207641.37 | C7: =+C26+C43 -> 182945.49 | D7: =+D26+D43 -> 122172.16 | E7: =+E26+E43 -> 128104.26 | F7: =+F26+F43 -> 98788.466 | G7: =+G26+G43 -> 0 | H7: =+H26+H43 -> 0 | I7: =+I26+I43 -> 0 | ... M7: =+M26+M43 -> 0 | N7: =SUMIF($B$4:$M$4,$N$4, B7:M7) -> 611547.48 | O7: =SUMIF($B$4:$M$4,$O$4, B7:M7) -> 128104.26 | P7: =SUM(N7:O7) -> 739651.74
A8: Overseas Staff | B8: ='Overseas Staff'!Y905 -> 0 | C8: ='Overseas Staff'!Z905 -> 0 | D8: ='Overseas Staff'!AA905 -> 0 | E8: ='Overseas Staff'!AB905 -> 0 | F8: ='Overseas Staff'!AC905 -> 0 | G8: ='Overseas Staff'!AD905 -> 0 | H8: ='Overseas Staff'!AE905 -> 0 | I8: ='Overseas Staff'!AF905 -> 0 | ... M8: ='Overseas Staff'!AJ905 -> 0 | N8: =SUMIF($B$4:$M$4,$N$4, B8:M8) -> 0 | O8: =SUMIF($B$4:$M$4,$O$4, B8:M8) -> 0 | P8: =SUM(N8:O8) -> 0
A9: Recruitment & Relocation | B9: =IF(B$4="SME", 'Recruitment & Relocation'!X$50*0.65, 'Recruitment & Relocation'!X$50) -> 4348.5 | C9: =IF(C$4="SME", 'Recruitment & Relocation'!Y$50*0.65, 'Recruitment & Relocation'!Y$50) -> 1131 | D9: =IF(D$4="SME", 'Recruitment & Relocation'!Z$50*0.65, 'Recruitment & Relocation'!Z$50) -> 2281.5 | E9: =IF(E$4="SME", 'Recruitment & Relocation'!AA$50*0.65, 'Recruitment & Relocation'!AA$50) -> 1300 | F9: =IF(F$4="SME", 'Recruitment & Relocation'!AB$50*0.65, 'Recruitment & Relocation'!AB$50) -> 1404 | G9: =IF(G$4="SME", 'Recruitment & Relocation'!AC$50*0.65, 'Recruitment & Relocation'!AC$50) -> 0 | H9: =IF(H$4="SME", 'Recruitment & Relocation'!AD$50*0.65, 'Recruitment & Relocation'!AD$50) -> 0 | I9: =IF(I$4="SME", 'Recruitment & Relocation'!AE$50*0.65, 'Recruitment & Relocation'!AE$50) -> 0 | ... M9: =IF(M$4="SME", 'Recruitment & Relocation'!AI$50*0.65, 'Recruitment & Relocation'!AI$50) -> 0 | N9: =SUMIF($B$4:$M$4,$N$4, B9:M9) -> 9165 | O9: =SUMIF($B$4:$M$4,$O$4, B9:M9) -> 1300 | P9: =SUM(N9:O9) -> 10465
A10: Training | B10: =Training!V52 -> 2135 | C10: =Training!W52 -> 2210 | D10: =Training!X52 -> 2355 | E10: =Training!Y52 -> 800 | F10: =Training!Z52 -> 1950 | G10: =Training!AA52 -> 0 | H10: =Training!AB52 -> 0 | I10: =Training!AC52 -> 0 | ... M10: =Training!AG52 -> 0 | N10: =SUMIF($B$4:$M$4,$N$4, B10:M10) -> 8650 | O10: =SUMIF($B$4:$M$4,$O$4, B10:M10) -> 800 | P10: =SUM(N10:O10) -> 9450
A11: Travel & Subsistence | B11: ='Travel & Subsistence'!V101 -> 760.5 | C11: ='Travel & Subsistence'!W101 -> 546.5 | D11: ='Travel & Subsistence'!X101 -> 686.5 | E11: ='Travel & Subsistence'!Y101 -> 353 | F11: ='Travel & Subsistence'!Z101 -> 628.5 | G11: ='Travel & Subsistence'!AA101 -> 0 | H11: ='Travel & Subsistence'!AB101 -> 0 | I11: ='Travel & Subsistence'!AC101 -> 0 | ... M11: ='Travel & Subsistence'!AG101 -> 0 | N11: =SUMIF($B$4:$M$4,$N$4, B11:M11) -> 2622 | O11: =SUMIF($B$4:$M$4,$O$4, B11:M11) -> 353 | P11: =SUM(N11:O11) -> 2975
B12: =SUM(B7:B11) -> 214885.37 | C12: =SUM(C7:C11) -> 186832.99 | D12: =SUM(D7:D11) -> 127495.16 | E12: =SUM(E7:E11) -> 130557.26 | F12: =SUM(F7:F11) -> 102770.97 | G12: =SUM(G7:G11) -> 0 | H12: =SUM(H7:H11) -> 0 | I12: =SUM(I7:I11) -> 0 | ... P12: =SUM(P7:P11) -> 762541.74
A14: EPW | B14: 0 | C14: 0 | D14: 0 | E14: 0 | F14: 0 | G14: 0 | H14: 0 | I14: 0 | J14: 0 | K14: 0 | L14: 0 | M14: 0 | N14: =SUMIF($B$4:$M$4,$N$4, B14:M14) -> 0 | O14: =SUMIF($B$4:$M$4,$O$4, B14:M14) -> 0 | P14: =SUM(N14:O14) -> 0
A15: Clinical Trial Participants | B15: 0 | C15: 0 | D15: 0 | E15: 0 | F15: 0 | G15: 0 | H15: 0 | I15: 0 | J15: 0 | K15: 0 | L15: 0 | M15: 0 | N15: =SUMIF($B$4:$M$4,$N$4, B15:M15) -> 0 | O15: =SUMIF($B$4:$M$4,$O$4, B15:M15) -> 0 | P15: =SUM(N15:O15) -> 0
A16: Software | B16: =Software!V247 -> 11172 | C16: =Software!W247 -> 10930 | D16: =Software!X247 -> 9630 | E16: =Software!Y247 -> 4368 | F16: =Software!Z247 -> 6940 | G16: =Software!AA247 -> 0 | H16: =Software!AB247 -> 0 | I16: =Software!AC247 -> 0 | ... M16: =Software!AG247 -> 0 | N16: =SUMIF($B$4:$M$4,$N$4, B16:M16) -> 38672 | O16: =SUMIF($B$4:$M$4,$O$4, B16:M16) -> 4368 | P16: =SUM(N16:O16) -> 43040
A17: Materials & Consumables | B17: ='Materials and Consumables'!V215+Subcontractors!AS210 -> 9499 | C17: ='Materials and Consumables'!W215+Subcontractors!AT210 -> 19671.5 | D17: ='Materials and Consumables'!X215+Subcontractors!AU210 -> 4513.5 | E17: ='Materials and Consumables'!Y215+Subcontractors!AV210 -> 22356 | F17: ='Materials and Consumables'!Z215+Subcontractors!AW210 -> 7470 | G17: ='Materials and Consumables'!AA215+Subcontractors!AX210 -> 0 | H17: ='Materials and Consumables'!AB215+Subcontractors!AY210 -> 0 | I17: ='Materials and Consumables'!AC215+Subcontractors!AZ210 -> 0 | ... M17: ='Materials and Consumables'!AG215+Subcontractors!BD210 -> 0 | N17: =SUMIF($B$4:$M$4,$N$4, B17:M17) -> 41154 | O17: =SUMIF($B$4:$M$4,$O$4, B17:M17) -> 22356 | P17: =SUM(N17:O17) -> 63510
A18: Sub-Contractors | B18: =IF(B$4="SME", Subcontractors!AB$210*0.65, Subcontractors!AB$210) -> 9404.2 | C18: =IF(C$4="SME", Subcontractors!AC$210*0.65, Subcontractors!AC$210) -> 12166.7 | D18: =IF(D$4="SME", Subcontractors!AD$210*0.65, Subcontractors!AD$210) -> 6825 | E18: =IF(E$4="SME", Subcontractors!AE$210*0.65, Subcontractors!AE$210) -> 1680 | F18: =IF(F$4="SME", Subcontractors!AF$210*0.65, Subcontractors!AF$210) -> 15977 | G18: =IF(G$4="SME", Subcontractors!AG$210*0.65, Subcontractors!AG$210) -> 0 | H18: =IF(H$4="SME", Subcontractors!AH$210*0.65, Subcontractors!AH$210) -> 0 | I18: =IF(I$4="SME", Subcontractors!AI$210*0.65, Subcontractors!AI$210) -> 0 | ... M18: =IF(M$4="SME", Subcontractors!AM$210*0.65, Subcontractors!AM$210) -> 0 | N18: =SUMIF($B$4:$M$4,$N$4, B18:M18) -> 44372.9 | O18: =SUMIF($B$4:$M$4,$O$4, B18:M18) -> 1680 | P18: =SUM(N18:O18) -> 46052.9
A20: Total (£) | B20: =SUM(B12:B19) -> 244960.57 | C20: =SUM(C12:C19) -> 229601.19 | D20: =SUM(D12:D19) -> 148463.66 | E20: =SUM(E12:E19) -> 158961.26 | F20: =SUM(F12:F19) -> 133157.97 | G20: =SUM(G12:G19) -> 0 | H20: =SUM(H12:H19) -> 0 | I20: =SUM(I12:I19) -> 0 | ... P20: =SUM(P12:P19) -> 915144.64
A21: Total SME or RDEC (%) | B21: =IFERROR(IF(B4="SME",B20/$N$20,B20/$O$20),0) -> 0.32394333 | C21: =IFERROR(IF(C4="SME",C20/$N$20,C20/$O$20),0) -> 0.30363163 | D21: =IFERROR(IF(D4="SME",D20/$N$20,D20/$O$20),0) -> 0.19633287 | E21: =IFERROR(IF(E4="SME",E20/$N$20,E20/$O$20),0) -> 1 | F21: =IFERROR(IF(F4="SME",F20/$N$20,F20/$O$20),0) -> 0.17609216 | G21: =IFERROR(IF(G4="SME",G20/$N$20,G20/$O$20),0) -> 0 | H21: =IFERROR(IF(H4="SME",H20/$N$20,H20/$O$20),0) -> 0 | I21: =IFERROR(IF(I4="SME",I20/$N$20,I20/$O$20),0) -> 0 | ... M21: =IFERROR(IF(M4="SME",M20/$N$20,M20/$O$20),0) -> 0 | N21: 1 | O21: 1 | P21: -
A22: Total SME and RDEC (%) | B22: =IFERROR(B20/$P$20, 0) -> 0.26767415 | C22: =IFERROR(C20/$P$20, 0) -> 0.25089061 | D22: =IFERROR(D20/$P$20, 0) -> 0.16222972 | E22: =IFERROR(E20/$P$20, 0) -> 0.17370069 | F22: =IFERROR(F20/$P$20, 0) -> 0.14550483 | G22: =IFERROR(G20/$P$20, 0) -> 0 | H22: =IFERROR(H20/$P$20, 0) -> 0 | I22: =IFERROR(I20/$P$20, 0) -> 0 | ... P22: =IFERROR(P20/$P$20, 0) -> 1
A25: Direct costs:
A26: UK Staff Salaries - Direct | B26: =Staff!AB921 -> 178267.78 | C26: =Staff!AC921 -> 154465.81 | D26: =Staff!AD921 -> 102822.89 | E26: =Staff!AE921 -> 108517.97 | F26: =Staff!AF921 -> 84332.849 | G26: =Staff!AG921 -> 0 | H26: =Staff!AH921 -> 0 | I26: =Staff!AI921 -> 0 | ... M26: =Staff!AM921 -> 0 | N26: =SUMIF($B$4:$M$4,$N$4, B26:M26) -> 519889.33 | O26: =SUMIF($B$4:$M$4,$O$4, B26:M26) -> 108517.97 | P26: =SUM(N26:O26) -> 628407.29
A27: Overseas Staff | B27: =+B8 -> 0 | C27: =+C8 -> 0 | D27: =+D8 -> 0 | E27: =+E8 -> 0 | F27: =+F8 -> 0 | G27: =+G8 -> 0 | H27: =+H8 -> 0 | I27: =+I8 -> 0 | ... M27: =+M8 -> 0 | N27: =SUMIF($B$4:$M$4,$N$4, B27:M27) -> 0 | O27: =SUMIF($B$4:$M$4,$O$4, B27:M27) -> 0 | P27: =SUM(N27:O27) -> 0
A28: Recruitment & Relocation | B28: =+B9 -> 4348.5 | C28: =+C9 -> 1131 | D28: =+D9 -> 2281.5 | E28: =+E9 -> 1300 | F28: =+F9 -> 1404 | G28: =+G9 -> 0 | H28: =+H9 -> 0 | I28: =+I9 -> 0 | ... M28: =+M9 -> 0 | N28: =SUMIF($B$4:$M$4,$N$4, B28:M28) -> 9165 | O28: =SUMIF($B$4:$M$4,$O$4, B28:M28) -> 1300 | P28: =SUM(N28:O28) -> 10465
A29: Training | B29: =+B10 -> 2135 | C29: =+C10 -> 2210 | D29: =+D10 -> 2355 | E29: =+E10 -> 800 | F29: =+F10 -> 1950 | G29: =+G10 -> 0 | H29: =+H10 -> 0 | I29: =+I10 -> 0 | ... M29: =+M10 -> 0 | N29: =SUMIF($B$4:$M$4,$N$4, B29:M29) -> 8650 | O29: =SUMIF($B$4:$M$4,$O$4, B29:M29) -> 800 | P29: =SUM(N29:O29) -> 9450
A30: Travel & Subsistence | B30: =+B11 -> 760.5 | C30: =+C11 -> 546.5 | D30: =+D11 -> 686.5 | E30: =+E11 -> 353 | F30: =+F11 -> 628.5 | G30: =+G11 -> 0 | H30: =+H11 -> 0 | I30: =+I11 -> 0 | ... M30: =+M11 -> 0 | N30: =SUMIF($B$4:$M$4,$N$4, B30:M30) -> 2622 | O30: =SUMIF($B$4:$M$4,$O$4, B30:M30) -> 353 | P30: =SUM(N30:O30) -> 2975
C31: =SUM(C26:C30) -> 158353.31 | D31: =SUM(D26:D30) -> 108145.89 | E31: =SUM(E26:E30) -> 110970.97 | F31: =SUM(F26:F30) -> 88315.349 | G31: =SUM(G26:G30) -> 0 | H31: =SUM(H26:H30) -> 0 | I31: =SUM(I26:I30) -> 0 | J31: =SUM(J26:J30) -> 0 | ... P31: =SUM(P26:P30) -> 651297.29
A33: EPW | B33: =+B14 -> 0 | C33: =+C14 -> 0 | D33: =+D14 -> 0 | E33: =+E14 -> 0 | F33: =+F14 -> 0 | G33: =+G14 -> 0 | H33: =+H14 -> 0 | I33: =+I14 -> 0 | ... M33: =+M14 -> 0 | N33: =SUMIF($B$4:$M$4,$N$4, B33:M33) -> 0 | O33: =SUMIF($B$4:$M$4,$O$4, B33:M33) -> 0 | P33: =SUM(N33:O33) -> 0
A34: Clinical Trial Participants | B34: =+B15 -> 0 | C34: =+C15 -> 0 | D34: =+D15 -> 0 | E34: =+E15 -> 0 | F34: =+F15 -> 0 | G34: =+G15 -> 0 | H34: =+H15 -> 0 | I34: =+I15 -> 0 | ... M34: =+M15 -> 0 | N34: =SUMIF($B$4:$M$4,$N$4, B34:M34) -> 0 | O34: =SUMIF($B$4:$M$4,$O$4, B34:M34) -> 0 | P34: =SUM(N34:O34) -> 0
A35: Software | B35: =+B16 -> 11172 | C35: =+C16 -> 10930 | D35: =+D16 -> 9630 | E35: =+E16 -> 4368 | F35: =+F16 -> 6940 | G35: =+G16 -> 0 | H35: =+H16 -> 0 | I35: =+I16 -> 0 | ... M35: =+M16 -> 0 | N35: =SUMIF($B$4:$M$4,$N$4, B35:M35) -> 38672 | O35: =SUMIF($B$4:$M$4,$O$4, B35:M35) -> 4368 | P35: =SUM(N35:O35) -> 43040
A36: Materials & Consumables | B36: =+B17 -> 9499 | C36: =+C17 -> 19671.5 | D36: =+D17 -> 4513.5 | E36: =+E17 -> 22356 | F36: =+F17 -> 7470 | G36: =+G17 -> 0 | H36: =+H17 -> 0 | I36: =+I17 -> 0 | ... M36: =+M17 -> 0 | N36: =SUMIF($B$4:$M$4,$N$4, B36:M36) -> 41154 | O36: =SUMIF($B$4:$M$4,$O$4, B36:M36) -> 22356 | P36: =SUM(N36:O36) -> 63510
A37: Sub-Contractors | B37: =+B18 -> 9404.2 | C37: =+C18 -> 12166.7 | D37: =+D18 -> 6825 | E37: =+E18 -> 1680 | F37: =+F18 -> 15977 | G37: =+G18 -> 0 | H37: =+H18 -> 0 | I37: =+I18 -> 0 | ... M37: =+M18 -> 0 | N37: =SUMIF($B$4:$M$4,$N$4, B37:M37) -> 44372.9 | O37: =SUMIF($B$4:$M$4,$O$4, B37:M37) -> 1680 | P37: =SUM(N37:O37) -> 46052.9
A39: Total direct costs (£) | B39: =SUM(B31:B38) -> 30075.2 | C39: =SUM(C31:C38) -> 201121.51 | D39: =SUM(D31:D38) -> 129114.39 | E39: =SUM(E31:E38) -> 139374.97 | F39: =SUM(F31:F38) -> 118702.35 | G39: =SUM(G31:G38) -> 0 | H39: =SUM(H31:H38) -> 0 | I39: =SUM(I31:I38) -> 0 | ... P39: =SUM(P31:P38) -> 803900.19
A42: Indirect costs:
A43: UK Staff Salaries - Indirect | B43: =Staff!AR921 -> 29373.586 | C43: =Staff!AS921 -> 28479.686 | D43: =Staff!AT921 -> 19349.265 | E43: =Staff!AU921 -> 19586.291 | F43: =Staff!AV921 -> 14455.617 | G43: =Staff!AW921 -> 0 | H43: =Staff!AX921 -> 0 | I43: =Staff!AY921 -> 0 | ... M43: =Staff!BC921 -> 0 | N43: =SUMIF($B$4:$M$4,$N$4, B43:M43) -> 91658.155 | O43: =SUMIF($B$4:$M$4,$O$4, B43:M43) -> 19586.291 | P43: =SUM(N43:O43) -> 111244.45
A44: Overseas Staff | B44: 0 | C44: 0 | D44: 0 | E44: 0 | F44: 0 | G44: 0 | H44: 0 | I44: 0 | J44: 0 | K44: 0 | L44: 0 | M44: 0 | N44: =SUMIF($B$4:$M$4,$N$4, B44:M44) -> 0 | O44: =SUMIF($B$4:$M$4,$O$4, B44:M44) -> 0 | P44: =SUM(N44:O44) -> 0
A45: Recruitment & Relocation | B45: 0 | C45: 0 | D45: 0 | E45: 0 | F45: 0 | G45: 0 | H45: 0 | I45: 0 | J45: 0 | K45: 0 | L45: 0 | M45: 0 | N45: =SUMIF($B$4:$M$4,$N$4, B45:M45) -> 0 | O45: =SUMIF($B$4:$M$4,$O$4, B45:M45) -> 0 | P45: =SUM(N45:O45) -> 0
A46: Training | B46: 0 | C46: 0 | D46: 0 | E46: 0 | F46: 0 | G46: 0 | H46: 0 | I46: 0 | J46: 0 | K46: 0 | L46: 0 | M46: 0 | N46: =SUMIF($B$4:$M$4,$N$4, B46:M46) -> 0 | O46: =SUMIF($B$4:$M$4,$O$4, B46:M46) -> 0 | P46: =SUM(N46:O46) -> 0
A47: Travel & Subsistence | B47: 0 | C47: 0 | D47: 0 | E47: 0 | F47: 0 | G47: 0 | H47: 0 | I47: 0 | J47: 0 | K47: 0 | L47: 0 | M47: 0 | N47: =SUMIF($B$4:$M$4,$N$4, B47:M47) -> 0 | O47: =SUMIF($B$4:$M$4,$O$4, B47:M47) -> 0 | P47: =SUM(N47:O47) -> 0
B48: 0 | C48: 0 | D48: 0 | E48: 0 | F48: 0 | G48: 0 | H48: 0 | I48: 0 | J48: 0 | K48: 0 | L48: 0 | M48: 0 | N48: =SUM(N43:N47) -> 91658.155 | O48: =SUM(O43:O47) -> 19586.291 | P48: =SUM(P43:P47) -> 111244.45
A50: EPW | B50: 0 | C50: 0 | D50: 0 | E50: 0 | F50: 0 | G50: 0 | H50: 0 | I50: 0 | J50: 0 | K50: 0 | L50: 0 | M50: 0 | N50: =SUMIF($B$4:$M$4,$N$4, B50:M50) -> 0 | O50: =SUMIF($B$4:$M$4,$O$4, B50:M50) -> 0 | P50: =SUM(N50:O50) -> 0
A51: Clinical Trial Participants | B51: 0 | C51: 0 | D51: 0 | E51: 0 | F51: 0 | G51: 0 | H51: 0 | I51: 0 | J51: 0 | K51: 0 | L51: 0 | M51: 0 | N51: =SUMIF($B$4:$M$4,$N$4, B51:M51) -> 0 | O51: =SUMIF($B$4:$M$4,$O$4, B51:M51) -> 0 | P51: =SUM(N51:O51) -> 0
A52: Software | B52: 0 | C52: 0 | D52: 0 | E52: 0 | F52: 0 | G52: 0 | H52: 0 | I52: 0 | J52: 0 | K52: 0 | L52: 0 | M52: 0 | N52: =SUMIF($B$4:$M$4,$N$4, B52:M52) -> 0 | O52: =SUMIF($B$4:$M$4,$O$4, B52:M52) -> 0 | P52: =SUM(N52:O52) -> 0
A53: Materials & Consumables | B53: 0 | C53: 0 | D53: 0 | E53: 0 | F53: 0 | G53: 0 | H53: 0 | I53: 0 | J53: 0 | K53: 0 | L53: 0 | M53: 0 | N53: =SUMIF($B$4:$M$4,$N$4, B53:M53) -> 0 | O53: =SUMIF($B$4:$M$4,$O$4, B53:M53) -> 0 | P53: =SUM(N53:O53) -> 0
A54: Sub-Contractors | B54: 0 | C54: 0 | D54: 0 | E54: 0 | F54: 0 | G54: 0 | H54: 0 | I54: 0 | J54: 0 | K54: 0 | L54: 0 | M54: 0 | N54: =SUMIF($B$4:$M$4,$N$4, B54:M54) -> 0 | O54: =SUMIF($B$4:$M$4,$O$4, B54:M54) -> 0 | P54: =SUM(N54:O54) -> 0
A56: Total indirect costs (£) | B56: =SUM(B48:B55) -> 0 | C56: =SUM(C48:C55) -> 0 | D56: =SUM(D48:D55) -> 0 | E56: =SUM(E48:E55) -> 0 | F56: =SUM(F48:F55) -> 0 | G56: =SUM(G48:G55) -> 0 | H56: =SUM(H48:H55) -> 0 | I56: =SUM(I48:I55) -> 0 | ... P56: =SUM(P48:P55) -> 111244.45
A58: Check | B58: =+B20-B39-B56 -> 214885.37 | C58: =+C20-C39-C56 -> 28479.686 | D58: =+D20-D39-D56 -> 19349.265 | E58: =+E20-E39-E56 -> 19586.291 | F58: =+F20-F39-F56 -> 14455.617 | G58: =+G20-G39-G56 -> 0 | H58: =+H20-H39-H56 -> 0 | I58: =+I20-I39-I56 -> 0 | ... M58: =+M20-M39-M56 -> 0

Sheet R&D Calculation (OLD)
A1: R&D Tax Credit Claim
A2: =Summary!A2 -> NovaTech Solutions Ltd
A3: =Summary!A3 -> Tax Reference: 1234567890
A5: =Summary!A4 -> Period: 01/01/2024 to 31/12/2024
D7: Total
A9: SME Scheme | D9: Spend | E9: Allowable % | F9: Allowable Spend | H9: Period 1 | I9: Period 2 | J9: Check
H10: 44743 | I10: 45017
H11: 45016 | I11: 45107
A13: UK staff costs | D13: =Staff!AO921+Staff!BE921 -> 611547.48 | E13: 1 | F13: =D13*E13 -> 611547.48 | J13: =+D13-H13-I13 -> 611547.48
A14: Overseas staff costs | D14: ='Overseas Staff'!AL905 -> 0 | E14: 1 | F14: =D14*E14 -> 0 | J14: =+D14-H14-I14 -> 0
A15: Recruitment & relocation | D15: ='Recruitment & Relocation'!AK50 -> 14100 | E15: 0.65 | F15: =D15*E15 -> 9165 | H15: =SUMIFS('Recruitment & Relocation'!AK7:AK48, 'Recruitment & Relocation'!A7:A48, ">="&H10, 'Recruitment & Relocation'!A7:A48, "<="&H11)*0.65 -> 0 | I15: =SUMIFS('Recruitment & Relocation'!AK7:AK48, 'Recruitment & Relocation'!A7:A48, ">="&I10, 'Recruitment & Relocation'!A7:A48, "<="&I11)*0.65 -> 0 | J15: =+F15-H15-I15 -> 9165
A16: Training | D16: =Training!AI52 -> 8650 | E16: 1 | F16: =D16*E16 -> 8650 | J16: =+D16-H16-I16 -> 8650
A17: Travel & subsistence (Out of pocket expenses only) | D17: ='Travel & Subsistence'!AI101 -> 2622 | E17: 1 | F17: =D17*E17 -> 2622 | J17: =+D17-H17-I17 -> 2622
A18: Software | D18: =Software!AI247 -> 38672 | E18: 1 | F18: =D18*E18 -> 38672 | J18: =+D18-H18-I18 -> 38672
A19: Materials & consumables | D19: ='Materials and Consumables'!AI215+Subcontractors!BF210 -> 41154 | E19: 1 | F19: =D19*E19 -> 41154 | J19: =+D19-H19-I19 -> 41154
A20: Sub contractors (Connected parties) | D20: =+Subcontractors!AO210 -> 0 | E20: 1 | F20: =D20*E20 -> 0 | J20: =+D20-H20-I20 -> 0
A21: Sub contractors (Unconnected parties) | D21: =+Subcontractors!AP210 -> 68266 | E21: 0.65 | F21: =D21*E21 -> 44372.9
A22: Total relevant net expenditure | D22: =SUM(D13:D21) -> 785011.48 | F22: =SUM(F13:F21) -> 756183.38 | H22: =SUM(H13:H21) -> 0 | I22: =SUM(I13:I21) -> 0
A24: Claim for enhancement: | B24: No. of Mths
A25: Jul 2022 - Mar 2023 | B25: 9 | E25: 1.3 | F25: =(F22/$B$27*$B$25)*$E$25 -> 737278.8 | H25: =+H22*E25 -> 0 | I25: 0
A26: Apr 2023 - Jun 2023 | B26: 3 | E26: 0.86 | F26: =(F22/$B$27*$B$26)*$E$26 -> 162579.43 | H26: 0 | I26: =+I22*E26 -> 0
A27: Total | B27: =SUM(B25:B26) -> 12 | F27: =F25+F26 -> 899858.22 | H27: =H25+H26 -> 0 | I27: =I25+I26 -> 0
A30: Normal taxable profit / (loss) on ordinary activities | B30: TBC | F30: 0
A33: Trading loss (after R&D Relief) | B33: A | F33: =IF((-F30+F27)>0,-F30+F27,0) -> 899858.22
A35: Total enhanced R&D spend | B35: B | F35: =F22+F27 -> 1656041.6
A37: Loss qualifying for conversion to repayable credits | B37: Lower of A or B | F37: =IF(F33<F35,F33,F35) -> 899858.22
A40: Payable tax credit under SME scheme
A42: =A25 -> Jul 2022 - Mar 2023 | D42: =((($F$37)/B27*B25)) -> 674893.67 | E42: 0.145 | F42: =D42*E42 -> 97859.582 | H42: =((($F$37)/B27*B25)) -> 674893.67 | I42: =((($F$37)/M27*M25)) -> #DIV/0! | L42: SME intensive test
A43: =A26 -> Apr 2023 - Jun 2023 | D43: =((($F$37)/B27*B26)) -> 224964.56 | E43: 0.1 | F43: =D43*E43 -> 22496.456 | H43: =((($F$37)/L27*L26)) -> #DIV/0! | I43: =((($F$37)/M27*M26)) -> #DIV/0! | L43: Total R&D expenditure | O43: 1
A44: =+A43 -> Apr 2023 - Jun 2023 | E44: 0.045 | F44: =IF(O45>0.4, D43*E44, 0) -> 10123.405 | L44: Total CT eligible expenditure | O44: 1
D45: =SUM(D42:D43) -> 899858.22 | F45: =SUM(F42:F44) -> 130479.44 | H45: =SUM(H42:H43) -> #DIV/0! | I45: =SUM(I42:I43) -> #DIV/0! | O45: =+O43/O44 -> 1
A48: RDEC Scheme | D48: Spend | E48: % Allowable | F48: Allowable Spend
A50: Expenditure on R&D for which Innovate UK grants received:
A51: UK staff costs | D51: =Staff!AN921+Staff!BD921 -> 128104.26 | E51: 1 | F51: =D51*E51 -> 128104.26
A52: Overseas staff costs | D52: ='Overseas Staff'!AK905 -> 0 | E52: 1 | F52: =D52*E52 -> 0
A53: Recruitment & relocation | D53: ='Recruitment & Relocation'!AJ50 -> 1300 | E53: 1 | F53: =D53*E53 -> 1300
A54: Training | D54: =Training!AH52 -> 800 | E54: 1 | F54: =D54*E54 -> 800
A55: Travel & subsistence (out of pocket expenses only) | D55: ='Travel & Subsistence'!AH101 -> 353 | E55: 1 | F55: =D55*E55 -> 353
A56: Software | D56: =Software!AH247 -> 4368 | E56: 1 | F56: =D56*E56 -> 4368
A57: Materials & consumables | D57: ='Materials and Consumables'!AH215+Subcontractors!BE210 -> 22356 | E57: 1 | F57: =D57*E57 -> 22356
A58: Sub contractors | D58: =Subcontractors!AN210 -> 1680 | E58: 1 | F58: =D58*E58 -> 1680
A59: Total relevant net expenditure | D59: =SUM(D51:D58) -> 158961.26 | F59: =SUM(F51:F58) -> 158961.26
A63: RDEC Income
A64: =A25 -> Jul 2022 - Mar 2023 | E64: 0.13 | F64: =(F59/B27*B25)*E64 -> 15498.723
A65: =A26 -> Apr 2023 - Jun 2023 | E65: 0.2 | F65: =(F59/B27*B26)*E65 -> 7948.0629
A66: Total | F66: =F64+F65 -> 23446.786
A68: Step 1
A69: CT Profit (Loss) before credit | F69: =F30 -> 0
A70: CT due | F70: 0
A71: RDEC amount remaining | F71: =F66-F70 -> 23446.786
A73: Step 2
A74: Amount remaining from Step 1 | B74: A | F74: =F71 -> 23446.786
A75: Less potential CT on the credit:
A76: =A25 -> Jul 2022 - Mar 2023 | D76: 0.19 | E76: =F66/B27*B25*D76 -> 3341.1669
A77: =A26 -> Apr 2023 - Jun 2023 | D77: 0.25 | E77: =F66/B27*B26*D77 -> 1465.4241
F78: =E76+E77 -> 4806.591
A79: Net RDEC | B79: B | F79: =F74-F78 -> 18640.195
A81: c/fwd | B81: Lower of A or B | F81: =IF(F79<F74,F79,F74) -> 18640.195
A83: Step 3
A84: b/fwd from Step 2 | B84: C | F84: =F81 -> 18640.195
A85: PAYE/NI liability on R&D workers | B85: D | F85: =Staff!AN923 -> 50272.179
A87: c/fwd | B87: Lower of C or D | F87: =IF(F85<F84,F85,F84) -> 18640.195
A89: Step 4
A90: b/fwd from Step 3 | F90: =F87 -> 18640.195
A91: Other period CT liability | F91: 0
A92: c/fwd | F92: =F90-F91 -> 18640.195
A94: Step 5
A95: b/fwd from Step 4 | F95: =F92 -> 18640.195
A96: CT liabilities of the group | F96: 0
A97: c/fwd | F97: =F95-F96 -> 18640.195
A99: Step 6
A100: b/fwd from Step 5 | F100: =F97 -> 18640.195
A101: Any HMRC liability | F101: 0
A102: c/fwd | F102: =F100-F101 -> 18640.195
A104: Step 7
A105: Payable to company | F105: =F102 -> 18640.195
A108: RDEC Summary
A109: Tax withheld available to set off against future liability b/fwd | F109: 0
A110: Tax withheld available to set off against future liability (Step 2) | F110: =F78 -> 4806.591
A111: PAYE capped credit b/fwd | F111: 0
A112: PAYE capped credit c/fwd (Step 3) | F112: =IF(F85<F84,F84-F85,0) -> 0
A113: Company CT liability of other accounting period (Step 4) | F113: =F91 -> 0
A114: Paid to company (Step 7) | F114: =F105 -> 18640.195
A115: RDEC total c/fwd | F115: =+F109+F110+F111+F112-F113 -> 4806.591
A118: CT600 Summary
A119: Box 530 R&D tax credit | F119: =F114+F111+F70+F45 -> 149119.64
A120: Box 650 / 655 - SME or Large Company | F120: SME
A121: Box 660 R&D enhanced expenditure | F121: =F22+F27+F59 -> 1815002.9
A122: Box 875 Payable R&D tax credit | F122: =F119 -> 149119.64
A124: PAYE / NIC
A125: Limit for R&D Tax Credits (Limit is £20,000 plus 3 x PAYE/NI) | F125: =20000+((Staff!F916+Staff!G916+Staff!H921)*3) -> 890788.49
A126: Limit applicable from 1st April 2021

Sheet R&D Calculation
A1: R&D Calculation
A2: =Summary!A2 -> NovaTech Solutions Ltd
A3: =Summary!A3 -> Tax Reference: 1234567890
A4: =Summary!A4 -> Period: 01/01/2024 to 31/12/2024
A7: SME Scheme
A8: Qualifying expenditure for the period: | B8: Check | C8: Period 1 | D8: Period 2 | E8: Total Spend | F8: Allowable | G8: Allowable Spend 1 | H8: Allowable Spend 2 | I8: Total Allowable | J8: Check
C9: =+Summary!$B$8 -> 45292 | D9: =+Summary!$B$9 -> 45383 | G9: =+Summary!$B$8 -> 45292 | H9: =+Summary!$B$9 -> 45383
C10: =+Summary!$C$8 -> 45382 | D10: =+Summary!$C$9 -> 45657 | G10: =+Summary!$C$8 -> 45382 | H10: =+Summary!$C$9 -> 45657
A11: UK staff costs | B11: =+E11-C11-D11 -> 0 | C11: =(SUMIFS(Staff!AO7:AO900,Staff!D7:D900,">="&C9,Staff!D7:D900,"<="&C10))+(SUMIFS(Staff!BE7:BE900,Staff!D7:D900,">="&C9,Staff!D7:D900,"<="&C10))-((Staff!AO919+Staff!BE919)/E25*E23) -> 153360.35 | D11: =(SUMIFS(Staff!AO7:AO900,Staff!D7:D900,">="&D9,Staff!D7:D900,"<="&D10))+(SUMIFS(Staff!BE7:BE900,Staff!D7:D900,">="&D9,Staff!D7:D900,"<="&D10))-((Staff!AO919+Staff!BE919)/E25*E24) -> 458187.13 | E11: =Staff!AO921+Staff!BE921 -> 611547.48 | F11: 1 | G11: =+C11*$F11 -> 153360.35 | H11: =+D11*$F11 -> 458187.13 | I11: =SUM(G11:H11) -> 611547.48 | J11: =+(E11*F11)-I11 -> 0
A12: Overseas Staff costs | B12: =+E12-C12-D12 -> 0 | C12: =(SUMIFS('Overseas Staff'!AL7:AL902,'Overseas Staff'!D7:D902,">="&C9,'Overseas Staff'!D7:D902,"<="&C10)) +(SUMIFS('Overseas Staff'!BB7:BB902,'Overseas Staff'!D7:D902,">="&C9,'Overseas Staff'!D7:D902,"<="&C10)) -> 0 | D12: =(SUMIFS('Overseas Staff'!AL7:AL902,'Overseas Staff'!D7:D902,">="&D9,'Overseas Staff'!D7:D902,"<="&D10)) +(SUMIFS('Overseas Staff'!BB7:BB902,'Overseas Staff'!D7:D902,">="&D9,'Overseas Staff'!D7:D902,"<="&D10)) -> 0 | E12: =+'Overseas Staff'!AL905+'Overseas Staff'!BB905 -> 0 | F12: 1 | G12: =+C12*$F12 -> 0 | H12: =+D12*$F12 -> 0 | I12: =SUM(G12:H12) -> 0 | J12: =+(E12*F12)-I12 -> 0
A13: Recruitment & relocation | B13: =+E13-C13-D13 -> 0 | C13: =SUMIFS('Recruitment & Relocation'!AK7:AK48, 'Recruitment & Relocation'!A7:A48, ">="&$C$9, 'Recruitment & Relocation'!A7:A48, "<="&$C$10) -> 10050 | D13: =SUMIFS('Recruitment & Relocation'!AK7:AK48, 'Recruitment & Relocation'!A7:A48, ">="&$D$9, 'Recruitment & Relocation'!A7:A48, "<="&$D$10) -> 4050 | E13: ='Recruitment & Relocation'!AK50 -> 14100 | F13: 0.65 | G13: =+C13*$F13 -> 6532.5 | H13: =+D13*$F13 -> 2632.5 | I13: =SUM(G13:H13) -> 9165 | J13: =+(E13*F13)-I13 -> 0
A14: Training | B14: =+E14-C14-D14 -> 0 | C14: =SUMIFS(Training!AI7:AI50,Training!A7:A50, ">="&$C$9,Training!A7:A50, "<="&$C$10) -> 2550 | D14: =SUMIFS(Training!AI7:AI50,Training!A7:A50, ">="&$D$9,Training!A7:A50, "<="&$D$10) -> 6100 | E14: =Training!AI52 -> 8650 | F14: 1 | G14: =+C14*$F14 -> 2550 | H14: =+D14*$F14 -> 6100 | I14: =SUM(G14:H14) -> 8650 | J14: =+(E14*F14)-I14 -> 0
A15: Travel & subsistence (Out of pocket expenses only) | B15: =+E15-C15-D15 -> 0 | C15: =SUMIFS('Travel & Subsistence'!AI7:AI99, 'Travel & Subsistence'!A7:A99, ">="&$C$9, 'Travel & Subsistence'!A7:A99, "<="&$C$10) -> 795 | D15: =SUMIFS('Travel & Subsistence'!AI7:AI99, 'Travel & Subsistence'!A7:A99, ">="&$D$9, 'Travel & Subsistence'!A7:A99, "<="&$D$10) -> 1827 | E15: ='Travel & Subsistence'!AI101 -> 2622 | F15: 1 | G15: =+C15*$F15 -> 795 | H15: =+D15*$F15 -> 1827 | I15: =SUM(G15:H15) -> 2622 | J15: =+(E15*F15)-I15 -> 0
A16: Software | B16: =+E16-C16-D16 -> 0 | C16: =SUMIFS(Software!AI7:AI245, Software!A7:A245, ">="&$C$9, Software!A7:A245, "<="&$C$10) -> 14080 | D16: =SUMIFS(Software!AI7:AI245, Software!A7:A245, ">="&$D$9, Software!A7:A245, "<="&$D$10) -> 24592 | E16: =Software!AI247 -> 38672 | F16: 1 | G16: =+C16*$F16 -> 14080 | H16: =+D16*$F16 -> 24592 | I16: =SUM(G16:H16) -> 38672 | J16: =+(E16*F16)-I16 -> 0
A17: Materials & consumables | B17: =+E17-C17-D17 -> 0 | C17: =(SUMIFS('Materials and Consumables'!AI7:AI211,'Materials and Consumables'!A7:A211,">="&$C$9,'Materials and Consumables'!A7:A211,"<="&$C$10))+(SUMIFS(Subcontractors!BF7:BF208,Subcontractors!A7:A208,">="&$C$9,Subcontractors!A7:A208,"<="&$C$10)) -> 17134 | D17: =(SUMIFS('Materials and Consumables'!AI7:AI211,'Materials and Consumables'!A7:A211,">="&$D$9,'Materials and Consumables'!A7:A211,"<="&$D$10))+(SUMIFS(Subcontractors!BF7:BF208,Subcontractors!A7:A208,">="&$D$9,Subcontractors!A7:A208,"<="&$D$10)) -> 24020 | E17: ='Materials and Consumables'!AI215+Subcontractors!BF210 -> 41154 | F17: 1 | G17: =+C17*$F17 -> 17134 | H17: =+D17*$F17 -> 24020 | I17: =SUM(G17:H17) -> 41154 | J17: =+(E17*F17)-I17 -> 0
A18: Subcontractors (Connected parties) | B18: =+E18-C18-D18 -> 0 | C18: =SUMIFS(Subcontractors!AO7:AO208, Subcontractors!A7:A208, ">="&$C$9, Subcontractors!A7:A208, "<="&$C$10) -> 0 | D18: =SUMIFS(Subcontractors!AO7:AO208, Subcontractors!A7:A208, ">="&$D$9, Subcontractors!A7:A208, "<="&$D$10) -> 0 | E18: =+Subcontractors!AO210 -> 0 | F18: 1 | G18: =+C18*$F18 -> 0 | H18: =+D18*$F18 -> 0 | I18: =SUM(G18:H18) -> 0 | J18: =+(E18*F18)-I18 -> 0
A19: Subcontractors (Unconnected parties) | B19: =+E19-C19-D19 -> 0 | C19: =SUMIFS(Subcontractors!AP7:AP208, Subcontractors!A7:A208, ">="&$C$9, Subcontractors!A7:A208, "<="&$C$10) -> 23476 | D19: =SUMIFS(Subcontractors!AP8:AP209, Subcontractors!A8:A209, ">="&$D$9, Subcontractors!A8:A209, "<="&$D$10) -> 44790 | E19: =+Subcontractors!AP210 -> 68266 | F19: 0.65 | G19: =+C19*$F19 -> 15259.4 | H19: =+D19*$F19 -> 29113.5 | I19: =SUM(G19:H19) -> 44372.9 | J19: =+(E19*F19)-I19 -> 0
A20: Total relevant net expenditure | B20: =SUM(B11:B19) -> 0 | C20: =SUM(C11:C19) -> 221445.35 | D20: =SUM(D11:D19) -> 563566.13 | E20: =SUM(E11:E19) -> 785011.48 | G20: =SUM(G11:G19) -> 209711.25 | H20: =SUM(H11:H19) -> 546472.13 | I20: =SUM(I11:I19) -> 756183.38 | J20: =SUM(J11:J19) -> 0
A22: Claim for enhancement:
A23: =(TEXT(C9,"MMM-YY")&" to "&(TEXT(C10,"mmm-yy"))) -> Jan-24 to Mar-24 | E23: =+Summary!D8 -> 3 | F23: 1.3 | G23: =+G20*F23 -> 272624.63 | H23: 0 | I23: =SUM(G23:H23) -> 272624.63
A24: =(TEXT(D9,"MMM-YY")&" to "&(TEXT(D10,"mmm-yy"))) -> Apr-24 to Dec-24 | E24: =+Summary!D9 -> 9 | F24: 0.86 | G24: 0 | H24: =+H20*F24 -> 469966.03 | I24: =SUM(G24:H24) -> 469966.03
A25: Total | E25: =SUM(E23:E24) -> 12 | G25: =SUM(G23:G24) -> 272624.63 | H25: =SUM(H23:H24) -> 469966.03 | I25: =SUM(I23:I24) -> 742590.66
A27: Surrendable tax credits:
A28: Normal taxable profit / (loss) on ordinary activities | G28: =+$I$28/$E$25*$E$23 -> -21250 | H28: =+$I$28/$E$25*$E$24 -> -63750 | I28: -85000 | J28: TBC
A29: Trading loss (after R&D relief) | G29: =IF((-G28+G25)>0,-G28+G25,0) -> 293874.63 | H29: =IF((-H28+H25)>0,-H28+H25,0) -> 533716.03 | I29: =IF((-I28+I25)>0,-I28+I25,0) -> 827590.66 | J29: A
A30: Total enhanced R&D spend | G30: =G20+G25 -> 482335.89 | H30: =H20+H25 -> 1016438.2 | I30: =I20+I25 -> 1498774 | J30: B
A31: Loss qualifying for conversion to repayable credits | G31: =IF(G29<G30,G29,G30) -> 293874.63 | H31: =IF(H29<H30,H29,H30) -> 533716.03 | I31: =IF(I29<I30,I29,I30) -> 827590.66 | J31: Lower of A or B
A33: SME intensive test:
A34: Total SME + RDEC R&D expenditure | I34: =+I20+I58 -> 915144.64
A35: Total trading & operating expenditure | I35: 1800000 | J35: TBC
A36: Intensitivity ratio | I36: =IFERROR(I34/I35, 0) -> 0.50841369
A38: Payable tax credit under SME scheme:
A39: =A23 -> Jan-24 to Mar-24 | F39: 0.145 | G39: =G31*F39 -> 42611.821 | H39: 0 | I39: =+G31*F39 -> 42611.821
A40: =A24 -> Apr-24 to Dec-24 | F40: 0.1 | G40: 0 | H40: =+H31*F40 -> 53371.603 | I40: =SUM(G40:H40) -> 53371.603
A41: =+A40 -> Apr-24 to Dec-24 | F41: 0.045 | G41: 0 | H41: =IF(I36>0.4,H31*F41, 0) -> 24017.221 | I41: =SUM(G41:H41) -> 24017.221
A42: Total payable SME tax credits | G42: =SUM(G39:G41) -> 42611.821 | H42: =SUM(H39:H41) -> 77388.824 | I42: =SUM(I39:I41) -> 120000.65
A46: RDEC Scheme
A47: Expenditure on R&D for which Innovate UK grants received: | B47: Check | C47: Period 1 | D47: Period 2 | E47: Spend | F47: Allowable % | G47: Allowable Spend 1 | H47: Allowable Spend 2 | I47: Total Allowable | J47: Check
C48: =+Summary!$B$8 -> 45292 | D48: =+Summary!$B$9 -> 45383 | G48: =+Summary!$B$8 -> 45292 | H48: =+Summary!$B$9 -> 45383
C49: =+Summary!$C$8 -> 45382 | D49: =+Summary!$C$9 -> 45657 | G49: =+Summary!$C$8 -> 45382 | H49: =+Summary!$C$9 -> 45657
A50: UK staff costs | B50: =+E50-C50-D50 -> 0 | C50: =(SUMIFS(Staff!AN7:AN900,Staff!D7:D900,">="&C48,Staff!D7:D900,"<="&C49))+(SUMIFS(Staff!BD7:BD900,Staff!D7:D900,">="&C48,Staff!D7:D900,"<="&C49))-((Staff!AN919+Staff!BD919)/E63*E61) -> 32134.235 | D50: =(SUMIFS(Staff!AN7:AN900,Staff!D7:D900,">="&D48,Staff!D7:D900,"<="&D49))+(SUMIFS(Staff!BD7:BD900,Staff!D7:D900,">="&D48,Staff!D7:D900,"<="&D49))-((Staff!AN919+Staff!BD919)/E63*E62) -> 95970.023 | E50: =+Staff!$AN$921+Staff!$BD$921 -> 128104.26 | F50: 1 | G50: =+C50*$F50 -> 32134.235 | H50: =+D50*$F50 -> 95970.023 | I50: =SUM(G50:H50) -> 128104.26 | J50: =+(E50*F50)-I50 -> 0
A51: Overseas staff costs | B51: =+E51-C51-D51 -> 0 | C51: =(SUMIFS('Overseas Staff'!AK7:AK902,'Overseas Staff'!D7:D902,">="&C48,'Overseas Staff'!D7:D902,"<="&C49)) +(SUMIFS('Overseas Staff'!BA7:BA902,'Overseas Staff'!D7:D902,">="&C48,'Overseas Staff'!D7:D902,"<="&C49)) -> 0 | D51: =(SUMIFS('Overseas Staff'!AK7:AK902,'Overseas Staff'!D7:D902,">="&D48,'Overseas Staff'!D7:D902,"<="&D49)) +(SUMIFS('Overseas Staff'!BA7:BA902,'Overseas Staff'!D7:D902,">="&D48,'Overseas Staff'!D7:D902,"<="&D49)) -> 0 | E51: =+'Overseas Staff'!$AK$905+'Overseas Staff'!$BA$905 -> 0 | F51: 1 | G51: =+C51*$F51 -> 0 | H51: =+D51*$F51 -> 0 | I51: =SUM(G51:H51) -> 0 | J51: =+(E51*F51)-I51 -> 0
A52: Recruitment & relocation | B52: =+E52-C52-D52 -> 0 | C52: =SUMIFS('Recruitment & Relocation'!AJ7:AJ48, 'Recruitment & Relocation'!A7:A48, ">="&C48, 'Recruitment & Relocation'!A7:A48, "<="&C49) -> 850 | D52: =SUMIFS('Recruitment & Relocation'!AJ7:AJ48, 'Recruitment & Relocation'!A7:A48, ">="&D48, 'Recruitment & Relocation'!A7:A48, "<="&D49) -> 450 | E52: =+'Recruitment & Relocation'!$AJ$50 -> 1300 | F52: 1 | G52: =+C52*$F52 -> 850 | H52: =+D52*$F52 -> 450 | I52: =SUM(G52:H52) -> 1300 | J52: =+(E52*F52)-I52 -> 0
A53: Training | B53: =+E53-C53-D53 -> 0 | C53: =SUMIFS(Training!AH7:AH50,Training!A7:A50, ">="&C48,Training!A7:A50, "<="&C49) -> 450 | D53: =SUMIFS(Training!AH7:AH50,Training!A7:A50, ">="&D48,Training!A7:A50, "<="&D49) -> 350 | E53: =+Training!$AH$52 -> 800 | F53: 1 | G53: =+C53*$F53 -> 450 | H53: =+D53*$F53 -> 350 | I53: =SUM(G53:H53) -> 800 | J53: =+(E53*F53)-I53 -> 0
A54: Travel & subsistence (out of pocket expenses only) | B54: =+E54-C54-D54 -> 0 | C54: =SUMIFS('Travel & Subsistence'!AH7:AH99, 'Travel & Subsistence'!A7:A99, ">="&$C$48, 'Travel & Subsistence'!A7:A99, "<="&$C$49) -> 0 | D54: =SUMIFS('Travel & Subsistence'!AH7:AH99, 'Travel & Subsistence'!A7:A99, ">="&$D$48, 'Travel & Subsistence'!A7:A99, "<="&$D$49) -> 353 | E54: =+'Travel & Subsistence'!$AH$101 -> 353 | F54: 1 | G54: =+C54*$F54 -> 0 | H54: =+D54*$F54 -> 353 | I54: =SUM(G54:H54) -> 353 | J54: =+(E54*F54)-I54 -> 0
A55: Software | B55: =+E55-C55-D55 -> 0 | C55: =SUMIFS(Software!AH7:AH245, Software!A7:A245, ">="&$C$48, Software!A7:A245, "<="&$C$49) -> 1920 | D55: =SUMIFS(Software!AH7:AH245, Software!A7:A245, ">="&$D$48, Software!A7:A245, "<="&$D$49) -> 2448 | E55: =+Software!$AH$247 -> 4368 | F55: 1 | G55: =+C55*$F55 -> 1920 | H55: =+D55*$F55 -> 2448 | I55: =SUM(G55:H55) -> 4368 | J55: =+(E55*F55)-I55 -> 0
A56: Materials & consumables | B56: =+E56-C56-D56 -> -6936 | C56: =(SUMIFS('Materials and Consumables'!AH7:AH211,'Materials and Consumables'!A7:A211,">="&$C$48,'Materials and Consumables'!A7:A211,"<="&$C$49))+(SUMIFS(Subcontractors!BE7:BE211,Subcontractors!A7:A211,">="&$C$48,Subcontractors!A7:A211,"<="&$C$49)) -> 8056 | D56: =(SUMIFS('Materials and Consumables'!AH7:AH211,'Materials and Consumables'!A7:A211,">="&$D$48,'Materials and Consumables'!A7:A211,"<="&$D$49))+(SUMIFS(Subcontractors!BE7:BE211,Subcontractors!A7:A211,">="&$D$48,Subcontractors!A7:A211,"<="&$D$49)) -> 14300 | E56: =+'Materials and Consumables'!$AH$215+Subcontractors!$BE$211 -> 15420 | F56: 1 | G56: =+C56*$F56 -> 8056 | H56: =+D56*$F56 -> 14300 | I56: =SUM(G56:H56) -> 22356 | J56: =+(E56*F56)-I56 -> -6936
A57: Subcontractors | B57: =+E57-C57-D57 -> 0 | C57: =SUMIFS(Subcontractors!AN7:AN208, Subcontractors!A7:A208, ">="&$C$48, Subcontractors!A7:A208, "<="&$C$49) -> 0 | D57: =SUMIFS(Subcontractors!AN7:AN208, Subcontractors!A7:A208, ">="&$D$48, Subcontractors!A7:A208, "<="&$D$49) -> 1680 | E57: =+Subcontractors!$AN$210 -> 1680 | F57: 1 | G57: =+C57*$F57 -> 0 | H57: =+D57*$F57 -> 1680 | I57: =SUM(G57:H57) -> 1680 | J57: =+(E57*F57)-I57 -> 0
A58: Total relevant net expenditure | B58: =SUM(B49:B57) -> -6936 | C58: =SUM(C50:C57) -> 43410.236 | D58: =SUM(D50:D57) -> 115551.02 | E58: =SUM(E50:E57) -> 152025.26 | G58: =SUM(G50:G57) -> 43410.236 | H58: =SUM(H50:H57) -> 115551.02 | I58: =SUM(I50:I57) -> 158961.26 | J58: =SUM(J49:J57) -> -6936
A60: RDEC income:
A61: =A23 -> Jan-24 to Mar-24 | E61: =+E23 -> 3 | F61: 0.13 | G61: =+G58*F61 -> 5643.3306 | H61: 0 | I61: =SUM(G61:H61) -> 5643.3306
A62: =A24 -> Apr-24 to Dec-24 | E62: =+E24 -> 9 | F62: 0.2 | G62: 0 | H62: =+H58*F62 -> 23110.204 | I62: =SUM(G62:H62) -> 23110.204
A63: Total | E63: =SUM(E61:E62) -> 12 | G63: =G61+G62 -> 5643.3306 | H63: =H61+H62 -> 23110.204 | I63: =I61+I62 -> 28753.535
A65: RDEC restrictions:
A66: Step 1
A67: CT profit / (loss) before credit | G67: =G28 -> -21250 | H67: =H28 -> -63750 | I67: =I28 -> -85000
A68: CT due | G68: =IF(G67>0, G67*F74, 0) -> 0 | H68: =IF(H67>0, H67*F75, 0) -> 0 | I68: =SUM(G68:H68) -> 0 | J68: TBC
A69: RDEC amount remaining | G69: =G63-G68 -> 5643.3306 | H69: =H63-H68 -> 23110.204 | I69: =I63-I68 -> 28753.535
A71: Step 2
A72: Amount remaining from Step 1 | G72: =G69 -> 5643.3306 | H72: =H69 -> 23110.204 | I72: =I69 -> 28753.535 | J72: A
A73: Less potential CT on the credit:
A74: =A23 -> Jan-24 to Mar-24 | F74: 0.19 | G74: =+G63*F74 -> 1072.2328 | H74: 0 | I74: =SUM(G74:H74) -> 1072.2328
A75: =A24 -> Apr-24 to Dec-24 | F75: 0.19 | G75: 0 | H75: =+H63*F75 -> 4390.9389 | I75: =SUM(G75:H75) -> 4390.9389
A76: Net RDEC | G76: =G72-SUM(G74:G75) -> 4571.0978 | H76: =H72-SUM(H74:H75) -> 18719.266 | I76: =I72-SUM(I74:I75) -> 23290.363 | J76: B
A77: C/fwd | G77: =IF(G76<G72,G76,G72) -> 4571.0978 | H77: =IF(H76<H72,H76,H72) -> 18719.266 | I77: =IF(I76<I72,I76,I72) -> 23290.363 | J77: Lower of A or B
A79: Step 3
A80: B/fwd from Step 2 | G80: =G77 -> 4571.0978 | H80: =H77 -> 18719.266 | I80: =SUM(G80:H80) -> 23290.363 | J80: C
A81: PAYE/NI liability on R&D workers | G81: =I81/E63*E61 -> 12568.045 | H81: =I81/E63*E62 -> 37704.134 | I81: =+Staff!AN923 -> 50272.179 | J81: D
A82: C/fwd | G82: =IF(G81<G80,G81,G80) -> 4571.0978 | H82: =IF(H81<H80,H81,H80) -> 18719.266 | I82: =IF(I81<I80,I81,I80) -> 23290.363 | J82: Lower of C or D
A84: Step 4
A85: B/fwd from Step 3 | G85: =G82 -> 4571.0978 | H85: =H82 -> 18719.266 | I85: =SUM(G85:H85) -> 23290.363
A86: Other period CT liability | G86: =+I86/$E$63*$E$61 -> 0 | H86: =+I86/$E$63*$E$62 -> 0 | I86: 0 | J86: TBC
A87: C/fwd | G87: =G85-G86 -> 4571.0978 | H87: =H85-H86 -> 18719.266 | I87: =I85-I86 -> 23290.363
A89: Step 5
A90: B/fwd from Step 4 | G90: =G87 -> 4571.0978 | H90: =H87 -> 18719.266 | I90: =SUM(G90:H90) -> 23290.363
A91: CT liabilities of the group | G91: =+I91/$E$63*$E$61 -> 0 | H91: =+I91/$E$63*$E$62 -> 0 | I91: 0 | J91: TBC
A92: C/fwd | G92: =G90-G91 -> 4571.0978 | H92: =H90-H91 -> 18719.266 | I92: =I90-I91 -> 23290.363
A94: Step 6
A95: B/fwd from Step 5 | G95: =G92 -> 4571.0978 | H95: =H92 -> 18719.266 | I95: =SUM(G95:H95) -> 23290.363
A96: Any HMRC liability | G96: =+I96/$E$63*$E$61 -> 0 | H96: =+I96/$E$63*$E$62 -> 0 | I96: 0 | J96: TBC
A97: C/fwd | G97: =G95-G96 -> 4571.0978 | H97: =H95-H96 -> 18719.266 | I97: =I95-I96 -> 23290.363
A99: Step 7
A100: Payable to company | G100: =G97 -> 4571.0978 | H100: =H97 -> 18719.266 | I100: =I97 -> 23290.363
A103: RDEC Summary:
A104: Tax withheld available to set off against future liability b/fwd | G104: 0 | H104: 0 | I104: 0 | J104: TBC
A105: Tax withheld available to set off against future liability (Step 2) | G105: =+G74+G75 -> 1072.2328 | H105: =+H74+H75 -> 4390.9389 | I105: =SUM(G105:H105) -> 5463.1717
A106: PAYE capped credit b/fwd | G106: 0 | H106: 0 | I106: 0 | J106: TBC
A107: PAYE capped credit c/fwd (Step 3) | G107: =IF(G81<G80,G80-G81,0) -> 0 | H107: =IF(H81<H80,H80-H81,0) -> 0 | I107: =IF(I81<I80,I80-I81,0) -> 0
A108: Company CT liability of other accounting period (Step 4) | G108: =G86 -> 0 | H108: =H86 -> 0 | I108: =I86 -> 0
A109: Paid to company (Step 7) | G109: =G100 -> 4571.0978 | H109: =H100 -> 18719.266 | I109: =I100 -> 23290.363
A110: RDEC total c/fwd | G110: =+G104+G105+G106+G107-G108 -> 1072.2328 | H110: =+H104+H105+H106+H107-H108 -> 4390.9389 | I110: =+I104+I105+I106+I107-I108 -> 5463.1717
A113: CT600 Summary
A114: Box 530 R&D tax credit | I114: =I109+I106+I68+I42 -> 143291.01
A115: Box 650 / 655 - SME or Large Company | I115: SME | J115: TBC
A116: Box 660 R&D enhanced expenditure | I116: =I20+I25+I58 -> 1657735.3
A117: Box 875 Payable R&D tax credit | I117: =I114 -> 143291.01
A119: Limit applicable from 1 April 2021:
A120: PAYE / NIC | G120: =(SUMIFS(Staff!F904:F915, Staff!D904:D915, ">="&$C$48, Staff!D904:D915, "<="&$C$49))+(SUMIFS(Staff!G904:G915, Staff!D904:D915, ">="&$C$48, Staff!D904:D915, "<="&$C$49))+(SUMIFS(Staff!H904:H915, Staff!D904:D915, ">="&$C$48, Staff!D904:D915, "<="&$C$49)) -> 72811.38 | H120: =(SUMIFS(Staff!F904:F915, Staff!D904:D915, ">="&$D$48, Staff!D904:D915, "<="&$D$49))+(SUMIFS(Staff!G904:G915, Staff!D904:D915, ">="&$D$48, Staff!D904:D915, "<="&$D$49))+(SUMIFS(Staff!H904:H915, Staff!D904:D915, ">="&$D$48, Staff!D904:D915, "<="&$D$49)) -> 217451.45 | I120: =+Staff!F916+Staff!G916+Staff!H921 -> 290262.83
A121: Threshold | G121: =I121/E63*E61 -> 5000 | H121: =I121/E63*E62 -> 15000 | I121: 20000
A122: Limit for R&D Tax Credits (Limit is £20,000 plus 3 x PAYE/NI) | G122: =+G121+(G120*3) -> 223434.14 | H122: =+H121+(H120*3) -> 667354.35 | I122: =+I121+(I120*3) -> 890788.49

Sheet Staff
A1: Staff Costs
L2: CLIENT INPUT | O2: CLIENT INPUT | AB2: DIRECT STAFF COSTS | AR2: INDIRECT STAFF COSTS | BJ2: ENGINEERS (Y / N)
B3: Name | C3: Position / Job Title | D3: Month | E3: Gross pay | F3: PAYE | G3: Employee's NI | H3: Employer's NI | I3: Employers Pension Contribution | J3: Total | L3: Direct % | M3: Indirect % | O3: =IF(Summary!$B$15>0,Summary!$B$15,"") -> Automated Document Intelligence Platform | P3: =IF(Summary!$B$16>0,Summary!$B$16,"") -> Real-Time Anomaly Detection Engine | Q3: =IF(Summary!$B$17>0,Summary!$B$17,"") -> Natural Language Query Interface | R3: =IF(Summary!$B$18>0,Summary!$B$18,"") -> Predictive Maintenance ML Pipeline | S3: =IF(Summary!$B$19>0,Summary!$B$19,"") -> Privacy-Preserving Data Linkage | T3: =IF(Summary!$B$20>0,Summary!$B$20,"") | U3: =IF(Summary!$B$21>0,Summary!$B$21,"") | V3: =IF(Summary!$B$22>0,Summary!$B$22,"") | W3: =IF(Summary!$B$23>0,Summary!$B$23,"") | X3: =IF(Summary!$B$24>0,Summary!$B$24,"") | Y3: =IF(Summary!$B$25>0,Summary!$B$25,"") | Z3: =IF(Summary!$B$26>0,Summary!$B$26,"") | AB3: =IF(Summary!$B$15>0,Summary!$B$15,"") -> Automated Document Intelligence Platform | AC3: =IF(Summary!$B$16>0,Summary!$B$16,"") -> Real-Time Anomaly Detection Engine | AD3: =IF(Summary!$B$17>0,Summary!$B$17,"") -> Natural Language Query Interface | AE3: =IF(Summary!$B$18>0,Summary!$B$18,"") -> Predictive Maintenance ML Pipeline | AF3: =IF(Summary!$B$19>0,Summary!$B$19,"") -> Privacy-Preserving Data Linkage | AG3: =IF(Summary!$B$20>0,Summary!$B$20,"") | AH3: =IF(Summary!$B$21>0,Summary!$B$21,"") | AI3: =IF(Summary!$B$22>0,Summary!$B$22,"") | AJ3: =IF(Summary!$B$23>0,Summary!$B$23,"") | AK3: =IF(Summary!$B$24>0,Summary!$B$24,"") | AL3: =IF(Summary!$B$25>0,Summary!$B$25,"") | AM3: =IF(Summary!$B$26>0,Summary!$B$26,"") | AN3: RDEC | AO3: SME | AP3: De Minimis | AR3: =IF(Summary!$B$15>0,Summary!$B$15,"") -> Automated Document Intelligence Platform | AS3: =IF(Summary!$B$16>0,Summary!$B$16,"") -> Real-Time Anomaly Detection Engine | AT3: =IF(Summary!$B$17>0,Summary!$B$17,"") -> Natural Language Query Interface | AU3: =IF(Summary!$B$18>0,Summary!$B$18,"") -> Predictive Maintenance ML Pipeline | AV3: =IF(Summary!$B$19>0,Summary!$B$19,"") -> Privacy-Preserving Data Linkage | AW3: =IF(Summary!$B$20>0,Summary!$B$20,"") | AX3: =IF(Summary!$B$21>0,Summary!$B$21,"") | AY3: =IF(Summary!$B$22>0,Summary!$B$22,"") | AZ3: =IF(Summary!$B$23>0,Summary!$B$23,"") | BA3: =IF(Summary!$B$24>0,Summary!$B$24,"") | BB3: =IF(Summary!$B$25>0,Summary!$B$25,"") | BC3: =IF(Summary!$B$26>0,Summary!$B$26,"") | BD3: RDEC | BE3: SME | BF3: De Minimis | BH3: Check | BJ3: Job Title | BK3: Engineer Y / N | BL3: Cost | BM3: RDEC | BN3: SME
O4: =IF(ISBLANK(Summary!$C$15),"", IF(Summary!$C$15="No", "SME", IF(AND(Summary!$C$15="Yes", Summary!$D$15="Yes"), "De Minimis", "RDEC"))) -> SME | P4: =IF(ISBLANK(Summary!$C$16),"", IF(Summary!$C$16="No", "SME", IF(AND(Summary!$C$16="Yes", Summary!$D$16="Yes"), "De Minimis", "RDEC"))) -> SME | Q4: =IF(ISBLANK(Summary!$C$17),"", IF(Summary!$C$17="No", "SME", IF(AND(Summary!$C$17="Yes", Summary!$D$17="Yes"), "De Minimis", "RDEC"))) -> SME | R4: =IF(ISBLANK(Summary!$C$18),"", IF(Summary!$C$18="No", "SME", IF(AND(Summary!$C$18="Yes", Summary!$D$18="Yes"), "De Minimis", "RDEC"))) -> RDEC | S4: =IF(ISBLANK(Summary!$C$19),"", IF(Summary!$C$19="No", "SME", IF(AND(Summary!$C$19="Yes", Summary!$D$19="Yes"), "De Minimis", "RDEC"))) -> SME | T4: =IF(ISBLANK(Summary!$C$20),"", IF(Summary!$C$20="No", "SME", IF(AND(Summary!$C$20="Yes", Summary!$D$20="Yes"), "De Minimis", "RDEC"))) | U4: =IF(ISBLANK(Summary!$C$21),"", IF(Summary!$C$21="No", "SME", IF(AND(Summary!$C$21="Yes", Summary!$D$21="Yes"), "De Minimis", "RDEC"))) | V4: =IF(ISBLANK(Summary!$C$22),"", IF(Summary!$C$22="No", "SME", IF(AND(Summary!$C$22="Yes", Summary!$D$22="Yes"), "De Minimis", "RDEC"))) | W4: =IF(ISBLANK(Summary!$C$23),"", IF(Summary!$C$23="No", "SME", IF(AND(Summary!$C$23="Yes", Summary!$D$23="Yes"), "De Minimis", "RDEC"))) | X4: =IF(ISBLANK(Summary!$C$24),"", IF(Summary!$C$24="No", "SME", IF(AND(Summary!$C$24="Yes", Summary!$D$24="Yes"), "De Minimis", "RDEC"))) | Y4: =IF(ISBLANK(Summary!$C$25),"", IF(Summary!$C$25="No", "SME", IF(AND(Summary!$C$25="Yes", Summary!$D$25="Yes"), "De Minimis", "RDEC"))) | Z4: =IF(ISBLANK(Summary!$C$26),"", IF(Summary!$C$26="No", "SME", IF(AND(Summary!$C$26="Yes", Summary!$D$26="Yes"), "De Minimis", "RDEC"))) | AB4: =IF(ISBLANK(Summary!$C$15),"", IF(Summary!$C$15="No", "SME", IF(AND(Summary!$C$15="Yes", Summary!$D$15="Yes"), "De Minimis", "RDEC"))) -> SME | AC4: =IF(ISBLANK(Summary!$C$16),"", IF(Summary!$C$16="No", "SME", IF(AND(Summary!$C$16="Yes", Summary!$D$16="Yes"), "De Minimis", "RDEC"))) -> SME | AD4: =IF(ISBLANK(Summary!$C$17),"", IF(Summary!$C$17="No", "SME", IF(AND(Summary!$C$17="Yes", Summary!$D$17="Yes"), "De Minimis", "RDEC"))) -> SME | AE4: =IF(ISBLANK(Summary!$C$18),"", IF(Summary!$C$18="No", "SME", IF(AND(Summary!$C$18="Yes", Summary!$D$18="Yes"), "De Minimis", "RDEC"))) -> RDEC | AF4: =IF(ISBLANK(Summary!$C$19),"", IF(Summary!$C$19="No", "SME", IF(AND(Summary!$C$19="Yes", Summary!$D$19="Yes"), "De Minimis", "RDEC"))) -> SME | AG4: =IF(ISBLANK(Summary!$C$20),"", IF(Summary!$C$20="No", "SME", IF(AND(Summary!$C$20="Yes", Summary!$D$20="Yes"), "De Minimis", "RDEC"))) | AH4: =IF(ISBLANK(Summary!$C$21),"", IF(Summary!$C$21="No", "SME", IF(AND(Summary!$C$21="Yes", Summary!$D$21="Yes"), "De Minimis", "RDEC"))) | AI4: =IF(ISBLANK(Summary!$C$22),"", IF(Summary!$C$22="No", "SME", IF(AND(Summary!$C$22="Yes", Summary!$D$22="Yes"), "De Minimis", "RDEC"))) | AJ4: =IF(ISBLANK(Summary!$C$23),"", IF(Summary!$C$23="No", "SME", IF(AND(Summary!$C$23="Yes", Summary!$D$23="Yes"), "De Minimis", "RDEC"))) | AK4: =IF(ISBLANK(Summary!$C$24),"", IF(Summary!$C$24="No", "SME", IF(AND(Summary!$C$24="Yes", Summary!$D$24="Yes"), "De Minimis", "RDEC"))) | AL4: =IF(ISBLANK(Summary!$C$25),"", IF(Summary!$C$25="No", "SME", IF(AND(Summary!$C$25="Yes", Summary!$D$25="Yes"), "De Minimis", "RDEC"))) | AM4: =IF(ISBLANK(Summary!$C$26),"", IF(Summary!$C$26="No", "SME", IF(AND(Summary!$C$26="Yes", Summary!$D$26="Yes"), "De Minimis", "RDEC"))) | AR4: =IF(ISBLANK(Summary!$C$15),"", IF(Summary!$C$15="No", "SME", IF(AND(Summary!$C$15="Yes", Summary!$D$15="Yes"), "De Minimis", "RDEC"))) -> SME | AS4: =IF(ISBLANK(Summary!$C$16),"", IF(Summary!$C$16="No", "SME", IF(AND(Summary!$C$16="Yes", Summary!$D$16="Yes"), "De Minimis", "RDEC"))) -> SME | AT4: =IF(ISBLANK(Summary!$C$17),"", IF(Summary!$C$17="No", "SME", IF(AND(Summary!$C$17="Yes", Summary!$D$17="Yes"), "De Minimis", "RDEC"))) -> SME | AU4: =IF(ISBLANK(Summary!$C$18),"", IF(Summary!$C$18="No", "SME", IF(AND(Summary!$C$18="Yes", Summary!$D$18="Yes"), "De Minimis", "RDEC"))) -> RDEC | AV4: =IF(ISBLANK(Summary!$C$19),"", IF(Summary!$C$19="No", "SME", IF(AND(Summary!$C$19="Yes", Summary!$D$19="Yes"), "De Minimis", "RDEC"))) -> SME | AW4: =IF(ISBLANK(Summary!$C$20),"", IF(Summary!$C$20="No", "SME", IF(AND(Summary!$C$20="Yes", Summary!$D$20="Yes"), "De Minimis", "RDEC"))) | AX4: =IF(ISBLANK(Summary!$C$21),"", IF(Summary!$C$21="No", "SME", IF(AND(Summary!$C$21="Yes", Summary!$D$21="Yes"), "De Minimis", "RDEC"))) | AY4: =IF(ISBLANK(Summary!$C$22),"", IF(Summary!$C$22="No", "SME", IF(AND(Summary!$C$22="Yes", Summary!$D$22="Yes"), "De Minimis", "RDEC"))) | AZ4: =IF(ISBLANK(Summary!$C$23),"", IF(Summary!$C$23="No", "SME", IF(AND(Summary!$C$23="Yes", Summary!$D$23="Yes"), "De Minimis", "RDEC"))) | BA4: =IF(ISBLANK(Summary!$C$24),"", IF(Summary!$C$24="No", "SME", IF(AND(Summary!$C$24="Yes", Summary!$D$24="Yes"), "De Minimis", "RDEC"))) | BB4: =IF(ISBLANK(Summary!$C$25),"", IF(Summary!$C$25="No", "SME", IF(AND(Summary!$C$25="Yes", Summary!$D$25="Yes"), "De Minimis", "RDEC"))) | BC4: =IF(ISBLANK(Summary!$C$26),"", IF(Summary!$C$26="No", "SME", IF(AND(Summary!$C$26="Yes", Summary!$D$26="Yes"), "De Minimis", "RDEC")))
O5: R&D % | P5: R&D % | Q5: R&D % | R5: R&D % | S5: R&D % | T5: R&D % | U5: R&D % | V5: R&D % | W5: R&D % | X5: R&D % | Y5: R&D % | Z5: R&D % | AB5: R&D £ | AC5: R&D £ | AD5: R&D £ | AE5: R&D £ | AF5: R&D £ | AG5: R&D £ | AH5: R&D £ | AI5: R&D £ | AJ5: R&D £ | AK5: R&D £ | AL5: R&D £ | AM5: R&D £ | AN5: R&D £ | AO5: R&D £ | AP5: R&D £ | AR5: R&D £ | AS5: R&D £ | AT5: R&D £ | AU5: R&D £ | AV5: R&D £ | AW5: R&D £ | AX5: R&D £ | AY5: R&D £ | AZ5: R&D £ | BA5: R&D £ | BB5: R&D £ | BC5: R&D £ | BD5: R&D £ | BE5: R&D £ | BF5: R&D £ | BH5: %
A6: 1 | B6: James Harrison | C6: Chief Technology Officer
D8: =+Summary!B8 -> 45292 | E8: 8025.74 | F8: 2648.49 | G8: 581.39 | H8: 1002.9 | I8: 401.29 | J8: =E8+H8+I8 -> 9429.93 | L8: 0.6 | M8: =1-L8 -> 0.4 | O8: 0.3 | P8: 0.25 | Q8: 0.15 | R8: 0.2 | S8: 0.1 | AB8: =IFERROR(($J8*O8)*$L8, "") -> 1697.3874 | AC8: =IFERROR(($J8*P8)*$L8, "") -> 1414.4895 | AD8: =IFERROR(($J8*Q8)*$L8, "") -> 848.6937 | AE8: =IFERROR(($J8*R8)*$L8, "") -> 1131.5916 | AF8: =IFERROR(($J8*S8)*$L8, "") -> 565.7958 | AG8: =IFERROR(($J8*T8)*$L8, "") -> 0 | AH8: =IFERROR(($J8*U8)*$L8, "") -> 0 | AI8: =IFERROR(($J8*V8)*$L8, "") -> 0 | ... AM8: =IFERROR(($J8*Z8)*$L8, "") -> 0 | AN8: =IFERROR(SUMIF($AB$4:$AM$4, "RDEC", AB8:AM8), "") -> 1131.5916 | AO8: =IFERROR(SUMIF($AB$4:$AM$4, "SME", AB8:AM8), "") -> 4526.3664 | AP8: =IFERROR(SUMIF($AB$4:$AM$4, "De Minimis", AB8:AM8), "") -> 0 | AR8: =IFERROR(($J8*O8)*$M8, "") -> 1131.5916 | AS8: =IFERROR(($J8*P8)*$M8, "") -> 942.993 | AT8: =IFERROR(($J8*Q8)*$M8, "") -> 565.7958 | AU8: =IFERROR(($J8*R8)*$M8, "") -> 754.3944 | AV8: =IFERROR(($J8*S8)*$M8, "") -> 377.1972 | AW8: =IFERROR(($J8*T8)*$M8, "") -> 0 | AX8: =IFERROR(($J8*U8)*$M8, "") -> 0 | AY8: =IFERROR(($J8*V8)*$M8, "") -> 0 | ... BC8: =IFERROR(($J8*Z8)*$M8, "") -> 0 | BD8: =IFERROR(SUMIF($AB$4:$AM$4, "RDEC", AR8:BC8), "") -> 754.3944 | BE8: =IFERROR(SUMIF($AB$4:$AM$4, "SME", AR8:BC8), "") -> 3017.5776 | BF8: =IFERROR(SUMIF($AB$4:$AM$4, "De Minimis", AR8:BC8), "") -> 0 | BH8: =IF((SUM(O8:Z8)>1),"ERROR","")
D9: =+EDATE(D8, 1) -> 45323 | E9: 7800.89 | F9: 2574.29 | G9: 563.4 | H9: 971.87 | I9: 390.04 | J9: =E9+H9+I9 -> 9162.8 | L9: 0.6 | M9: =1-L9 -> 0.4 | O9: 0.3 | P9: 0.25 | Q9: 0.15 | R9: 0.2 | S9: 0.1 | AB9: =IFERROR(($J9*O9)*$L9, "") -> 1649.304 | AC9: =IFERROR(($J9*P9)*$L9, "") -> 1374.42 | AD9: =IFERROR(($J9*Q9)*$L9, "") -> 824.652 | AE9: =IFERROR(($J9*R9)*$L9, "") -> 1099.536 | AF9: =IFERROR(($J9*S9)*$L9, "") -> 549.768 | AG9: =IFERROR(($J9*T9)*$L9, "") -> 0 | AH9: =IFERROR(($J9*U9)*$L9, "") -> 0 | AI9: =IFERROR(($J9*V9)*$L9, "") -> 0 | ... AM9: =IFERROR(($J9*Z9)*$L9, "") -> 0 | AN9: =IFERROR(SUMIF($AB$4:$AM$4, "RDEC", AB9:AM9), "") -> 1099.536 | AO9: =IFERROR(SUMIF($AB$4:$AM$4, "SME", AB9:AM9), "") -> 4398.144 | AP9: =IFERROR(SUMIF($AB$4:$AM$4, "De Minimis", AB9:AM9), "") -> 0 | AR9: =IFERROR(($J9*O9)*$M9, "") -> 1099.536 | AS9: =IFERROR(($J9*P9)*$M9, "") -> 916.28 | AT9: =IFERROR(($J9*Q9)*$M9, "") -> 549.768 | AU9: =IFERROR(($J9*R9)*$M9, "") -> 733.024 | AV9: =IFERROR(($J9*S9)*$M9, "") -> 366.512 | AW9: =IFERROR(($J9*T9)*$M9, "") -> 0 | AX9: =IFERROR(($J9*U9)*$M9, "") -> 0 | AY9: =IFERROR(($J9*V9)*$M9, "") -> 0 | ... BC9: =IFERROR(($J9*Z9)*$M9, "") -> 0 | BD9: =IFERROR(SUMIF($AB$4:$AM$4, "RDEC", AR9:BC9), "") -> 733.024 | BE9: =IFERROR(SUMIF($AB$4:$AM$4, "SME", AR9:BC9), "") -> 2932.096 | BF9: =IFERROR(SUMIF($AB$4:$AM$4, "De Minimis", AR9:BC9), "") -> 0 | BH9: =IF((SUM(O9:Z9)>1),"ERROR","")
D10: =+EDATE(D9, 1) -> 45352 | E10: 8061.08 | F10: 2660.16 | G10: 584.22 | H10: 1007.78 | I10: 403.05 | J10: =E10+H10+I10 -> 9471.91 | L10: 0.6 | M10: =1-L10 -> 0.4 | O10: 0.3 | P10: 0.25 | Q10: 0.15 | R10: 0.2 | S10: 0.1 | AB10: =IFERROR(($J10*O10)*$L10, "") -> 1704.9438 | AC10: =IFERROR(($J10*P10)*$L10, "") -> 1420.7865 | AD10: =IFERROR(($J10*Q10)*$L10, "") -> 852.4719 | AE10: =IFERROR(($J10*R10)*$L10, "") -> 1136.6292 | AF10: =IFERROR(($J10*S10)*$L10, "") -> 568.3146 | AG10: =IFERROR(($J10*T10)*$L10, "") -> 0 | AH10: =IFERROR(($J10*U10)*$L10, "") -> 0 | AI10: =IFERROR(($J10*V10)*$L10, "") -> 0 | ... AM10: =IFERROR(($J10*Z10)*$L10, "") -> 0 | AN10: =IFERROR(SUMIF($AB$4:$AM$4, "RDEC", AB10:AM10), "") -> 1136.6292 | AO10: =IFERROR(SUMIF($AB$4:$AM$4, "SME", AB10:AM10), "") -> 4546.5168 | AP10: =IFERROR(SUMIF($AB$4:$AM$4, "De Minimis", AB10:AM10), "") -> 0 | AR10: =IFERROR(($J10*O10)*$M10, "") -> 1136.6292 | AS10: =IFERROR(($J10*P10)*$M10, "") -> 947.191 | AT10: =IFERROR(($J10*Q10)*$M10, "") -> 568.3146 | AU10: =IFERROR(($J10*R10)*$M10, "") -> 757.7528 | AV10: =IFERROR(($J10*S10)*$M10, "") -> 378.8764 | AW10: =IFERROR(($J10*T10)*$M10, "") -> 0 | AX10: =IFERROR(($J10*U10)*$M10, "") -> 0 | AY10: =IFERROR(($J10*V10)*$M10, "") -> 0 | ... BC10: =IFERROR(($J10*Z10)*$M10, "") -> 0 | BD10: =IFERROR(SUMIF($AB$4:$AM$4, "RDEC", AR10:BC10), "") -> 757.7528 | BE10: =IFERROR(SUMIF($AB$4:$AM$4, "SME", AR10:BC10), "") -> 3031.0112 | BF10: =IFERROR(SUMIF($AB$4:$AM$4, "De Minimis", AR10:BC10), "") -> 0 | BH10: =IF((SUM(O10:Z10)>1),"ERROR","")
D11: =+EDATE(D10, 1) -> 45383 | E11: 7833.69 | F11: 2585.12 | G11: 566.03 | H11: 976.4 | I11: 391.68 | J11: =E11+H11+I11 -> 9201.77 | L11: 0.6 | M11: =1-L11 -> 0.4 | O11: 0.3 | P11: 0.25 | Q11: 0.15 | R11: 0.2 | S11: 0.1 | AB11: =IFERROR(($J11*O11)*$L11, "") -> 1656.3186 | AC11: =IFERROR(($J11*P11)*$L11, "") -> 1380.2655 | AD11: =IFERROR(($J11*Q11)*$L11, "") -> 828.1593 | AE11: =IFERROR(($J11*R11)*$L11, "") -> 1104.2124 | AF11: =IFERROR(($J11*S11)*$L11, "") -> 552.1062 | AG11: =IFERROR(($J11*T11)*$L11, "") -> 0 | AH11: =IFERROR(($J11*U11)*$L11, "") -> 0 | AI11: =IFERROR(($J11*V11)*$L11, "") -> 0 | ... AM11: =IFERROR(($J11*Z11)*$L11, "") -> 0 | AN11: =IFERROR(SUMIF($AB$4:$AM$4, "RDEC", AB11:AM11), "") -> 1104.2124 | AO11: =IFERROR(SUMIF($AB$4:$AM$4, "SME", AB11:AM11), "") -> 4416.8496 | AP11: =IFERROR(SUMIF($AB$4:$AM$4, "De Minimis", AB11:AM11), "") -> 0 | AR11: =IFERROR(($J11*O11)*$M11, "") -> 1104.2124 | AS11: =IFERROR(($J11*P11)*$M11, "") -> 920.177 | AT11: =IFERROR(($J11*Q11)*$M11, "") -> 552.1062 | AU11: =IFERROR(($J11*R11)*$M11, "") -> 736.1416 | AV11: =IFERROR(($J11*S11)*$M11, "") -> 368.0708 | AW11: =IFERROR(($J11*T11)*$M11, "") -> 0 | AX11: =IFERROR(($J11*U11)*$M11, "") -> 0 | AY11: =IFERROR(($J11*V11)*$M11, "") -> 0 | ... BC11: =IFERROR(($J11*Z11)*$M11, "") -> 0 | BD11: =IFERROR(SUMIF($AB$4:$AM$4, "RDEC", AR11:BC11), "") -> 736.1416 | BE11: =IFERROR(SUMIF($AB$4:$AM$4, "SME", AR11:BC11), "") -> 2944.5664 | BF11: =IFERROR(SUMIF($AB$4:$AM$4, "De Minimis", AR11:BC11), "") -> 0 | BH11: =IF((SUM(O11:Z11)>1),"ERROR","")
D12: =+EDATE(D11, 1) -> 45413 | E12: 7833.09 | F12: 2584.92 | G12: 565.98 | H12: 976.32 | I12: 391.65 | J12: =E12+H12+I12 -> 9201.06 | L12: 0.6 | M12: =1-L12 -> 0.4 | O12: 0.3 | P12: 0.25 | Q12: 0.15 | R12: 0.2 | S12: 0.1 | AB12: =IFERROR(($J12*O12)*$L12, "") -> 1656.1908 | AC12: =IFERROR(($J12*P12)*$L12, "") -> 1380.159 | AD12: =IFERROR(($J12*Q12)*$L12, "") -> 828.0954 | AE12: =IFERROR(($J12*R12)*$L12, "") -> 1104.1272 | AF12: =IFERROR(($J12*S12)*$L12, "") -> 552.0636 | AG12: =IFERROR(($J12*T12)*$L12, "") -> 0 | AH12: =IFERROR(($J12*U12)*$L12, "") -> 0 | AI12: =IFERROR(($J12*V12)*$L12, "") -> 0 | ... AM12: =IFERROR(($J12*Z12)*$L12, "") -> 0 | AN12: =IFERROR(SUMIF($AB$4:$AM$4, "RDEC", AB12:AM12), "") -> 1104.1272 | AO12: =IFERROR(SUMIF($AB$4:$AM$4, "SME", AB12:AM12), "") -> 4416.5088 | AP12: =IFERROR(SUMIF($AB$4:$AM$4, "De Minimis", AB12:AM12), "") -> 0 | AR12: =IFERROR(($J12*O12)*$M12, "") -> 1104.1272 | AS12: =IFERROR(($J12*P12)*$M12, "") -> 920.106 | AT12: =IFERROR(($J12*Q12)*$M12, "") -> 552.0636 | AU12: =IFERROR(($J12*R12)*$M12, "") -> 736.0848 | AV12: =IFERROR(($J12*S12)*$M12, "") -> 368.0424 | AW12: =IFERROR(($J12*T12)*$M12, "") -> 0 | AX12: =IFERROR(($J12*U12)*$M12, "") -> 0 | AY12: =IFERROR(($J12*V12)*$M12, "") -> 0 | ... BC12: =IFERROR(($J12*Z12)*$M12, "") -> 0 | BD12: =IFERROR(SUMIF($AB$4:$AM$4, "RDEC", AR12:BC12), "") -> 736.0848 | BE12: =IFERROR(SUMIF($AB$4:$AM$4, "SME", AR12:BC12), "") -> 2944.3392 | BF12: =IFERROR(SUMIF($AB$4:$AM$4, "De Minimis", AR12:BC12), "") -> 0 | BH12: =IF((SUM(O12:Z12)>1),"ERROR","")
D13: =+EDATE(D12, 1) -> 45444 | E13: 7955.59 | F13: 2625.34 | G13: 575.78 | H13: 993.22 | I13: 397.78 | J13: =E13+H13+I13 -> 9346.59 | L13: 0.6 | M13: =1-L13 -> 0.4 | O13: 0.3 | P13: 0.25 | Q13: 0.15 | R13: 0.2 | S13: 0.1 | AB13: =IFERROR(($J13*O13)*$L13, "") -> 1682.3862 | AC13: =IFERROR(($J13*P13)*$L13, "") -> 1401.9885 | AD13: =IFERROR(($J13*Q13)*$L13, "") -> 841.1931 | AE13: =IFERROR(($J13*R13)*$L13, "") -> 1121.5908 | AF13: =IFERROR(($J13*S13)*$L13, "") -> 560.7954 | AG13: =IFERROR(($J13*T13)*$L13, "") -> 0 | AH13: =IFERROR(($J13*U13)*$L13, "") -> 0 | AI13: =IFERROR(($J13*V13)*$L13, "") -> 0 | ... AM13: =IFERROR(($J13*Z13)*$L13, "") -> 0 | AN13: =IFERROR(SUMIF($AB$4:$AM$4, "RDEC", AB13:AM13), "") -> 1121.5908 | AO13: =IFERROR(SUMIF($AB$4:$AM$4, "SME", AB13:AM13), "") -> 4486.3632 | AP13: =IFERROR(SUMIF($AB$4:$AM$4, "De Minimis", AB13:AM13), "") -> 0 | AR13: =IFERROR(($J13*O13)*$M13, "") -> 1121.5908 | AS13: =IFERROR(($J13*P13)*$M13, "") -> 934.659 | AT13: =IFERROR(($J13*Q13)*$M13, "") -> 560.7954 | AU13: =IFERROR(($J13*R13)*$M13, "") -> 747.7272 | AV13: =IFERROR(($J13*S13)*$M13, "") -> 373.8636 | AW13: =IFERROR(($J13*T13)*$M13, "") -> 0 | AX13: =IFERROR(($J13*U13)*$M13, "") -> 0 | AY13: =IFERROR(($J13*V13)*$M13, "") -> 0 | ... BC13: =IFERROR(($J13*Z13)*$M13, "") -> 0 | BD13: =IFERROR(SUMIF($AB$4:$AM$4, "RDEC", AR13:BC13), "") -> 747.7272 | BE13: =IFERROR(SUMIF($AB$4:$AM$4, "SME", AR13:BC13), "") -> 2990.9088 | BF13: =IFERROR(SUMIF($AB$4:$AM$4, "De Minimis", AR13:BC13), "") -> 0 | BH13: =IF((SUM(O13:Z13)>1),"ERROR","")
D14: =+EDATE(D13, 1) -> 45474 | E14: 8009.56 | F14: 2643.15 | G14: 580.1 | H14: 1000.67 | I14: 400.48 | J14: =E14+H14+I14 -> 9410.71 | L14: 0.6 | M14: =1-L14 -> 0.4 | O14: 0.3 | P14: 0.25 | Q14: 0.15 | R14: 0.2 | S14: 0.1 | AB14: =IFERROR(($J14*O14)*$L14, "") -> 1693.9278 | AC14: =IFERROR(($J14*P14)*$L14, "") -> 1411.6065 | AD14: =IFERROR(($J14*Q14)*$L14, "") -> 846.9639 | AE14: =IFERROR(($J14*R14)*$L14, "") -> 1129.2852 | AF14: =IFERROR(($J14*S14)*$L14, "") -> 564.6426 | AG14: =IFERROR(($J14*T14)*$L14, "") -> 0 | AH14: =IFERROR(($J14*U14)*$L14, "") -> 0 | AI14: =IFERROR(($J14*V14)*$L14, "") -> 0 | ... AM14: =IFERROR(($J14*Z14)*$L14, "") -> 0 | AN14: =IFERROR(SUMIF($AB$4:$AM$4, "RDEC", AB14:AM14), "") -> 1129.2852 | AO14: =IFERROR(SUMIF($AB$4:$AM$4, "SME", AB14:AM14), "") -> 4517.1408 | AP14: =IFERROR(SUMIF($AB$4:$AM$4, "De Minimis", AB14:AM14), "") -> 0 | AR14: =IFERROR(($J14*O14)*$M14, "") -> 1129.2852 | AS14: =IFERROR(($J14*P14)*$M14, "") -> 941.071 | AT14: =IFERROR(($J14*Q14)*$M14, "") -> 564.6426 | AU14: =IFERROR(($J14*R14)*$M14, "") -> 752.8568 | AV14: =IFERROR(($J14*S14)*$M14, "") -> 376.4284 | AW14: =IFERROR(($J14*T14)*$M14, "") -> 0 | AX14: =IFERROR(($J14*U14)*$M14, "") -> 0 | AY14: =IFERROR(($J14*V14)*$M14, "") -> 0 | ... BC14: =IFERROR(($J14*Z14)*$M14, "") -> 0 | BD14: =IFERROR(SUMIF($AB$4:$AM$4, "RDEC", AR14:BC14), "") -> 752.8568 | BE14: =IFERROR(SUMIF($AB$4:$AM$4, "SME", AR14:BC14), "") -> 3011.4272 | BF14: =IFERROR(SUMIF($AB$4:$AM$4, "De Minimis", AR14:BC14), "") -> 0 | BH14: =IF((SUM(O14:Z14)>1),"ERROR","")
D15: =+EDATE(D14, 1) -> 45505 | E15: 7860.88 | F15: 2594.09 | G15: 568.2 | H15: 980.15 | I15: 393.04 | J15: =E15+H15+I15 -> 9234.07 | L15: 0.6 | M15: =1-L15 -> 0.4 | O15: 0.3 | P15: 0.25 | Q15: 0.15 | R15: 0.2 | S15: 0.1 | AB15: =IFERROR(($J15*O15)*$L15, "") -> 1662.1326 | AC15: =IFERROR(($J15*P15)*$L15, "") -> 1385.1105 | AD15: =IFERROR(($J15*Q15)*$L15, "") -> 831.0663 | AE15: =IFERROR(($J15*R15)*$L15, "") -> 1108.0884 | AF15: =IFERROR(($J15*S15)*$L15, "") -> 554.0442 | AG15: =IFERROR(($J15*T15)*$L15, "") -> 0 | AH15: =IFERROR(($J15*U15)*$L15, "") -> 0 | AI15: =IFERROR(($J15*V15)*$L15, "") -> 0 | ... AM15: =IFERROR(($J15*Z15)*$L15, "") -> 0 | AN15: =IFERROR(SUMIF($AB$4:$AM$4, "RDEC", AB15:AM15), "") -> 1108.0884 | AO15: =IFERROR(SUMIF($AB$4:$AM$4, "SME", AB15:AM15), "") -> 4432.3536 | AP15: =IFERROR(SUMIF($AB$4:$AM$4, "De Minimis", AB15:AM15), "") -> 0 | AR15: =IFERROR(($J15*O15)*$M15, "") -> 1108.0884 | AS15: =IFERROR(($J15*P15)*$M15, "") -> 923.407 | AT15: =IFERROR(($J15*Q15)*$M15, "") -> 554.0442 | AU15: =IFERROR(($J15*R15)*$M15, "") -> 738.7256 | AV15: =IFERROR(($J15*S15)*$M15, "") -> 369.3628 | AW15: =IFERROR(($J15*T15)*$M15, "") -> 0 | AX15: =IFERROR(($J15*U15)*$M15, "") -> 0 | AY15: =IFERROR(($J15*V15)*$M15, "") -> 0 | ... BC15: =IFERROR(($J15*Z15)*$M15, "") -> 0 | BD15: =IFERROR(SUMIF($AB$4:$AM$4, "RDEC", AR15:BC15), "") -> 738.7256 | BE15: =IFERROR(SUMIF($AB$4:$AM$4, "SME", AR15:BC15), "") -> 2954.9024 | BF15: =IFERROR(SUMIF($AB$4:$AM$4, "De Minimis", AR15:BC15), "") -> 0 | BH15: =IF((SUM(O15:Z15)>1),"ERROR","")
D16: =+EDATE(D15, 1) -> 45536 | E16: 7830.13 | F16: 2583.94 | G16: 565.74 | H16: 975.91 | I16: 391.51 | J16: =E16+H16+I16 -> 9197.55 | L16: 0.6 | M16: =1-L16 -> 0.4 | O16: 0.3 | P16: 0.25 | Q16: 0.15 | R16: 0.2 | S16: 0.1 | AB16: =IFERROR(($J16*O16)*$L16, "") -> 1655.559 | AC16: =IFERROR(($J16*P16)*$L16, "") -> 1379.6325 | AD16: =IFERROR(($J16*Q16)*$L16, "") -> 827.7795 | AE16: =IFERROR(($J16*R16)*$L16, "") -> 1103.706 | AF16: =IFERROR(($J16*S16)*$L16, "") -> 551.853 | AG16: =IFERROR(($J16*T16)*$L16, "") -> 0 | AH16: =IFERROR(($J16*U16)*$L16, "") -> 0 | AI16: =IFERROR(($J16*V16)*$L16, "") -> 0 | ... AM16: =IFERROR(($J16*Z16)*$L16, "") -> 0 | AN16: =IFERROR(SUMIF($AB$4:$AM$4, "RDEC", AB16:AM16), "") -> 1103.706 | AO16: =IFERROR(SUMIF($AB$4:$AM$4, "SME", AB16:AM16), "") -> 4414.824 | AP16: =IFERROR(SUMIF($AB$4:$AM$4, "De Minimis", AB16:AM16), "") -> 0 | AR16: =IFERROR(($J16*O16)*$M16, "") -> 1103.706 | AS16: =IFERROR(($J16*P16)*$M16, "") -> 919.755 | AT16: =IFERROR(($J16*Q16)*$M16, "") -> 551.853 | AU16: =IFERROR(($J16*R16)*$M16, "") -> 735.804 | AV16: =IFERROR(($J16*S16)*$M16, "") -> 367.902 | AW16: =IFERROR(($J16*T16)*$M16, "") -> 0 | AX16: =IFERROR(($J16*U16)*$M16, "") -> 0 | AY16: =IFERROR(($J16*V16)*$M16, "") -> 0 | ... BC16: =IFERROR(($J16*Z16)*$M16, "") -> 0 | BD16: =IFERROR(SUMIF($AB$4:$AM$4, "RDEC", AR16:BC16), "") -> 735.804 | BE16: =IFERROR(SUMIF($AB$4:$AM$4, "SME", AR16:BC16), "") -> 2943.216 | BF16: =IFERROR(SUMIF($AB$4:$AM$4, "De Minimis", AR16:BC16), "") -> 0 | BH16: =IF((SUM(O16:Z16)>1),"ERROR","")
D17: =+EDATE(D16, 1) -> 45566 | E17: 7904.96 | F17: 2608.64 | G17: 571.73 | H17: 986.23 | I17: 395.25 | J17: =E17+H17+I17 -> 9286.44 | L17: 0.6 | M17: =1-L17 -> 0.4 | O17: 0.3 | P17: 0.25 | Q17: 0.15 | R17: 0.2 | S17: 0.1 | AB17: =IFERROR(($J17*O17)*$L17, "") -> 1671.5592 | AC17: =IFERROR(($J17*P17)*$L17, "") -> 1392.966 | AD17: =IFERROR(($J17*Q17)*$L17, "") -> 835.7796 | AE17: =IFERROR(($J17*R17)*$L17, "") -> 1114.3728 | AF17: =IFERROR(($J17*S17)*$L17, "") -> 557.1864 | AG17: =IFERROR(($J17*T17)*$L17, "") -> 0 | AH17: =IFERROR(($J17*U17)*$L17, "") -> 0 | AI17: =IFERROR(($J17*V17)*$L17, "") -> 0 | ... AM17: =IFERROR(($J17*Z17)*$L17, "") -> 0 | AN17: =IFERROR(SUMIF($AB$4:$AM$4, "RDEC", AB17:AM17), "") -> 1114.3728 | AO17: =IFERROR(SUMIF($AB$4:$AM$4, "SME", AB17:AM17), "") -> 4457.4912 | AP17: =IFERROR(SUMIF($AB$4:$AM$4, "De Minimis", AB17:AM17), "") -> 0 | AR17: =IFERROR(($J17*O17)*$M17, "") -> 1114.3728 | AS17: =IFERROR(($J17*P17)*$M17, "") -> 928.644 | AT17: =IFERROR(($J17*Q17)*$M17, "") -> 557.1864 | AU17: =IFERROR(($J17*R17)*$M17, "") -> 742.9152 | AV17: =IFERROR(($J17*S17)*$M17, "") -> 371.4576 | AW17: =IFERROR(($J17*T17)*$M17, "") -> 0 | AX17: =IFERROR(($J17*U17)*$M17, "") -> 0 | AY17: =IFERROR(($J17*V17)*$M17, "") -> 0 | ... BC17: =IFERROR(($J17*Z17)*$M17, "") -> 0 | BD17: =IFERROR(SUMIF($AB$4:$AM$4, "RDEC", AR17:BC17), "") -> 742.9152 | BE17: =IFERROR(SUMIF($AB$4:$AM$4, "SME", AR17:BC17), "") -> 2971.6608 | BF17: =IFERROR(SUMIF($AB$4:$AM$4, "De Minimis", AR17:BC17), "") -> 0 | BH17: =IF((SUM(O17:Z17)>1),"ERROR","")
D18: =+EDATE(D17, 1) -> 45597 | E18: 7939.28 | F18: 2619.96 | G18: 574.48 | H18: 990.97 | I18: 396.96 | J18: =E18+H18+I18 -> 9327.21 | L18: 0.6 | M18: =1-L18 -> 0.4 | O18: 0.3 | P18: 0.25 | Q18: 0.15 | R18: 0.2 | S18: 0.1 | AB18: =IFERROR(($J18*O18)*$L18, "") -> 1678.8978 | AC18: =IFERROR(($J18*P18)*$L18, "") -> 1399.0815 | AD18: =IFERROR(($J18*Q18)*$L18, "") -> 839.4489 | AE18: =IFERROR(($J18*R18)*$L18, "") -> 1119.2652 | AF18: =IFERROR(($J18*S18)*$L18, "") -> 559.6326 | AG18: =IFERROR(($J18*T18)*$L18, "") -> 0 | AH18: =IFERROR(($J18*U18)*$L18, "") -> 0 | AI18: =IFERROR(($J18*V18)*$L18, "") -> 0 | ... AM18: =IFERROR(($J18*Z18)*$L18, "") -> 0 | AN18: =IFERROR(SUMIF($AB$4:$AM$4, "RDEC", AB18:AM18), "") -> 1119.2652 | AO18: =IFERROR(SUMIF($AB$4:$AM$4, "SME", AB18:AM18), "") -> 4477.0608 | AP18: =IFERROR(SUMIF($AB$4:$AM$4, "De Minimis", AB18:AM18), "") -> 0 | AR18: =IFERROR(($J18*O18)*$M18, "") -> 1119.2652 | AS18: =IFERROR(($J18*P18)*$M18, "") -> 932.721 | AT18: =IFERROR(($J18*Q18)*$M18, "") -> 559.6326 | AU18: =IFERROR(($J18*R18)*$M18, "") -> 746.1768 | AV18: =IFERROR(($J18*S18)*$M18, "") -> 373.0884 | AW18: =IFERROR(($J18*T18)*$M18, "") -> 0 | AX18: =IFERROR(($J18*U18)*$M18, "") -> 0 | AY18: =IFERROR(($J18*V18)*$M18, "") -> 0 | ... BC18: =IFERROR(($J18*Z18)*$M18, "") -> 0 | BD18: =IFERROR(SUMIF($AB$4:$AM$4, "RDEC", AR18:BC18), "") -> 746.1768 | BE18: =IFERROR(SUMIF($AB$4:$AM$4, "SME", AR18:BC18), "") -> 2984.7072 | BF18: =IFERROR(SUMIF($AB$4:$AM$4, "De Minimis", AR18:BC18), "") -> 0 | BH18: =IF((SUM(O18:Z18)>1),"ERROR","")
D19: =+EDATE(D18, 1) -> 45627 | E19: 7901.59 | F19: 2607.52 | G19: 571.46 | H19: 985.77 | I19: 395.08 | J19: =E19+H19+I19 -> 9282.44 | L19: 0.6 | M19: =1-L19 -> 0.4 | O19: 0.3 | P19: 0.25 | Q19: 0.15 | R19: 0.2 | S19: 0.1 | AB19: =IFERROR(($J19*O19)*$L19, "") -> 1670.8392 | AC19: =IFERROR(($J19*P19)*$L19, "") -> 1392.366 | AD19: =IFERROR(($J19*Q19)*$L19, "") -> 835.4196 | AE19: =IFERROR(($J19*R19)*$L19, "") -> 1113.8928 | AF19: =IFERROR(($J19*S19)*$L19, "") -> 556.9464 | AG19: =IFERROR(($J19*T19)*$L19, "") -> 0 | AH19: =IFERROR(($J19*U19)*$L19, "") -> 0 | AI19: =IFERROR(($J19*V19)*$L19, "") -> 0 | ... AM19: =IFERROR(($J19*Z19)*$L19, "") -> 0 | AN19: =IFERROR(SUMIF($AB$4:$AM$4, "RDEC", AB19:AM19), "") -> 1113.8928 | AO19: =IFERROR(SUMIF($AB$4:$AM$4, "SME", AB19:AM19), "") -> 4455.5712 | AP19: =IFERROR(SUMIF($AB$4:$AM$4, "De Minimis", AB19:AM19), "") -> 0 | AR19: =IFERROR(($J19*O19)*$M19, "") -> 1113.8928 | AS19: =IFERROR(($J19*P19)*$M19, "") -> 928.244 | AT19: =IFERROR(($J19*Q19)*$M19, "") -> 556.9464 | AU19: =IFERROR(($J19*R19)*$M19, "") -> 742.5952 | AV19: =IFERROR(($J19*S19)*$M19, "") -> 371.2976 | AW19: =IFERROR(($J19*T19)*$M19, "") -> 0 | AX19: =IFERROR(($J19*U19)*$M19, "") -> 0 | AY19: =IFERROR(($J19*V19)*$M19, "") -> 0 | ... BC19: =IFERROR(($J19*Z19)*$M19, "") -> 0 | BD19: =IFERROR(SUMIF($AB$4:$AM$4, "RDEC", AR19:BC19), "") -> 742.5952 | BE19: =IFERROR(SUMIF($AB$4:$AM$4, "SME", AR19:BC19), "") -> 2970.3808 | BF19: =IFERROR(SUMIF($AB$4:$AM$4, "De Minimis", AR19:BC19), "") -> 0 | BH19: =IF((SUM(O19:Z19)>1),"ERROR","")
D20: Total | E20: =SUM(E8:E19) -> 94956.48 | F20: =SUM(F8:F19) -> 31335.62 | G20: =SUM(G8:G19) -> 6868.51 | H20: =SUM(H8:H19) -> 11848.19 | I20: =SUM(I8:I19) -> 4747.81 | J20: =SUM(J8:J19) -> 111552.48 | L20: =AVERAGE(L8:L19) -> 0.6 | M20: =AVERAGE(M8:M19) -> 0.4 | O20: =IF(SUM(O8:O19)>0,((AB20+AR20)/J20),0) -> 0.3 | P20: =IF(SUM(P8:P19)>0,((AC20+AS20)/J20),0) -> 0.25 | Q20: =IF(SUM(Q8:Q19)>0,((AD20+AT20)/J20),0) -> 0.15 | R20: =IF(SUM(R8:R19)>0,((AE20+AU20)/J20),0) -> 0.2 | S20: =IF(SUM(S8:S19)>0,((AF20+AV20)/J20),0) -> 0.1 | T20: =IF(SUM(T8:T19)>0,((AG20+AW20)/J20),0) -> 0 | U20: =IF(SUM(U8:U19)>0,((AH20+AX20)/J20),0) -> 0 | V20: =IF(SUM(V8:V19)>0,((AI20+AY20)/J20),0) -> 0 | W20: =IF(SUM(W8:W19)>0,((AJ20+AZ20)/J20),0) -> 0 | X20: =IF(SUM(X8:X19)>0,((AK20+BA20)/J20),0) -> 0 | Y20: =IF(SUM(Y8:Y19)>0,((AL20+BB20)/J20),0) -> 0 | Z20: =IF(SUM(Z8:Z19)>0,((AM20+BC20)/J20),0) -> 0 | AB20: =SUM(AB8:AB19) -> 20079.446 | AC20: =SUM(AC8:AC19) -> 16732.872 | AD20: =SUM(AD8:AD19) -> 10039.723 | AE20: =SUM(AE8:AE19) -> 13386.298 | AF20: =SUM(AF8:AF19) -> 6693.1488 | AG20: =SUM(AG8:AG19) -> 0 | AH20: =SUM(AH8:AH19) -> 0 | AI20: =SUM(AI8:AI19) -> 0 | ... AP20: =SUM(AP8:AP19) -> 0 | AR20: =SUM(AR8:AR19) -> 13386.298 | AS20: =SUM(AS8:AS19) -> 11155.248 | AT20: =SUM(AT8:AT19) -> 6693.1488 | AU20: =SUM(AU8:AU19) -> 8924.1984 | AV20: =SUM(AV8:AV19) -> 4462.0992 | AW20: =SUM(AW8:AW19) -> 0 | AX20: =SUM(AX8:AX19) -> 0 | AY20: =SUM(AY8:AY19) -> 0 | ... BF20: =SUM(BF8:BF19) -> 0 | BJ20: =IF(C6>0, C6, "") -> Chief Technology Officer | BK20: N | BL20: =IF($BK20="Y",J20,0) -> 0 | BM20: =IF(BK20="Y", AN20,0) -> 0 | BN20: =IF((BK20="Y"),AO20,0) -> 0
BJ21: =IF(C8>0, C8, "")
A22: 2 | B22: Sarah Chen | C22: Senior ML Engineer | BJ22: =IF(C9>0, C9, "")
D24: =D8 -> 45292 | E24: 6407.87 | F24: 1730.12 | G24: 451.96 | H24: 779.64 | I24: 320.39 | J24: =E24+H24+I24 -> 7507.9 | L24: 1 | M24: =1-L24 -> 0 | O24: 0.4 | P24: 0.35 | R24: 0.25 | AB24: =IFERROR(($J24*O24)*$L24, "") -> 3003.16 | AC24: =IFERROR(($J24*P24)*$L24, "") -> 2627.765 | AD24: =IFERROR(($J24*Q24)*$L24, "") -> 0 | AE24: =IFERROR(($J24*R24)*$L24, "") -> 1876.975 | AF24: =IFERROR(($J24*S24)*$L24, "") -> 0 | AG24: =IFERROR(($J24*T24)*$L24, "") -> 0 | AH24: =IFERROR(($J24*U24)*$L24, "") -> 0 | AI24: =IFERROR(($J24*V24)*$L24, "") -> 0 | ... AM24: =IFERROR(($J24*Z24)*$L24, "") -> 0 | AN24: =IFERROR(SUMIF($AB$4:$AM$4, "RDEC", AB24:AM24), "") -> 1876.975 | AO24: =IFERROR(SUMIF($AB$4:$AM$4, "SME", AB24:AM24), "") -> 5630.925 | AP24: =IFERROR(SUMIF($AB$4:$AM$4, "De Minimis", AB24:AM24), "") -> 0 | AR24: =IFERROR(($J24*O24)*$M24, "") -> 0 | AS24: =IFERROR(($J24*P24)*$M24, "") -> 0 | AT24: =IFERROR(($J24*Q24)*$M24, "") -> 0 | AU24: =IFERROR(($J24*R24)*$M24, "") -> 0 | AV24: =IFERROR(($J24*S24)*$M24, "") -> 0 | AW24: =IFERROR(($J24*T24)*$M24, "") -> 0 | AX24: =IFERROR(($J24*U24)*$M24, "") -> 0 | AY24: =IFERROR(($J24*V24)*$M24, "") -> 0 | ... BC24: =IFERROR(($J24*Z24)*$M24, "") -> 0 | BD24: =IFERROR(SUMIF($AB$4:$AM$4, "RDEC", AR24:BC24), "") -> 0 | BE24: =IFERROR(SUMIF($AB$4:$AM$4, "SME", AR24:BC24), "") -> 0 | BF24: =IFERROR(SUMIF($AB$4:$AM$4, "De Minimis", AR24:BC24), "") -> 0 | BH24: =IF((SUM(O24:Z24)>1),"ERROR","") | BJ24: =IF(C10>0, C10, "")
D25: =D9 -> 45323 | E25: 6521.1 | F25: 1760.7 | G25: 461.02 | H25: 795.26 | I25: 326.06 | J25: =E25+H25+I25 -> 7642.42 | L25: 1 | M25: =1-L25 -> 0 | O25: 0.4 | P25: 0.35 | R25: 0.25 | AB25: =IFERROR(($J25*O25)*$L25, "") -> 3056.968 | AC25: =IFERROR(($J25*P25)*$L25, "") -> 2674.847 | AD25: =IFERROR(($J25*Q25)*$L25, "") -> 0 | AE25: =IFERROR(($J25*R25)*$L25, "") -> 1910.605 | AF25: =IFERROR(($J25*S25)*$L25, "") -> 0 | AG25: =IFERROR(($J25*T25)*$L25, "") -> 0 | AH25: =IFERROR(($J25*U25)*$L25, "") -> 0 | AI25: =IFERROR(($J25*V25)*$L25, "") -> 0 | ... AM25: =IFERROR(($J25*Z25)*$L25, "") -> 0 | AN25: =IFERROR(SUMIF($AB$4:$AM$4, "RDEC", AB25:AM25), "") -> 1910.605 | AO25: =IFERROR(SUMIF($AB$4:$AM$4, "SME", AB25:AM25), "") -> 5731.815 | AP25: =IFERROR(SUMIF($AB$4:$AM$4, "De Minimis", AB25:AM25), "") -> 0 | AR25: =IFERROR(($J25*O25)*$M25, "") -> 0 | AS25: =IFERROR(($J25*P25)*$M25, "") -> 0 | AT25: =IFERROR(($J25*Q25)*$M25, "") -> 0 | AU25: =IFERROR(($J25*R25)*$M25, "") -> 0 | AV25: =IFERROR(($J25*S25)*$M25, "") -> 0 | AW25: =IFERROR(($J25*T25)*$M25, "") -> 0 | AX25: =IFERROR(($J25*U25)*$M25, "") -> 0 | AY25: =IFERROR(($J25*V25)*$M25, "") -> 0 | ... BC25: =IFERROR(($J25*Z25)*$M25, "") -> 0 | BD25: =IFERROR(SUMIF($AB$4:$AM$4, "RDEC", AR25:BC25), "") -> 0 | BE25: =IFERROR(SUMIF($AB$4:$AM$4, "SME", AR25:BC25), "") -> 0 | BF25: =IFERROR(SUMIF($AB$4:$AM$4, "De Minimis", AR25:BC25), "") -> 0 | BH25: =IF((SUM(O25:Z25)>1),"ERROR","") | BJ25: =IF(C11>0, C11, "")
D26: =D10 -> 45352 | E26: 6408.52 | F26: 1730.3 | G26: 452.02 | H26: 779.73 | I26: 320.43 | J26: =E26+H26+I26 -> 7508.68 | L26: 1 | M26: =1-L26 -> 0 | O26: 0.4 | P26: 0.35 | R26: 0.25 | AB26: =IFERROR(($J26*O26)*$L26, "") -> 3003.472 | AC26: =IFERROR(($J26*P26)*$L26, "") -> 2628.038 | AD26: =IFERROR(($J26*Q26)*$L26, "") -> 0 | AE26: =IFERROR(($J26*R26)*$L26, "") -> 1877.17 | AF26: =IFERROR(($J26*S26)*$L26, "") -> 0 | AG26: =IFERROR(($J26*T26)*$L26, "") -> 0 | AH26: =IFERROR(($J26*U26)*$L26, "") -> 0 | AI26: =IFERROR(($J26*V26)*$L26, "") -> 0 | ... AM26: =IFERROR(($J26*Z26)*$L26, "") -> 0 | AN26: =IFERROR(SUMIF($AB$4:$AM$4, "RDEC", AB26:AM26), "") -> 1877.17 | AO26: =IFERROR(SUMIF($AB$4:$AM$4, "SME", AB26:AM26), "") -> 5631.51 | AP26: =IFERROR(SUMIF($AB$4:$AM$4, "De Minimis", AB26:AM26), "") -> 0 | AR26: =IFERROR(($J26*O26)*$M26, "") -> 0 | AS26: =IFERROR(($J26*P26)*$M26, "") -> 0 | AT26: =IFERROR(($J26*Q26)*$M26, "") -> 0 | AU26: =IFERROR(($J26*R26)*$M26, "") -> 0 | AV26: =IFERROR(($J26*S26)*$M26, "") -> 0 | AW26: =IFERROR(($J26*T26)*$M26, "") -> 0 | AX26: =IFERROR(($J26*U26)*$M26, "") -> 0 | AY26: =IFERROR(($J26*V26)*$M26, "") -> 0 | ... BC26: =IFERROR(($J26*Z26)*$M26, "") -> 0 | BD26: =IFERROR(SUMIF($AB$4:$AM$4, "RDEC", AR26:BC26), "") -> 0 | BE26: =IFERROR(SUMIF($AB$4:$AM$4, "SME", AR26:BC26), "") -> 0 | BF26: =IFERROR(SUMIF($AB$4:$AM$4, "De Minimis", AR26:BC26), "") -> 0 | BH26: =IF((SUM(O26:Z26)>1),"ERROR","") | BJ26: =IF(C12>0, C12, "")
D27: =D11 -> 45383 | E27: 6624.55 | F27: 1788.63 | G27: 469.3 | H27: 809.54 | I27: 331.23 | J27: =E27+H27+I27 -> 7765.32 | L27: 1 | M27: =1-L27 -> 0 | O27: 0.4 | P27: 0.35 | R27: 0.25 | AB27: =IFERROR(($J27*O27)*$L27, "") -> 3106.128 | AC27: =IFERROR(($J27*P27)*$L27, "") -> 2717.862 | AD27: =IFERROR(($J27*Q27)*$L27, "") -> 0 | AE27: =IFERROR(($J27*R27)*$L27, "") -> 1941.33 | AF27: =IFERROR(($J27*S27)*$L27, "") -> 0 | AG27: =IFERROR(($J27*T27)*$L27, "") -> 0 | AH27: =IFERROR(($J27*U27)*$L27, "") -> 0 | AI27: =IFERROR(($J27*V27)*$L27, "") -> 0 | ... AM27: =IFERROR(($J27*Z27)*$L27, "") -> 0 | AN27: =IFERROR(SUMIF($AB$4:$AM$4, "RDEC", AB27:AM27), "") -> 1941.33 | AO27: =IFERROR(SUMIF($AB$4:$AM$4, "SME", AB27:AM27), "") -> 5823.99 | AP27: =IFERROR(SUMIF($AB$4:$AM$4, "De Minimis", AB27:AM27), "") -> 0 | AR27: =IFERROR(($J27*O27)*$M27, "") -> 0 | AS27: =IFERROR(($J27*P27)*$M27, "") -> 0 | AT27: =IFERROR(($J27*Q27)*$M27, "") -> 0 | AU27: =IFERROR(($J27*R27)*$M27, "") -> 0 | AV27: =IFERROR(($J27*S27)*$M27, "") -> 0 | AW27: =IFERROR(($J27*T27)*$M27, "") -> 0 | AX27: =IFERROR(($J27*U27)*$M27, "") -> 0 | AY27: =IFERROR(($J27*V27)*$M27, "") -> 0 | ... BC27: =IFERROR(($J27*Z27)*$M27, "") -> 0 | BD27: =IFERROR(SUMIF($AB$4:$AM$4, "RDEC", AR27:BC27), "") -> 0 | BE27: =IFERROR(SUMIF($AB$4:$AM$4, "SME", AR27:BC27), "") -> 0 | BF27: =IFERROR(SUMIF($AB$4:$AM$4, "De Minimis", AR27:BC27), "") -> 0 | BH27: =IF((SUM(O27:Z27)>1),"ERROR","") | BJ27: =IF(C13>0, C13, "")
D28: =D12 -> 45413 | E28: 6619.59 | F28: 1787.29 | G28: 468.9 | H28: 808.85 | I28: 330.98 | J28: =E28+H28+I28 -> 7759.42 | L28: 1 | M28: =1-L28 -> 0 | O28: 0.4 | P28: 0.35 | R28: 0.25 | AB28: =IFERROR(($J28*O28)*$L28, "") -> 3103.768 | AC28: =IFERROR(($J28*P28)*$L28, "") -> 2715.797 | AD28: =IFERROR(($J28*Q28)*$L28, "") -> 0 | AE28: =IFERROR(($J28*R28)*$L28, "") -> 1939.855 | AF28: =IFERROR(($J28*S28)*$L28, "") -> 0 | AG28: =IFERROR(($J28*T28)*$L28, "") -> 0 | AH28: =IFERROR(($J28*U28)*$L28, "") -> 0 | AI28: =IFERROR(($J28*V28)*$L28, "") -> 0 | ... AM28: =IFERROR(($J28*Z28)*$L28, "") -> 0 | AN28: =IFERROR(SUMIF($AB$4:$AM$4, "RDEC", AB28:AM28), "") -> 1939.855 | AO28: =IFERROR(SUMIF($AB$4:$AM$4, "SME", AB28:AM28), "") -> 5819.565 | AP28: =IFERROR(SUMIF($AB$4:$AM$4, "De Minimis", AB28:AM28), "") -> 0 | AR28: =IFERROR(($J28*O28)*$M28, "") -> 0 | AS28: =IFERROR(($J28*P28)*$M28, "") -> 0 | AT28: =IFERROR(($J28*Q28)*$M28, "") -> 0 | AU28: =IFERROR(($J28*R28)*$M28, "") -> 0 | AV28: =IFERROR(($J28*S28)*$M28, "") -> 0 | AW28: =IFERROR(($J28*T28)*$M28, "") -> 0 | AX28: =IFERROR(($J28*U28)*$M28, "") -> 0 | AY28: =IFERROR(($J28*V28)*$M28, "") -> 0 | ... BC28: =IFERROR(($J28*Z28)*$M28, "") -> 0 | BD28: =IFERROR(SUMIF($AB$4:$AM$4, "RDEC", AR28:BC28), "") -> 0 | BE28: =IFERROR(SUMIF($AB$4:$AM$4, "SME", AR28:BC28), "") -> 0 | BF28: =IFERROR(SUMIF($AB$4:$AM$4, "De Minimis", AR28:BC28), "") -> 0 | BH28: =IF((SUM(O28:Z28)>1),"ERROR","") | BJ28: =IF(C14>0, C14, "")
D29: =D13 -> 45444 | E29: 6598.31 | F29: 1781.54 | G29: 467.2 | H29: 805.92 | I29: 329.92 | J29: =E29+H29+I29 -> 7734.15 | L29: 1 | M29: =1-L29 -> 0 | O29: 0.4 | P29: 0.35 | R29: 0.25 | AB29: =IFERROR(($J29*O29)*$L29, "") -> 3093.66 | AC29: =IFERROR(($J29*P29)*$L29, "") -> 2706.9525 | AD29: =IFERROR(($J29*Q29)*$L29, "") -> 0 | AE29: =IFERROR(($J29*R29)*$L29, "") -> 1933.5375 | AF29: =IFERROR(($J29*S29)*$L29, "") -> 0 | AG29: =IFERROR(($J29*T29)*$L29, "") -> 0 | AH29: =IFERROR(($J29*U29)*$L29, "") -> 0 | AI29: =IFERROR(($J29*V29)*$L29, "") -> 0 | ... AM29: =IFERROR(($J29*Z29)*$L29, "") -> 0 | AN29: =IFERROR(SUMIF($AB$4:$AM$4, "RDEC", AB29:AM29), "") -> 1933.5375 | AO29: =IFERROR(SUMIF($AB$4:$AM$4, "SME", AB29:AM29), "") -> 5800.6125 | AP29: =IFERROR(SUMIF($AB$4:$AM$4, "De Minimis", AB29:AM29), "") -> 0 | AR29: =IFERROR(($J29*O29)*$M29, "") -> 0 | AS29: =IFERROR(($J29*P29)*$M29, "") -> 0 | AT29: =IFERROR(($J29*Q29)*$M29, "") -> 0 | AU29: =IFERROR(($J29*R29)*$M29, "") -> 0 | AV29: =IFERROR(($J29*S29)*$M29, "") -> 0 | AW29: =IFERROR(($J29*T29)*$M29, "") -> 0 | AX29: =IFERROR(($J29*U29)*$M29, "") -> 0 | AY29: =IFERROR(($J29*V29)*$M29, "") -> 0 | ... BC29: =IFERROR(($J29*Z29)*$M29, "") -> 0 | BD29: =IFERROR(SUMIF($AB$4:$AM$4, "RDEC", AR29:BC29), "") -> 0 | BE29: =IFERROR(SUMIF($AB$4:$AM$4, "SME", AR29:BC29), "") -> 0 | BF29: =IFERROR(SUMIF($AB$4:$AM$4, "De Minimis", AR29:BC29), "") -> 0 | BH29: =IF((SUM(O29:Z29)>1),"ERROR","") | BJ29: =IF(C15>0, C15, "")
D30: =D14 -> 45474 | E30: 6554.78 | F30: 1769.79 | G30: 463.72 | H30: 799.91 | I30: 327.74 | J30: =E30+H30+I30 -> 7682.43 | L30: 1 | M30: =1-L30 -> 0 | O30: 0.4 | P30: 0.35 | R30: 0.25 | AB30: =IFERROR(($J30*O30)*$L30, "") -> 3072.972 | AC30: =IFERROR(($J30*P30)*$L30, "") -> 2688.8505 | AD30: =IFERROR(($J30*Q30)*$L30, "") -> 0 | AE30: =IFERROR(($J30*R30)*$L30, "") -> 1920.6075 | AF30: =IFERROR(($J30*S30)*$L30, "") -> 0 | AG30: =IFERROR(($J30*T30)*$L30, "") -> 0 | AH30: =IFERROR(($J30*U30)*$L30, "") -> 0 | AI30: =IFERROR(($J30*V30)*$L30, "") -> 0 | ... AM30: =IFERROR(($J30*Z30)*$L30, "") -> 0 | AN30: =IFERROR(SUMIF($AB$4:$AM$4, "RDEC", AB30:AM30), "") -> 1920.6075 | AO30: =IFERROR(SUMIF($AB$4:$AM$4, "SME", AB30:AM30), "") -> 5761.8225 | AP30: =IFERROR(SUMIF($AB$4:$AM$4, "De Minimis", AB30:AM30), "") -> 0 | AR30: =IFERROR(($J30*O30)*$M30, "") -> 0 | AS30: =IFERROR(($J30*P30)*$M30, "") -> 0 | AT30: =IFERROR(($J30*Q30)*$M30, "") -> 0 | AU30: =IFERROR(($J30*R30)*$M30, "") -> 0 | AV30: =IFERROR(($J30*S30)*$M30, "") -> 0 | AW30: =IFERROR(($J30*T30)*$M30, "") -> 0 | AX30: =IFERROR(($J30*U30)*$M30, "") -> 0 | AY30: =IFERROR(($J30*V30)*$M30, "") -> 0 | ... BC30: =IFERROR(($J30*Z30)*$M30, "") -> 0 | BD30: =IFERROR(SUMIF($AB$4:$AM$4, "RDEC", AR30:BC30), "") -> 0 | BE30: =IFERROR(SUMIF($AB$4:$AM$4, "SME", AR30:BC30), "") -> 0 | BF30: =IFERROR(SUMIF($AB$4:$AM$4, "De Minimis", AR30:BC30), "") -> 0 | BH30: =IF((SUM(O30:Z30)>1),"ERROR","") | BJ30: =IF(C16>0, C16, "")
D31: =D15 -> 45505 | E31: 6434.09 | F31: 1737.2 | G31: 454.06 | H31: 783.25 | I31: 321.7 | J31: =E31+H31+I31 -> 7539.04 | L31: 1 | M31: =1-L31 -> 0 | O31: 0.4 | P31: 0.35 | R31: 0.25 | AB31: =IFERROR(($J31*O31)*$L31, "") -> 3015.616 | AC31: =IFERROR(($J31*P31)*$L31, "") -> 2638.664 | AD31: =IFERROR(($J31*Q31)*$L31, "") -> 0 | AE31: =IFERROR(($J31*R31)*$L31, "") -> 1884.76 | AF31: =IFERROR(($J31*S31)*$L31, "") -> 0 | AG31: =IFERROR(($J31*T31)*$L31, "") -> 0 | AH31: =IFERROR(($J31*U31)*$L31, "") -> 0 | AI31: =IFERROR(($J31*V31)*$L31, "") -> 0 | ... AM31: =IFERROR(($J31*Z31)*$L31, "") -> 0 | AN31: =IFERROR(SUMIF($AB$4:$AM$4, "RDEC", AB31:AM31), "") -> 1884.76 | AO31: =IFERROR(SUMIF($AB$4:$AM$4, "SME", AB31:AM31), "") -> 5654.28 | AP31: =IFERROR(SUMIF($AB$4:$AM$4, "De Minimis", AB31:AM31), "") -> 0 | AR31: =IFERROR(($J31*O31)*$M31, "") -> 0 | AS31: =IFERROR(($J31*P31)*$M31, "") -> 0 | AT31: =IFERROR(($J31*Q31)*$M31, "") -> 0 | AU31: =IFERROR(($J31*R31)*$M31, "") -> 0 | AV31: =IFERROR(($J31*S31)*$M31, "") -> 0 | AW31: =IFERROR(($J31*T31)*$M31, "") -> 0 | AX31: =IFERROR(($J31*U31)*$M31, "") -> 0 | AY31: =IFERROR(($J31*V31)*$M31, "") -> 0 | ... BC31: =IFERROR(($J31*Z31)*$M31, "") -> 0 | BD31: =IFERROR(SUMIF($AB$4:$AM$4, "RDEC", AR31:BC31), "") -> 0 | BE31: =IFERROR(SUMIF($AB$4:$AM$4, "SME", AR31:BC31), "") -> 0 | BF31: =IFERROR(SUMIF($AB$4:$AM$4, "De Minimis", AR31:BC31), "") -> 0 | BH31: =IF((SUM(O31:Z31)>1),"ERROR","") | BJ31: =IF(C17>0, C17, "")
D32: =D16 -> 45536 | E32: 6403.94 | F32: 1729.06 | G32: 451.65 | H32: 779.09 | I32: 320.2 | J32: =E32+H32+I32 -> 7503.23 | L32: 1 | M32: =1-L32 -> 0 | O32: 0.4 | P32: 0.35 | R32: 0.25 | AB32: =IFERROR(($J32*O32)*$L32, "") -> 3001.292 | AC32: =IFERROR(($J32*P32)*$L32, "") -> 2626.1305 | AD32: =IFERROR(($J32*Q32)*$L32, "") -> 0 | AE32: =IFERROR(($J32*R32)*$L32, "") -> 1875.8075 | AF32: =IFERROR(($J32*S32)*$L32, "") -> 0 | AG32: =IFERROR(($J32*T32)*$L32, "") -> 0 | AH32: =IFERROR(($J32*U32)*$L32, "") -> 0 | AI32: =IFERROR(($J32*V32)*$L32, "") -> 0 | ... AM32: =IFERROR(($J32*Z32)*$L32, "") -> 0 | AN32: =IFERROR(SUMIF($AB$4:$AM$4, "RDEC", AB32:AM32), "") -> 1875.8075 | AO32: =IFERROR(SUMIF($AB$4:$AM$4, "SME", AB32:AM32), "") -> 5627.4225 | AP32: =IFERROR(SUMIF($AB$4:$AM$4, "De Minimis", AB32:AM32), "") -> 0 | AR32: =IFERROR(($J32*O32)*$M32, "") -> 0 | AS32: =IFERROR(($J32*P32)*$M32, "") -> 0 | AT32: =IFERROR(($J32*Q32)*$M32, "") -> 0 | AU32: =IFERROR(($J32*R32)*$M32, "") -> 0 | AV32: =IFERROR(($J32*S32)*$M32, "") -> 0 | AW32: =IFERROR(($J32*T32)*$M32, "") -> 0 | AX32: =IFERROR(($J32*U32)*$M32, "") -> 0 | AY32: =IFERROR(($J32*V32)*$M32, "") -> 0 | ... BC32: =IFERROR(($J32*Z32)*$M32, "") -> 0 | BD32: =IFERROR(SUMIF($AB$4:$AM$4, "RDEC", AR32:BC32), "") -> 0 | BE32: =IFERROR(SUMIF($AB$4:$AM$4, "SME", AR32:BC32), "") -> 0 | BF32: =IFERROR(SUMIF($AB$4:$AM$4, "De Minimis", AR32:BC32), "") -> 0 | BH32: =IF((SUM(O32:Z32)>1),"ERROR","") | BJ32: =IF(C18>0, C18, "")
D33: =D17 -> 45566 | E33: 6442.69 | F33: 1739.53 | G33: 454.75 | H33: 784.44 | I33: 322.13 | J33: =E33+H33+I33 -> 7549.26 | L33: 1 | M33: =1-L33 -> 0 | O33: 0.4 | P33: 0.35 | R33: 0.25 | AB33: =IFERROR(($J33*O33)*$L33, "") -> 3019.704 | AC33: =IFERROR(($J33*P33)*$L33, "") -> 2642.241 | AD33: =IFERROR(($J33*Q33)*$L33, "") -> 0 | AE33: =IFERROR(($J33*R33)*$L33, "") -> 1887.315 | AF33: =IFERROR(($J33*S33)*$L33, "") -> 0 | AG33: =IFERROR(($J33*T33)*$L33, "") -> 0 | AH33: =IFERROR(($J33*U33)*$L33, "") -> 0 | AI33: =IFERROR(($J33*V33)*$L33, "") -> 0 | ... AM33: =IFERROR(($J33*Z33)*$L33, "") -> 0 | AN33: =IFERROR(SUMIF($AB$4:$AM$4, "RDEC", AB33:AM33), "") -> 1887.315 | AO33: =IFERROR(SUMIF($AB$4:$AM$4, "SME", AB33:AM33), "") -> 5661.945 | AP33: =IFERROR(SUMIF($AB$4:$AM$4, "De Minimis", AB33:AM33), "") -> 0 | AR33: =IFERROR(($J33*O33)*$M33, "") -> 0 | AS33: =IFERROR(($J33*P33)*$M33, "") -> 0 | AT33: =IFERROR(($J33*Q33)*$M33, "") -> 0 | AU33: =IFERROR(($J33*R33)*$M33, "") -> 0 | AV33: =IFERROR(($J33*S33)*$M33, "") -> 0 | AW33: =IFERROR(($J33*T33)*$M33, "") -> 0 | AX33: =IFERROR(($J33*U33)*$M33, "") -> 0 | AY33: =IFERROR(($J33*V33)*$M33, "") -> 0 | ... BC33: =IFERROR(($J33*Z33)*$M33, "") -> 0 | BD33: =IFERROR(SUMIF($AB$4:$AM$4, "RDEC", AR33:BC33), "") -> 0 | BE33: =IFERROR(SUMIF($AB$4:$AM$4, "SME", AR33:BC33), "") -> 0 | BF33: =IFERROR(SUMIF($AB$4:$AM$4, "De Minimis", AR33:BC33), "") -> 0 | BH33: =IF((SUM(O33:Z33)>1),"ERROR","") | BJ33: =IF(C19>0, C19, "")
D34: =D18 -> 45597 | E34: 6612.91 | F34: 1785.49 | G34: 468.37 | H34: 807.93 | I34: 330.65 | J34: =E34+H34+I34 -> 7751.49 | L34: 1 | M34: =1-L34 -> 0 | O34: 0.4 | P34: 0.35 | R34: 0.25 | AB34: =IFERROR(($J34*O34)*$L34, "") -> 3100.596 | AC34: =IFERROR(($J34*P34)*$L34, "") -> 2713.0215 | AD34: =IFERROR(($J34*Q34)*$L34, "") -> 0 | AE34: =IFERROR(($J34*R34)*$L34, "") -> 1937.8725 | AF34: =IFERROR(($J34*S34)*$L34, "") -> 0 | AG34: =IFERROR(($J34*T34)*$L34, "") -> 0 | AH34: =IFERROR(($J34*U34)*$L34, "") -> 0 | AI34: =IFERROR(($J34*V34)*$L34, "") -> 0 | ... AM34: =IFERROR(($J34*Z34)*$L34, "") -> 0 | AN34: =IFERROR(SUMIF($AB$4:$AM$4, "RDEC", AB34:AM34), "") -> 1937.8725 | AO34: =IFERROR(SUMIF($AB$4:$AM$4, "SME", AB34:AM34), "") -> 5813.6175 | AP34: =IFERROR(SUMIF($AB$4:$AM$4, "De Minimis", AB34:AM34), "") -> 0 | AR34: =IFERROR(($J34*O34)*$M34, "") -> 0 | AS34: =IFERROR(($J34*P34)*$M34, "") -> 0 | AT34: =IFERROR(($J34*Q34)*$M34, "") -> 0 | AU34: =IFERROR(($J34*R34)*$M34, "") -> 0 | AV34: =IFERROR(($J34*S34)*$M34, "") -> 0 | AW34: =IFERROR(($J34*T34)*$M34, "") -> 0 | AX34: =IFERROR(($J34*U34)*$M34, "") -> 0 | AY34: =IFERROR(($J34*V34)*$M34, "") -> 0 | ... BC34: =IFERROR(($J34*Z34)*$M34, "") -> 0 | BD34: =IFERROR(SUMIF($AB$4:$AM$4, "RDEC", AR34:BC34), "") -> 0 | BE34: =IFERROR(SUMIF($AB$4:$AM$4, "SME", AR34:BC34), "") -> 0 | BF34: =IFERROR(SUMIF($AB$4:$AM$4, "De Minimis", AR34:BC34), "") -> 0 | BH34: =IF((SUM(O34:Z34)>1),"ERROR","") | BJ34: =IF(C20>0, C20, "")
D35: =D19 -> 45627 | E35: 6585.06 | F35: 1777.97 | G35: 466.14 | H35: 804.09 | I35: 329.25 | J35: =E35+H35+I35 -> 7718.4 | L35: 1 | M35: =1-L35 -> 0 | O35: 0.4 | P35: 0.35 | R35: 0.25 | AB35: =IFERROR(($J35*O35)*$L35, "") -> 3087.36 | AC35: =IFERROR(($J35*P35)*$L35, "") -> 2701.44 | AD35: =IFERROR(($J35*Q35)*$L35, "") -> 0 | AE35: =IFERROR(($J35*R35)*$L35, "") -> 1929.6 | AF35: =IFERROR(($J35*S35)*$L35, "") -> 0 | AG35: =IFERROR(($J35*T35)*$L35, "") -> 0 | AH35: =IFERROR(($J35*U35)*$L35, "") -> 0 | AI35: =IFERROR(($J35*V35)*$L35, "") -> 0 | ... AM35: =IFERROR(($J35*Z35)*$L35, "") -> 0 | AN35: =IFERROR(SUMIF($AB$4:$AM$4, "RDEC", AB35:AM35), "") -> 1929.6 | AO35: =IFERROR(SUMIF($AB$4:$AM$4, "SME", AB35:AM35), "") -> 5788.8 | AP35: =IFERROR(SUMIF($AB$4:$AM$4, "De Minimis", AB35:AM35), "") -> 0 | AR35: =IFERROR(($J35*O35)*$M35, "") -> 0 | AS35: =IFERROR(($J35*P35)*$M35, "") -> 0 | AT35: =IFERROR(($J35*Q35)*$M35, "") -> 0 | AU35: =IFERROR(($J35*R35)*$M35, "") -> 0 | AV35: =IFERROR(($J35*S35)*$M35, "") -> 0 | AW35: =IFERROR(($J35*T35)*$M35, "") -> 0 | AX35: =IFERROR(($J35*U35)*$M35, "") -> 0 | AY35: =IFERROR(($J35*V35)*$M35, "") -> 0 | ... BC35: =IFERROR(($J35*Z35)*$M35, "") -> 0 | BD35: =IFERROR(SUMIF($AB$4:$AM$4, "RDEC", AR35:BC35), "") -> 0 | BE35: =IFERROR(SUMIF($AB$4:$AM$4, "SME", AR35:BC35), "") -> 0 | BF35: =IFERROR(SUMIF($AB$4:$AM$4, "De Minimis", AR35:BC35), "") -> 0 | BH35: =IF((SUM(O35:Z35)>1),"ERROR","") | BJ35: =IF(C21>0, C21, "")
D36: Total | E36: =SUM(E24:E35) -> 78213.41 | F36: =SUM(F24:F35) -> 21117.62 | G36: =SUM(G24:G35) -> 5529.09 | H36: =SUM(H24:H35) -> 9537.65 | I36: =SUM(I24:I35) -> 3910.68 | J36: =SUM(J24:J35) -> 91661.74 | L36: =AVERAGE(L24:L35) -> 1 | M36: =AVERAGE(M24:M35) -> 0 | O36: =IF(SUM(O24:O35)>0,((AB36+AR36)/J36),0) -> 0.4 | P36: =IF(SUM(P24:P35)>0,((AC36+AS36)/J36),0) -> 0.35 | Q36: =IF(SUM(Q24:Q35)>0,((AD36+AT36)/J36),0) -> 0 | R36: =IF(SUM(R24:R35)>0,((AE36+AU36)/J36),0) -> 0.25 | S36: =IF(SUM(S24:S35)>0,((AF36+AV36)/J36),0) -> 0 | T36: =IF(SUM(T24:T35)>0,((AG36+AW36)/J36),0) -> 0 | U36: =IF(SUM(U24:U35)>0,((AH36+AX36)/J36),0) -> 0 | V36: =IF(SUM(V24:V35)>0,((AI36+AY36)/J36),0) -> 0 | W36: =IF(SUM(W24:W35)>0,((AJ36+AZ36)/J36),0) -> 0 | X36: =IF(SUM(X24:X35)>0,((AK36+BA36)/J36),0) -> 0 | Y36: =IF(SUM(Y24:Y35)>0,((AL36+BB36)/J36),0) -> 0 | Z36: =IF(SUM(Z24:Z35)>0,((AM36+BC36)/J36),0) -> 0 | AB36: =SUM(AB24:AB35) -> 36664.696 | AC36: =SUM(AC24:AC35) -> 32081.609 | AD36: =SUM(AD24:AD35) -> 0 | AE36: =SUM(AE24:AE35) -> 22915.435 | AF36: =SUM(AF24:AF35) -> 0 | AG36: =SUM(AG24:AG35) -> 0 | AH36: =SUM(AH24:AH35) -> 0 | AI36: =SUM(AI24:AI35) -> 0 | ... AP36: =SUM(AP24:AP35) -> 0 | AR36: =SUM(AR24:AR35) -> 0 | AS36: =SUM(AS24:AS35) -> 0 | AT36: =SUM(AT24:AT35) -> 0 | AU36: =SUM(AU24:AU35) -> 0 | AV36: =SUM(AV24:AV35) -> 0 | AW36: =SUM(AW24:AW35) -> 0 | AX36: =SUM(AX24:AX35) -> 0 | AY36: =SUM(AY24:AY35) -> 0 | ... BF36: =SUM(BF24:BF35) -> 0 | BJ36: =IF(C22>0, C22, "") -> Senior ML Engineer | BK36: N | BL36: =IF($BK36="Y",J36,0) -> 0 | BM36: =IF(BK36="Y", AN36,0) -> 0 | BN36: =IF((BK36="Y"),AO36,0) -> 0
BJ37: =IF(C24>0, C24, "")
A38: 3 | B38: David Okonkwo | C38: Backend Developer | BJ38: =IF(C25>0, C25, "")
D40: =D24 -> 45292 | E40: 5072.76 | F40: 1369.65 | G40: 345.15 | H40: 595.39 | I40: 253.64 | J40: =E40+H40+I40 -> 5921.79 | L40: 1 | M40: =1-L40 -> 0 | O40: 0.5 | P40: 0.3 | Q40: 0.2 | AB40: =IFERROR(($J40*O40)*$L40, "") -> 2960.895 | AC40: =IFERROR(($J40*P40)*$L40, "") -> 1776.537 | AD40: =IFERROR(($J40*Q40)*$L40, "") -> 1184.358 | AE40: =IFERROR(($J40*R40)*$L40, "") -> 0 | AF40: =IFERROR(($J40*S40)*$L40, "") -> 0 | AG40: =IFERROR(($J40*T40)*$L40, "") -> 0 | AH40: =IFERROR(($J40*U40)*$L40, "") -> 0 | AI40: =IFERROR(($J40*V40)*$L40, "") -> 0 | ... AM40: =IFERROR(($J40*Z40)*$L40, "") -> 0 | AN40: =IFERROR(SUMIF($AB$4:$AM$4, "RDEC", AB40:AM40), "") -> 0 | AO40: =IFERROR(SUMIF($AB$4:$AM$4, "SME", AB40:AM40), "") -> 5921.79 | AP40: =IFERROR(SUMIF($AB$4:$AM$4, "De Minimis", AB40:AM40), "") -> 0 | AR40: =IFERROR(($J40*O40)*$M40, "") -> 0 | AS40: =IFERROR(($J40*P40)*$M40, "") -> 0 | AT40: =IFERROR(($J40*Q40)*$M40, "") -> 0 | AU40: =IFERROR(($J40*R40)*$M40, "") -> 0 | AV40: =IFERROR(($J40*S40)*$M40, "") -> 0 | AW40: =IFERROR(($J40*T40)*$M40, "") -> 0 | AX40: =IFERROR(($J40*U40)*$M40, "") -> 0 | AY40: =IFERROR(($J40*V40)*$M40, "") -> 0 | ... BC40: =IFERROR(($J40*Z40)*$M40, "") -> 0 | BD40: =IFERROR(SUMIF($AB$4:$AM$4, "RDEC", AR40:BC40), "") -> 0 | BE40: =IFERROR(SUMIF($AB$4:$AM$4, "SME", AR40:BC40), "") -> 0 | BF40: =IFERROR(SUMIF($AB$4:$AM$4, "De Minimis", AR40:BC40), "") -> 0 | BH40: =IF((SUM(O40:Z40)>1),"ERROR","") | BJ40: =IF(C26>0, C26, "")
D41: =D25 -> 45323 | E41: 5077.2 | F41: 1370.84 | G41: 345.51 | H41: 596 | I41: 253.86 | J41: =E41+H41+I41 -> 5927.06 | L41: 1 | M41: =1-L41 -> 0 | O41: 0.5 | P41: 0.3 | Q41: 0.2 | AB41: =IFERROR(($J41*O41)*$L41, "") -> 2963.53 | AC41: =IFERROR(($J41*P41)*$L41, "") -> 1778.118 | AD41: =IFERROR(($J41*Q41)*$L41, "") -> 1185.412 | AE41: =IFERROR(($J41*R41)*$L41, "") -> 0 | AF41: =IFERROR(($J41*S41)*$L41, "") -> 0 | AG41: =IFERROR(($J41*T41)*$L41, "") -> 0 | AH41: =IFERROR(($J41*U41)*$L41, "") -> 0 | AI41: =IFERROR(($J41*V41)*$L41, "") -> 0 | ... AM41: =IFERROR(($J41*Z41)*$L41, "") -> 0 | AN41: =IFERROR(SUMIF($AB$4:$AM$4, "RDEC", AB41:AM41), "") -> 0 | AO41: =IFERROR(SUMIF($AB$4:$AM$4, "SME", AB41:AM41), "") -> 5927.06 | AP41: =IFERROR(SUMIF($AB$4:$AM$4, "De Minimis", AB41:AM41), "") -> 0 | AR41: =IFERROR(($J41*O41)*$M41, "") -> 0 | AS41: =IFERROR(($J41*P41)*$M41, "") -> 0 | AT41: =IFERROR(($J41*Q41)*$M41, "") -> 0 | AU41: =IFERROR(($J41*R41)*$M41, "") -> 0 | AV41: =IFERROR(($J41*S41)*$M41, "") -> 0 | AW41: =IFERROR(($J41*T41)*$M41, "") -> 0 | AX41: =IFERROR(($J41*U41)*$M41, "") -> 0 | AY41: =IFERROR(($J41*V41)*$M41, "") -> 0 | ... BC41: =IFERROR(($J41*Z41)*$M41, "") -> 0 | BD41: =IFERROR(SUMIF($AB$4:$AM$4, "RDEC", AR41:BC41), "") -> 0 | BE41: =IFERROR(SUMIF($AB$4:$AM$4, "SME", AR41:BC41), "") -> 0 | BF41: =IFERROR(SUMIF($AB$4:$AM$4, "De Minimis", AR41:BC41), "") -> 0 | BH41: =IF((SUM(O41:Z41)>1),"ERROR","") | BJ41: =IF(C27>0, C27, "")
D42: =D26 -> 45352 | E42: 5221.21 | F42: 1409.73 | G42: 357.03 | H42: 615.88 | I42: 261.06 | J42: =E42+H42+I42 -> 6098.15 | L42: 1 | M42: =1-L42 -> 0 | O42: 0.5 | P42: 0.3 | Q42: 0.2 | AB42: =IFERROR(($J42*O42)*$L42, "") -> 3049.075 | AC42: =IFERROR(($J42*P42)*$L42, "") -> 1829.445 | AD42: =IFERROR(($J42*Q42)*$L42, "") -> 1219.63 | AE42: =IFERROR(($J42*R42)*$L42, "") -> 0 | AF42: =IFERROR(($J42*S42)*$L42, "") -> 0 | AG42: =IFERROR(($J42*T42)*$L42, "") -> 0 | AH42: =IFERROR(($J42*U42)*$L42, "") -> 0 | AI42: =IFERROR(($J42*V42)*$L42, "") -> 0 | ... AM42: =IFERROR(($J42*Z42)*$L42, "") -> 0 | AN42: =IFERROR(SUMIF($AB$4:$AM$4, "RDEC", AB42:AM42), "") -> 0 | AO42: =IFERROR(SUMIF($AB$4:$AM$4, "SME", AB42:AM42), "") -> 6098.15 | AP42: =IFERROR(SUMIF($AB$4:$AM$4, "De Minimis", AB42:AM42), "") -> 0 | AR42: =IFERROR(($J42*O42)*$M42, "") -> 0 | AS42: =IFERROR(($J42*P42)*$M42, "") -> 0 | AT42: =IFERROR(($J42*Q42)*$M42, "") -> 0 | AU42: =IFERROR(($J42*R42)*$M42, "") -> 0 | AV42: =IFERROR(($J42*S42)*$M42, "") -> 0 | AW42: =IFERROR(($J42*T42)*$M42, "") -> 0 | AX42: =IFERROR(($J42*U42)*$M42, "") -> 0 | AY42: =IFERROR(($J42*V42)*$M42, "") -> 0 | ... BC42: =IFERROR(($J42*Z42)*$M42, "") -> 0 | BD42: =IFERROR(SUMIF($AB$4:$AM$4, "RDEC", AR42:BC42), "") -> 0 | BE42: =IFERROR(SUMIF($AB$4:$AM$4, "SME", AR42:BC42), "") -> 0 | BF42: =IFERROR(SUMIF($AB$4:$AM$4, "De Minimis", AR42:BC42), "") -> 0 | BH42: =IF((SUM(O42:Z42)>1),"ERROR","") | BJ42: =IF(C28>0, C28, "")
D43: =D27 -> 45383 | E43: 5082.09 | F43: 1372.16 | G43: 345.9 | H43: 596.68 | I43: 254.1 | J43: =E43+H43+I43 -> 5932.87 | L43: 1 | M43: =1-L43 -> 0 | O43: 0.5 | P43: 0.3 | Q43: 0.2 | AB43: =IFERROR(($J43*O43)*$L43, "") -> 2966.435 | AC43: =IFERROR(($J43*P43)*$L43, "") -> 1779.861 | AD43: =IFERROR(($J43*Q43)*$L43, "") -> 1186.574 | AE43: =IFERROR(($J43*R43)*$L43, "") -> 0 | AF43: =IFERROR(($J43*S43)*$L43, "") -> 0 | AG43: =IFERROR(($J43*T43)*$L43, "") -> 0 | AH43: =IFERROR(($J43*U43)*$L43, "") -> 0 | AI43: =IFERROR(($J43*V43)*$L43, "") -> 0 | ... AM43: =IFERROR(($J43*Z43)*$L43, "") -> 0 | AN43: =IFERROR(SUMIF($AB$4:$AM$4, "RDEC", AB43:AM43), "") -> 0 | AO43: =IFERROR(SUMIF($AB$4:$AM$4, "SME", AB43:AM43), "") -> 5932.87 | AP43: =IFERROR(SUMIF($AB$4:$AM$4, "De Minimis", AB43:AM43), "") -> 0 | AR43: =IFERROR(($J43*O43)*$M43, "") -> 0 | AS43: =IFERROR(($J43*P43)*$M43, "") -> 0 | AT43: =IFERROR(($J43*Q43)*$M43, "") -> 0 | AU43: =IFERROR(($J43*R43)*$M43, "") -> 0 | AV43: =IFERROR(($J43*S43)*$M43, "") -> 0 | AW43: =IFERROR(($J43*T43)*$M43, "") -> 0 | AX43: =IFERROR(($J43*U43)*$M43, "") -> 0 | AY43: =IFERROR(($J43*V43)*$M43, "") -> 0 | ... BC43: =IFERROR(($J43*Z43)*$M43, "") -> 0 | BD43: =IFERROR(SUMIF($AB$4:$AM$4, "RDEC", AR43:BC43), "") -> 0 | BE43: =IFERROR(SUMIF($AB$4:$AM$4, "SME", AR43:BC43), "") -> 0 | BF43: =IFERROR(SUMIF($AB$4:$AM$4, "De Minimis", AR43:BC43), "") -> 0 | BH43: =IF((SUM(O43:Z43)>1),"ERROR","") | BJ43: =IF(C29>0, C29, "")
D44: =D28 -> 45413 | E44: 5145.36 | F44: 1389.25 | G44: 350.96 | H44: 605.41 | I44: 257.27 | J44: =E44+H44+I44 -> 6008.04 | L44: 1 | M44: =1-L44 -> 0 | O44: 0.5 | P44: 0.3 | Q44: 0.2 | AB44: =IFERROR(($J44*O44)*$L44, "") -> 3004.02 | AC44: =IFERROR(($J44*P44)*$L44, "") -> 1802.412 | AD44: =IFERROR(($J44*Q44)*$L44, "") -> 1201.608 | AE44: =IFERROR(($J44*R44)*$L44, "") -> 0 | AF44: =IFERROR(($J44*S44)*$L44, "") -> 0 | AG44: =IFERROR(($J44*T44)*$L44, "") -> 0 | AH44: =IFERROR(($J44*U44)*$L44, "") -> 0 | AI44: =IFERROR(($J44*V44)*$L44, "") -> 0 | ... AM44: =IFERROR(($J44*Z44)*$L44, "") -> 0 | AN44: =IFERROR(SUMIF($AB$4:$AM$4, "RDEC", AB44:AM44), "") -> 0 | AO44: =IFERROR(SUMIF($AB$4:$AM$4, "SME", AB44:AM44), "") -> 6008.04 | AP44: =IFERROR(SUMIF($AB$4:$AM$4, "De Minimis", AB44:AM44), "") -> 0 | AR44: =IFERROR(($J44*O44)*$M44, "") -> 0 | AS44: =IFERROR(($J44*P44)*$M44, "") -> 0 | AT44: =IFERROR(($J44*Q44)*$M44, "") -> 0 | AU44: =IFERROR(($J44*R44)*$M44, "") -> 0 | AV44: =IFERROR(($J44*S44)*$M44, "") -> 0 | AW44: =IFERROR(($J44*T44)*$M44, "") -> 0 | AX44: =IFERROR(($J44*U44)*$M44, "") -> 0 | AY44: =IFERROR(($J44*V44)*$M44, "") -> 0 | ... BC44: =IFERROR(($J44*Z44)*$M44, "") -> 0 | BD44: =IFERROR(SUMIF($AB$4:$AM$4, "RDEC", AR44:BC44), "") -> 0 | BE44: =IFERROR(SUMIF($AB$4:$AM$4, "SME", AR44:BC44), "") -> 0 | BF44: =IFERROR(SUMIF($AB$4:$AM$4, "De Minimis", AR44:BC44), "") -> 0 | BH44: =IF((SUM(O44:Z44)>1),"ERROR","") | BJ44: =IF(C30>0, C30, "")
D45: =D29 -> 45444 | E45: 5153.12 | F45: 1391.34 | G45: 351.58 | H45: 606.48 | I45: 257.66 | J45: =E45+H45+I45 -> 6017.26 | L45: 1 | M45: =1-L45 -> 0 | O45: 0.5 | P45: 0.3 | Q45: 0.2 | AB45: =IFERROR(($J45*O45)*$L45, "") -> 3008.63 | AC45: =IFERROR(($J45*P45)*$L45, "") -> 1805.178 | AD45: =IFERROR(($J45*Q45)*$L45, "") -> 1203.452 | AE45: =IFERROR(($J45*R45)*$L45, "") -> 0 | AF45: =IFERROR(($J45*S45)*$L45, "") -> 0 | AG45: =IFERROR(($J45*T45)*$L45, "") -> 0 | AH45: =IFERROR(($J45*U45)*$L45, "") -> 0 | AI45: =IFERROR(($J45*V45)*$L45, "") -> 0 | ... AM45: =IFERROR(($J45*Z45)*$L45, "") -> 0 | AN45: =IFERROR(SUMIF($AB$4:$AM$4, "RDEC", AB45:AM45), "") -> 0 | AO45: =IFERROR(SUMIF($AB$4:$AM$4, "SME", AB45:AM45), "") -> 6017.26 | AP45: =IFERROR(SUMIF($AB$4:$AM$4, "De Minimis", AB45:AM45), "") -> 0 | AR45: =IFERROR(($J45*O45)*$M45, "") -> 0 | AS45: =IFERROR(($J45*P45)*$M45, "") -> 0 | AT45: =IFERROR(($J45*Q45)*$M45, "") -> 0 | AU45: =IFERROR(($J45*R45)*$M45, "") -> 0 | AV45: =IFERROR(($J45*S45)*$M45, "") -> 0 | AW45: =IFERROR(($J45*T45)*$M45, "") -> 0 | AX45: =IFERROR(($J45*U45)*$M45, "") -> 0 | AY45: =IFERROR(($J45*V45)*$M45, "") -> 0 | ... BC45: =IFERROR(($J45*Z45)*$M45, "") -> 0 | BD45: =IFERROR(SUMIF($AB$4:$AM$4, "RDEC", AR45:BC45), "") -> 0 | BE45: =IFERROR(SUMIF($AB$4:$AM$4, "SME", AR45:BC45), "") -> 0 | BF45: =IFERROR(SUMIF($AB$4:$AM$4, "De Minimis", AR45:BC45), "") -> 0 | BH45: =IF((SUM(O45:Z45)>1),"ERROR","") | BJ45: =IF(C31>0, C31, "")
D46: =D30 -> 45474 | E46: 5065.12 | F46: 1367.58 | G46: 344.54 | H46: 594.34 | I46: 253.26 | J46: =E46+H46+I46 -> 5912.72 | L46: 1 | M46: =1-L46 -> 0 | O46: 0.5 | P46: 0.3 | Q46: 0.2 | AB46: =IFERROR(($J46*O46)*$L46, "") -> 2956.36 | AC46: =IFERROR(($J46*P46)*$L46, "") -> 1773.816 | AD46: =IFERROR(($J46*Q46)*$L46, "") -> 1182.544 | AE46: =IFERROR(($J46*R46)*$L46, "") -> 0 | AF46: =IFERROR(($J46*S46)*$L46, "") -> 0 | AG46: =IFERROR(($J46*T46)*$L46, "") -> 0 | AH46: =IFERROR(($J46*U46)*$L46, "") -> 0 | AI46: =IFERROR(($J46*V46)*$L46, "") -> 0 | ... AM46: =IFERROR(($J46*Z46)*$L46, "") -> 0 | AN46: =IFERROR(SUMIF($AB$4:$AM$4, "RDEC", AB46:AM46), "") -> 0 | AO46: =IFERROR(SUMIF($AB$4:$AM$4, "SME", AB46:AM46), "") -> 5912.72 | AP46: =IFERROR(SUMIF($AB$4:$AM$4, "De Minimis", AB46:AM46), "") -> 0 | AR46: =IFERROR(($J46*O46)*$M46, "") -> 0 | AS46: =IFERROR(($J46*P46)*$M46, "") -> 0 | AT46: =IFERROR(($J46*Q46)*$M46, "") -> 0 | AU46: =IFERROR(($J46*R46)*$M46, "") -> 0 | AV46: =IFERROR(($J46*S46)*$M46, "") -> 0 | AW46: =IFERROR(($J46*T46)*$M46, "") -> 0 | AX46: =IFERROR(($J46*U46)*$M46, "") -> 0 | AY46: =IFERROR(($J46*V46)*$M46, "") -> 0 | ... BC46: =IFERROR(($J46*Z46)*$M46, "") -> 0 | BD46: =IFERROR(SUMIF($AB$4:$AM$4, "RDEC", AR46:BC46), "") -> 0 | BE46: =IFERROR(SUMIF($AB$4:$AM$4, "SME", AR46:BC46), "") -> 0 | BF46: =IFERROR(SUMIF($AB$4:$AM$4, "De Minimis", AR46:BC46), "") -> 0 | BH46: =IF((SUM(O46:Z46)>1),"ERROR","") | BJ46: =IF(C32>0, C32, "")
D47: =D31 -> 45505 | E47: 5167.91 | F47: 1395.34 | G47: 352.77 | H47: 608.52 | I47: 258.4 | J47: =E47+H47+I47 -> 6034.83 | L47: 1 | M47: =1-L47 -> 0 | O47: 0.5 | P47: 0.3 | Q47: 0.2 | AB47: =IFERROR(($J47*O47)*$L47, "") -> 3017.415 | AC47: =IFERROR(($J47*P47)*$L47, "") -> 1810.449 | AD47: =IFERROR(($J47*Q47)*$L47, "") -> 1206.966 | AE47: =IFERROR(($J47*R47)*$L47, "") -> 0 | AF47: =IFERROR(($J47*S47)*$L47, "") -> 0 | AG47: =IFERROR(($J47*T47)*$L47, "") -> 0 | AH47: =IFERROR(($J47*U47)*$L47, "") -> 0 | AI47: =IFERROR(($J47*V47)*$L47, "") -> 0 | ... AM47: =IFERROR(($J47*Z47)*$L47, "") -> 0 | AN47: =IFERROR(SUMIF($AB$4:$AM$4, "RDEC", AB47:AM47), "") -> 0 | AO47: =IFERROR(SUMIF($AB$4:$AM$4, "SME", AB47:AM47), "") -> 6034.83 | AP47: =IFERROR(SUMIF($AB$4:$AM$4, "De Minimis", AB47:AM47), "") -> 0 | AR47: =IFERROR(($J47*O47)*$M47, "") -> 0 | AS47: =IFERROR(($J47*P47)*$M47, "") -> 0 | AT47: =IFERROR(($J47*Q47)*$M47, "") -> 0 | AU47: =IFERROR(($J47*R47)*$M47, "") -> 0 | AV47: =IFERROR(($J47*S47)*$M47, "") -> 0 | AW47: =IFERROR(($J47*T47)*$M47, "") -> 0 | AX47: =IFERROR(($J47*U47)*$M47, "") -> 0 | AY47: =IFERROR(($J47*V47)*$M47, "") -> 0 | ... BC47: =IFERROR(($J47*Z47)*$M47, "") -> 0 | BD47: =IFERROR(SUMIF($AB$4:$AM$4, "RDEC", AR47:BC47), "") -> 0 | BE47: =IFERROR(SUMIF($AB$4:$AM$4, "SME", AR47:BC47), "") -> 0 | BF47: =IFERROR(SUMIF($AB$4:$AM$4, "De Minimis", AR47:BC47), "") -> 0 | BH47: =IF((SUM(O47:Z47)>1),"ERROR","") | BJ47: =IF(C33>0, C33, "")
D48: =D32 -> 45536 | E48: 5121.01 | F48: 1382.67 | G48: 349.01 | H48: 602.05 | I48: 256.05 | J48: =E48+H48+I48 -> 5979.11 | L48: 1 | M48: =1-L48 -> 0 | O48: 0.5 | P48: 0.3 | Q48: 0.2 | AB48: =IFERROR(($J48*O48)*$L48, "") -> 2989.555 | AC48: =IFERROR(($J48*P48)*$L48, "") -> 1793.733 | AD48: =IFERROR(($J48*Q48)*$L48, "") -> 1195.822 | AE48: =IFERROR(($J48*R48)*$L48, "") -> 0 | AF48: =IFERROR(($J48*S48)*$L48, "") -> 0 | AG48: =IFERROR(($J48*T48)*$L48, "") -> 0 | AH48: =IFERROR(($J48*U48)*$L48, "") -> 0 | AI48: =IFERROR(($J48*V48)*$L48, "") -> 0 | ... AM48: =IFERROR(($J48*Z48)*$L48, "") -> 0 | AN48: =IFERROR(SUMIF($AB$4:$AM$4, "RDEC", AB48:AM48), "") -> 0 | AO48: =IFERROR(SUMIF($AB$4:$AM$4, "SME", AB48:AM48), "") -> 5979.11 | AP48: =IFERROR(SUMIF($AB$4:$AM$4, "De Minimis", AB48:AM48), "") -> 0 | AR48: =IFERROR(($J48*O48)*$M48, "") -> 0 | AS48: =IFERROR(($J48*P48)*$M48, "") -> 0 | AT48: =IFERROR(($J48*Q48)*$M48, "") -> 0 | AU48: =IFERROR(($J48*R48)*$M48, "") -> 0 | AV48: =IFERROR(($J48*S48)*$M48, "") -> 0 | AW48: =IFERROR(($J48*T48)*$M48, "") -> 0 | AX48: =IFERROR(($J48*U48)*$M48, "") -> 0 | AY48: =IFERROR(($J48*V48)*$M48, "") -> 0 | ... BC48: =IFERROR(($J48*Z48)*$M48, "") -> 0 | BD48: =IFERROR(SUMIF($AB$4:$AM$4, "RDEC", AR48:BC48), "") -> 0 | BE48: =IFERROR(SUMIF($AB$4:$AM$4, "SME", AR48:BC48), "") -> 0 | BF48: =IFERROR(SUMIF($AB$4:$AM$4, "De Minimis", AR48:BC48), "") -> 0 | BH48: =IF((SUM(O48:Z48)>1),"ERROR","") | BJ48: =IF(C34>0, C34, "")
D49: =D33 -> 45566 | E49: 5178.46 | F49: 1398.18 | G49: 353.61 | H49: 609.98 | I49: 258.92 | J49: =E49+H49+I49 -> 6047.36 | L49: 1 | M49: =1-L49 -> 0 | O49: 0.5 | P49: 0.3 | Q49: 0.2 | AB49: =IFERROR(($J49*O49)*$L49, "") -> 3023.68 | AC49: =IFERROR(($J49*P49)*$L49, "") -> 1814.208 | AD49: =IFERROR(($J49*Q49)*$L49, "") -> 1209.472 | AE49: =IFERROR(($J49*R49)*$L49, "") -> 0 | AF49: =IFERROR(($J49*S49)*$L49, "") -> 0 | AG49: =IFERROR(($J49*T49)*$L49, "") -> 0 | AH49: =IFERROR(($J49*U49)*$L49, "") -> 0 | AI49: =IFERROR(($J49*V49)*$L49, "") -> 0 | ... AM49: =IFERROR(($J49*Z49)*$L49, "") -> 0 | AN49: =IFERROR(SUMIF($AB$4:$AM$4, "RDEC", AB49:AM49), "") -> 0 | AO49: =IFERROR(SUMIF($AB$4:$AM$4, "SME", AB49:AM49), "") -> 6047.36 | AP49: =IFERROR(SUMIF($AB$4:$AM$4, "De Minimis", AB49:AM49), "") -> 0 | AR49: =IFERROR(($J49*O49)*$M49, "") -> 0 | AS49: =IFERROR(($J49*P49)*$M49, "") -> 0 | AT49: =IFERROR(($J49*Q49)*$M49, "") -> 0 | AU49: =IFERROR(($J49*R49)*$M49, "") -> 0 | AV49: =IFERROR(($J49*S49)*$M49, "") -> 0 | AW49: =IFERROR(($J49*T49)*$M49, "") -> 0 | AX49: =IFERROR(($J49*U49)*$M49, "") -> 0 | AY49: =IFERROR(($J49*V49)*$M49, "") -> 0 | ... BC49: =IFERROR(($J49*Z49)*$M49, "") -> 0 | BD49: =IFERROR(SUMIF($AB$4:$AM$4, "RDEC", AR49:BC49), "") -> 0 | BE49: =IFERROR(SUMIF($AB$4:$AM$4, "SME", AR49:BC49), "") -> 0 | BF49: =IFERROR(SUMIF($AB$4:$AM$4, "De Minimis", AR49:BC49), "") -> 0 | BH49: =IF((SUM(O49:Z49)>1),"ERROR","") | BJ49: =IF(C35>0, C35, "")
D50: =D34 -> 45597 | E50: 5142.84 | F50: 1388.57 | G50: 350.76 | H50: 605.06 | I50: 257.14 | J50: =E50+H50+I50 -> 6005.04 | L50: 1 | M50: =1-L50 -> 0 | O50: 0.5 | P50: 0.3 | Q50: 0.2 | AB50: =IFERROR(($J50*O50)*$L50, "") -> 3002.52 | AC50: =IFERROR(($J50*P50)*$L50, "") -> 1801.512 | AD50: =IFERROR(($J50*Q50)*$L50, "") -> 1201.008 | AE50: =IFERROR(($J50*R50)*$L50, "") -> 0 | AF50: =IFERROR(($J50*S50)*$L50, "") -> 0 | AG50: =IFERROR(($J50*T50)*$L50, "") -> 0 | AH50: =IFERROR(($J50*U50)*$L50, "") -> 0 | AI50: =IFERROR(($J50*V50)*$L50, "") -> 0 | ... AM50: =IFERROR(($J50*Z50)*$L50, "") -> 0 | AN50: =IFERROR(SUMIF($AB$4:$AM$4, "RDEC", AB50:AM50), "") -> 0 | AO50: =IFERROR(SUMIF($AB$4:$AM$4, "SME", AB50:AM50), "") -> 6005.04 | AP50: =IFERROR(SUMIF($AB$4:$AM$4, "De Minimis", AB50:AM50), "") -> 0 | AR50: =IFERROR(($J50*O50)*$M50, "") -> 0 | AS50: =IFERROR(($J50*P50)*$M50, "") -> 0 | AT50: =IFERROR(($J50*Q50)*$M50, "") -> 0 | AU50: =IFERROR(($J50*R50)*$M50, "") -> 0 | AV50: =IFERROR(($J50*S50)*$M50, "") -> 0 | AW50: =IFERROR(($J50*T50)*$M50, "") -> 0 | AX50: =IFERROR(($J50*U50)*$M50, "") -> 0 | AY50: =IFERROR(($J50*V50)*$M50, "") -> 0 | ... BC50: =IFERROR(($J50*Z50)*$M50, "") -> 0 | BD50: =IFERROR(SUMIF($AB$4:$AM$4, "RDEC", AR50:BC50), "") -> 0 | BE50: =IFERROR(SUMIF($AB$4:$AM$4, "SME", AR50:BC50), "") -> 0 | BF50: =IFERROR(SUMIF($AB$4:$AM$4, "De Minimis", AR50:BC50), "") -> 0 | BH50: =IF((SUM(O50:Z50)>1),"ERROR","") | BJ50: =IF(C36>0, C36, "")
D51: =D35 -> 45627 | E51: 5180.08 | F51: 1398.62 | G51: 353.74 | H51: 610.2 | I51: 259 | J51: =E51+H51+I51 -> 6049.28 | L51: 1 | M51: =1-L51 -> 0 | O51: 0.5 | P51: 0.3 | Q51: 0.2 | AB51: =IFERROR(($J51*O51)*$L51, "") -> 3024.64 | AC51: =IFERROR(($J51*P51)*$L51, "") -> 1814.784 | AD51: =IFERROR(($J51*Q51)*$L51, "") -> 1209.856 | AE51: =IFERROR(($J51*R51)*$L51, "") -> 0 | AF51: =IFERROR(($J51*S51)*$L51, "") -> 0 | AG51: =IFERROR(($J51*T51)*$L51, "") -> 0 | AH51: =IFERROR(($J51*U51)*$L51, "") -> 0 | AI51: =IFERROR(($J51*V51)*$L51, "") -> 0 | ... AM51: =IFERROR(($J51*Z51)*$L51, "") -> 0 | AN51: =IFERROR(SUMIF($AB$4:$AM$4, "RDEC", AB51:AM51), "") -> 0 | AO51: =IFERROR(SUMIF($AB$4:$AM$4, "SME", AB51:AM51), "") -> 6049.28 | AP51: =IFERROR(SUMIF($AB$4:$AM$4, "De Minimis", AB51:AM51), "") -> 0 | AR51: =IFERROR(($J51*O51)*$M51, "") -> 0 | AS51: =IFERROR(($J51*P51)*$M51, "") -> 0 | AT51: =IFERROR(($J51*Q51)*$M51, "") -> 0 | AU51: =IFERROR(($J51*R51)*$M51, "") -> 0 | AV51: =IFERROR(($J51*S51)*$M51, "") -> 0 | AW51: =IFERROR(($J51*T51)*$M51, "") -> 0 | AX51: =IFERROR(($J51*U51)*$M51, "") -> 0 | AY51: =IFERROR(($J51*V51)*$M51, "") -> 0 | ... BC51: =IFERROR(($J51*Z51)*$M51, "") -> 0 | BD51: =IFERROR(SUMIF($AB$4:$AM$4, "RDEC", AR51:BC51), "") -> 0 | BE51: =IFERROR(SUMIF($AB$4:$AM$4, "SME", AR51:BC51), "") -> 0 | BF51: =IFERROR(SUMIF($AB$4:$AM$4, "De Minimis", AR51:BC51), "") -> 0 | BH51: =IF((SUM(O51:Z51)>1),"ERROR","") | BJ51: =IF(C37>0, C37, "")
D52: Total | E52: =SUM(E39:E51) -> 61607.16 | F52: =SUM(F39:F51) -> 16633.93 | G52: =SUM(G39:G51) -> 4200.56 | H52: =SUM(H39:H51) -> 7245.99 | I52: =SUM(I39:I51) -> 3080.36 | J52: =SUM(J39:J51) -> 71933.51 | L52: =AVERAGE(L39:L51) -> 1 | M52: =AVERAGE(M39:M51) -> 0 | O52: =IF(SUM(O40:O51)>0,((AB52+AR52)/J52),0) -> 0.5 | P52: =IF(SUM(P40:P51)>0,((AC52+AS52)/J52),0) -> 0.3 | Q52: =IF(SUM(Q40:Q51)>0,((AD52+AT52)/J52),0) -> 0.2 | R52: =IF(SUM(R40:R51)>0,((AE52+AU52)/J52),0) -> 0 | S52: =IF(SUM(S40:S51)>0,((AF52+AV52)/J52),0) -> 0 | T52: =IF(SUM(T40:T51)>0,((AG52+AW52)/J52),0) -> 0 | U52: =IF(SUM(U40:U51)>0,((AH52+AX52)/J52),0) -> 0 | V52: =IF(SUM(V40:V51)>0,((AI52+AY52)/J52),0) -> 0 | W52: =IF(SUM(W40:W51)>0,((AJ52+AZ52)/J52),0) -> 0 | X52: =IF(SUM(X40:X51)>0,((AK52+BA52)/J52),0) -> 0 | Y52: =IF(SUM(Y40:Y51)>0,((AL52+BB52)/J52),0) -> 0 | Z52: =IF(SUM(Z40:Z51)>0,((AM52+BC52)/J52),0) -> 0 | AB52: =SUM(AB39:AB51) -> 35966.755 | AC52: =SUM(AC39:AC51) -> 21580.053 | AD52: =SUM(AD39:AD51) -> 14386.702 | AE52: =SUM(AE39:AE51) -> 0 | AF52: =SUM(AF39:AF51) -> 0 | AG52: =SUM(AG39:AG51) -> 0 | AH52: =SUM(AH39:AH51) -> 0 | AI52: =SUM(AI39:AI51) -> 0 | ... AP52: =SUM(AP39:AP51) -> 0 | AR52: =SUM(AR39:AR51) -> 0 | AS52: =SUM(AS39:AS51) -> 0 | AT52: =SUM(AT39:AT51) -> 0 | AU52: =SUM(AU39:AU51) -> 0 | AV52: =SUM(AV39:AV51) -> 0 | AW52: =SUM(AW39:AW51) -> 0 | AX52: =SUM(AX39:AX51) -> 0 | AY52: =SUM(AY39:AY51) -> 0 | ... BF52: =SUM(BF39:BF51) -> 0 | BJ52: =IF(C38>0, C38, "") -> Backend Developer | BK52: N | BL52: =IF($BK52="Y",J52,0) -> 0 | BM52: =IF(BK52="Y", AN52,0) -> 0 | BN52: =IF((BK52="Y"),AO52,0) -> 0
BJ53: =IF(C39>0, C39, "")
A54: 4 | B54: Emma Whitfield | C54: Data Scientist | BJ54: =IF(C41>0, C41, "")
D56: =D40 -> 45292 | E56: 5688.81 | F56: 1535.98 | G56: 394.44 | H56: 680.41 | I56: 284.44 | J56: =E56+H56+I56 -> 6653.66 | L56: 1 | M56: =1-L56 -> 0 | P56: 0.4 | R56: 0.35 | S56: 0.25 | AB56: =IFERROR(($J56*O56)*$L56, "") -> 0 | AC56: =IFERROR(($J56*P56)*$L56, "") -> 2661.464 | AD56: =IFERROR(($J56*Q56)*$L56, "") -> 0 | AE56: =IFERROR(($J56*R56)*$L56, "") -> 2328.781 | AF56: =IFERROR(($J56*S56)*$L56, "") -> 1663.415 | AG56: =IFERROR(($J56*T56)*$L56, "") -> 0 | AH56: =IFERROR(($J56*U56)*$L56, "") -> 0 | AI56: =IFERROR(($J56*V56)*$L56, "") -> 0 | ... AM56: =IFERROR(($J56*Z56)*$L56, "") -> 0 | AN56: =IFERROR(SUMIF($AB$4:$AM$4, "RDEC", AB56:AM56), "") -> 2328.781 | AO56: =IFERROR(SUMIF($AB$4:$AM$4, "SME", AB56:AM56), "") -> 4324.879 | AP56: =IFERROR(SUMIF($AB$4:$AM$4, "De Minimis", AB56:AM56), "") -> 0 | AR56: =IFERROR(($J56*O56)*$M56, "") -> 0 | AS56: =IFERROR(($J56*P56)*$M56, "") -> 0 | AT56: =IFERROR(($J56*Q56)*$M56, "") -> 0 | AU56: =IFERROR(($J56*R56)*$M56, "") -> 0 | AV56: =IFERROR(($J56*S56)*$M56, "") -> 0 | AW56: =IFERROR(($J56*T56)*$M56, "") -> 0 | AX56: =IFERROR(($J56*U56)*$M56, "") -> 0 | AY56: =IFERROR(($J56*V56)*$M56, "") -> 0 | ... BC56: =IFERROR(($J56*Z56)*$M56, "") -> 0 | BD56: =IFERROR(SUMIF($AB$4:$AM$4, "RDEC", AR56:BC56), "") -> 0 | BE56: =IFERROR(SUMIF($AB$4:$AM$4, "SME", AR56:BC56), "") -> 0 | BF56: =IFERROR(SUMIF($AB$4:$AM$4, "De Minimis", AR56:BC56), "") -> 0 | BH56: =IF((SUM(O56:Z56)>1),"ERROR","") | BJ56: =IF(C42>0, C42, "")
D57: =D41 -> 45323 | E57: 5643.72 | F57: 1523.8 | G57: 390.83 | H57: 674.18 | I57: 282.19 | J57: =E57+H57+I57 -> 6600.09 | L57: 1 | M57: =1-L57 -> 0 | P57: 0.4 | R57: 0.35 | S57: 0.25 | AB57: =IFERROR(($J57*O57)*$L57, "") -> 0 | AC57: =IFERROR(($J57*P57)*$L57, "") -> 2640.036 | AD57: =IFERROR(($J57*Q57)*$L57, "") -> 0 | AE57: =IFERROR(($J57*R57)*$L57, "") -> 2310.0315 | AF57: =IFERROR(($J57*S57)*$L57, "") -> 1650.0225 | AG57: =IFERROR(($J57*T57)*$L57, "") -> 0 | AH57: =IFERROR(($J57*U57)*$L57, "") -> 0 | AI57: =IFERROR(($J57*V57)*$L57, "") -> 0 | ... AM57: =IFERROR(($J57*Z57)*$L57, "") -> 0 | AN57: =IFERROR(SUMIF($AB$4:$AM$4, "RDEC", AB57:AM57), "") -> 2310.0315 | AO57: =IFERROR(SUMIF($AB$4:$AM$4, "SME", AB57:AM57), "") -> 4290.0585 | AP57: =IFERROR(SUMIF($AB$4:$AM$4, "De Minimis", AB57:AM57), "") -> 0 | AR57: =IFERROR(($J57*O57)*$M57, "") -> 0 | AS57: =IFERROR(($J57*P57)*$M57, "") -> 0 | AT57: =IFERROR(($J57*Q57)*$M57, "") -> 0 | AU57: =IFERROR(($J57*R57)*$M57, "") -> 0 | AV57: =IFERROR(($J57*S57)*$M57, "") -> 0 | AW57: =IFERROR(($J57*T57)*$M57, "") -> 0 | AX57: =IFERROR(($J57*U57)*$M57, "") -> 0 | AY57: =IFERROR(($J57*V57)*$M57, "") -> 0 | ... BC57: =IFERROR(($J57*Z57)*$M57, "") -> 0 | BD57: =IFERROR(SUMIF($AB$4:$AM$4, "RDEC", AR57:BC57), "") -> 0 | BE57: =IFERROR(SUMIF($AB$4:$AM$4, "SME", AR57:BC57), "") -> 0 | BF57: =IFERROR(SUMIF($AB$4:$AM$4, "De Minimis", AR57:BC57), "") -> 0 | BH57: =IF((SUM(O57:Z57)>1),"ERROR","") | BJ57: =IF(C43>0, C43, "")
D58: =D42 -> 45352 | E58: 5772.12 | F58: 1558.47 | G58: 401.1 | H58: 691.9 | I58: 288.61 | J58: =E58+H58+I58 -> 6752.63 | L58: 1 | M58: =1-L58 -> 0 | P58: 0.4 | R58: 0.35 | S58: 0.25 | AB58: =IFERROR(($J58*O58)*$L58, "") -> 0 | AC58: =IFERROR(($J58*P58)*$L58, "") -> 2701.052 | AD58: =IFERROR(($J58*Q58)*$L58, "") -> 0 | AE58: =IFERROR(($J58*R58)*$L58, "") -> 2363.4205 | AF58: =IFERROR(($J58*S58)*$L58, "") -> 1688.1575 | AG58: =IFERROR(($J58*T58)*$L58, "") -> 0 | AH58: =IFERROR(($J58*U58)*$L58, "") -> 0 | AI58: =IFERROR(($J58*V58)*$L58, "") -> 0 | ... AM58: =IFERROR(($J58*Z58)*$L58, "") -> 0 | AN58: =IFERROR(SUMIF($AB$4:$AM$4, "RDEC", AB58:AM58), "") -> 2363.4205 | AO58: =IFERROR(SUMIF($AB$4:$AM$4, "SME", AB58:AM58), "") -> 4389.2095 | AP58: =IFERROR(SUMIF($AB$4:$AM$4, "De Minimis", AB58:AM58), "") -> 0 | AR58: =IFERROR(($J58*O58)*$M58, "") -> 0 | AS58: =IFERROR(($J58*P58)*$M58, "") -> 0 | AT58: =IFERROR(($J58*Q58)*$M58, "") -> 0 | AU58: =IFERROR(($J58*R58)*$M58, "") -> 0 | AV58: =IFERROR(($J58*S58)*$M58, "") -> 0 | AW58: =IFERROR(($J58*T58)*$M58, "") -> 0 | AX58: =IFERROR(($J58*U58)*$M58, "") -> 0 | AY58: =IFERROR(($J58*V58)*$M58, "") -> 0 | ... BC58: =IFERROR(($J58*Z58)*$M58, "") -> 0 | BD58: =IFERROR(SUMIF($AB$4:$AM$4, "RDEC", AR58:BC58), "") -> 0 | BE58: =IFERROR(SUMIF($AB$4:$AM$4, "SME", AR58:BC58), "") -> 0 | BF58: =IFERROR(SUMIF($AB$4:$AM$4, "De Minimis", AR58:BC58), "") -> 0 | BH58: =IF((SUM(O58:Z58)>1),"ERROR","") | BJ58: =IF(C44>0, C44, "")
D59: =D43 -> 45383 | E59: 5560.51 | F59: 1501.34 | G59: 384.17 | H59: 662.7 | I59: 278.03 | J59: =E59+H59+I59 -> 6501.24 | L59: 1 | M59: =1-L59 -> 0 | P59: 0.4 | R59: 0.35 | S59: 0.25 | AB59: =IFERROR(($J59*O59)*$L59, "") -> 0 | AC59: =IFERROR(($J59*P59)*$L59, "") -> 2600.496 | AD59: =IFERROR(($J59*Q59)*$L59, "") -> 0 | AE59: =IFERROR(($J59*R59)*$L59, "") -> 2275.434 | AF59: =IFERROR(($J59*S59)*$L59, "") -> 1625.31 | AG59: =IFERROR(($J59*T59)*$L59, "") -> 0 | AH59: =IFERROR(($J59*U59)*$L59, "") -> 0 | AI59: =IFERROR(($J59*V59)*$L59, "") -> 0 | ... AM59: =IFERROR(($J59*Z59)*$L59, "") -> 0 | AN59: =IFERROR(SUMIF($AB$4:$AM$4, "RDEC", AB59:AM59), "") -> 2275.434 | AO59: =IFERROR(SUMIF($AB$4:$AM$4, "SME", AB59:AM59), "") -> 4225.806 | AP59: =IFERROR(SUMIF($AB$4:$AM$4, "De Minimis", AB59:AM59), "") -> 0 | AR59: =IFERROR(($J59*O59)*$M59, "") -> 0 | AS59: =IFERROR(($J59*P59)*$M59, "") -> 0 | AT59: =IFERROR(($J59*Q59)*$M59, "") -> 0 | AU59: =IFERROR(($J59*R59)*$M59, "") -> 0 | AV59: =IFERROR(($J59*S59)*$M59, "") -> 0 | AW59: =IFERROR(($J59*T59)*$M59, "") -> 0 | AX59: =IFERROR(($J59*U59)*$M59, "") -> 0 | AY59: =IFERROR(($J59*V59)*$M59, "") -> 0 | ... BC59: =IFERROR(($J59*Z59)*$M59, "") -> 0 | BD59: =IFERROR(SUMIF($AB$4:$AM$4, "RDEC", AR59:BC59), "") -> 0 | BE59: =IFERROR(SUMIF($AB$4:$AM$4, "SME", AR59:BC59), "") -> 0 | BF59: =IFERROR(SUMIF($AB$4:$AM$4, "De Minimis", AR59:BC59), "") -> 0 | BH59: =IF((SUM(O59:Z59)>1),"ERROR","") | BJ59: =IF(C45>0, C45, "")
D60: =D44 -> 45413 | E60: 5583.68 | F60: 1507.59 | G60: 386.03 | H60: 665.9 | I60: 279.18 | J60: =E60+H60+I60 -> 6528.76 | L60: 1 | M60: =1-L60 -> 0 | P60: 0.4 | R60: 0.35 | S60: 0.25 | AB60: =IFERROR(($J60*O60)*$L60, "") -> 0 | AC60: =IFERROR(($J60*P60)*$L60, "") -> 2611.504 | AD60: =IFERROR(($J60*Q60)*$L60, "") -> 0 | AE60: =IFERROR(($J60*R60)*$L60, "") -> 2285.066 | AF60: =IFERROR(($J60*S60)*$L60, "") -> 1632.19 | AG60: =IFERROR(($J60*T60)*$L60, "") -> 0 | AH60: =IFERROR(($J60*U60)*$L60, "") -> 0 | AI60: =IFERROR(($J60*V60)*$L60, "") -> 0 | ... AM60: =IFERROR(($J60*Z60)*$L60, "") -> 0 | AN60: =IFERROR(SUMIF($AB$4:$AM$4, "RDEC", AB60:AM60), "") -> 2285.066 | AO60: =IFERROR(SUMIF($AB$4:$AM$4, "SME", AB60:AM60), "") -> 4243.694 | AP60: =IFERROR(SUMIF($AB$4:$AM$4, "De Minimis", AB60:AM60), "") -> 0 | AR60: =IFERROR(($J60*O60)*$M60, "") -> 0 | AS60: =IFERROR(($J60*P60)*$M60, "") -> 0 | AT60: =IFERROR(($J60*Q60)*$M60, "") -> 0 | AU60: =IFERROR(($J60*R60)*$M60, "") -> 0 | AV60: =IFERROR(($J60*S60)*$M60, "") -> 0 | AW60: =IFERROR(($J60*T60)*$M60, "") -> 0 | AX60: =IFERROR(($J60*U60)*$M60, "") -> 0 | AY60: =IFERROR(($J60*V60)*$M60, "") -> 0 | ... BC60: =IFERROR(($J60*Z60)*$M60, "") -> 0 | BD60: =IFERROR(SUMIF($AB$4:$AM$4, "RDEC", AR60:BC60), "") -> 0 | BE60: =IFERROR(SUMIF($AB$4:$AM$4, "SME", AR60:BC60), "") -> 0 | BF60: =IFERROR(SUMIF($AB$4:$AM$4, "De Minimis", AR60:BC60), "") -> 0 | BH60: =IF((SUM(O60:Z60)>1),"ERROR","") | BJ60: =IF(C46>0, C46, "")
D61: =D45 -> 45444 | E61: 5594.72 | F61: 1510.57 | G61: 386.91 | H61: 667.42 | I61: 279.74 | J61: =E61+H61+I61 -> 6541.88 | L61: 1 | M61: =1-L61 -> 0 | P61: 0.4 | R61: 0.35 | S61: 0.25 | AB61: =IFERROR(($J61*O61)*$L61, "") -> 0 | AC61: =IFERROR(($J61*P61)*$L61, "") -> 2616.752 | AD61: =IFERROR(($J61*Q61)*$L61, "") -> 0 | AE61: =IFERROR(($J61*R61)*$L61, "") -> 2289.658 | AF61: =IFERROR(($J61*S61)*$L61, "") -> 1635.47 | AG61: =IFERROR(($J61*T61)*$L61, "") -> 0 | AH61: =IFERROR(($J61*U61)*$L61, "") -> 0 | AI61: =IFERROR(($J61*V61)*$L61, "") -> 0 | ... AM61: =IFERROR(($J61*Z61)*$L61, "") -> 0 | AN61: =IFERROR(SUMIF($AB$4:$AM$4, "RDEC", AB61:AM61), "") -> 2289.658 | AO61: =IFERROR(SUMIF($AB$4:$AM$4, "SME", AB61:AM61), "") -> 4252.222 | AP61: =IFERROR(SUMIF($AB$4:$AM$4, "De Minimis", AB61:AM61), "") -> 0 | AR61: =IFERROR(($J61*O61)*$M61, "") -> 0 | AS61: =IFERROR(($J61*P61)*$M61, "") -> 0 | AT61: =IFERROR(($J61*Q61)*$M61, "") -> 0 | AU61: =IFERROR(($J61*R61)*$M61, "") -> 0 | AV61: =IFERROR(($J61*S61)*$M61, "") -> 0 | AW61: =IFERROR(($J61*T61)*$M61, "") -> 0 | AX61: =IFERROR(($J61*U61)*$M61, "") -> 0 | AY61: =IFERROR(($J61*V61)*$M61, "") -> 0 | ... BC61: =IFERROR(($J61*Z61)*$M61, "") -> 0 | BD61: =IFERROR(SUMIF($AB$4:$AM$4, "RDEC", AR61:BC61), "") -> 0 | BE61: =IFERROR(SUMIF($AB$4:$AM$4, "SME", AR61:BC61), "") -> 0 | BF61: =IFERROR(SUMIF($AB$4:$AM$4, "De Minimis", AR61:BC61), "") -> 0 | BH61: =IF((SUM(O61:Z61)>1),"ERROR","") | BJ61: =IF(C47>0, C47, "")
D62: =D46 -> 45474 | E62: 5650.77 | F62: 1525.71 | G62: 391.4 | H62: 675.16 | I62: 282.54 | J62: =E62+H62+I62 -> 6608.47 | L62: 1 | M62: =1-L62 -> 0 | P62: 0.4 | R62: 0.35 | S62: 0.25 | AB62: =IFERROR(($J62*O62)*$L62, "") -> 0 | AC62: =IFERROR(($J62*P62)*$L62, "") -> 2643.388 | AD62: =IFERROR(($J62*Q62)*$L62, "") -> 0 | AE62: =IFERROR(($J62*R62)*$L62, "") -> 2312.9645 | AF62: =IFERROR(($J62*S62)*$L62, "") -> 1652.1175 | AG62: =IFERROR(($J62*T62)*$L62, "") -> 0 | AH62: =IFERROR(($J62*U62)*$L62, "") -> 0 | AI62: =IFERROR(($J62*V62)*$L62, "") -> 0 | ... AM62: =IFERROR(($J62*Z62)*$L62, "") -> 0 | AN62: =IFERROR(SUMIF($AB$4:$AM$4, "RDEC", AB62:AM62), "") -> 2312.9645 | AO62: =IFERROR(SUMIF($AB$4:$AM$4, "SME", AB62:AM62), "") -> 4295.5055 | AP62: =IFERROR(SUMIF($AB$4:$AM$4, "De Minimis", AB62:AM62), "") -> 0 | AR62: =IFERROR(($J62*O62)*$M62, "") -> 0 | AS62: =IFERROR(($J62*P62)*$M62, "") -> 0 | AT62: =IFERROR(($J62*Q62)*$M62, "") -> 0 | AU62: =IFERROR(($J62*R62)*$M62, "") -> 0 | AV62: =IFERROR(($J62*S62)*$M62, "") -> 0 | AW62: =IFERROR(($J62*T62)*$M62, "") -> 0 | AX62: =IFERROR(($J62*U62)*$M62, "") -> 0 | AY62: =IFERROR(($J62*V62)*$M62, "") -> 0 | ... BC62: =IFERROR(($J62*Z62)*$M62, "") -> 0 | BD62: =IFERROR(SUMIF($AB$4:$AM$4, "RDEC", AR62:BC62), "") -> 0 | BE62: =IFERROR(SUMIF($AB$4:$AM$4, "SME", AR62:BC62), "") -> 0 | BF62: =IFERROR(SUMIF($AB$4:$AM$4, "De Minimis", AR62:BC62), "") -> 0 | BH62: =IF((SUM(O62:Z62)>1),"ERROR","") | BJ62: =IF(C48>0, C48, "")
D63: =D47 -> 45505 | E63: 5697.89 | F63: 1538.43 | G63: 395.16 | H63: 681.66 | I63: 284.89 | J63: =E63+H63+I63 -> 6664.44 | L63: 1 | M63: =1-L63 -> 0 | P63: 0.4 | R63: 0.35 | S63: 0.25 | AB63: =IFERROR(($J63*O63)*$L63, "") -> 0 | AC63: =IFERROR(($J63*P63)*$L63, "") -> 2665.776 | AD63: =IFERROR(($J63*Q63)*$L63, "") -> 0 | AE63: =IFERROR(($J63*R63)*$L63, "") -> 2332.554 | AF63: =IFERROR(($J63*S63)*$L63, "") -> 1666.11 | AG63: =IFERROR(($J63*T63)*$L63, "") -> 0 | AH63: =IFERROR(($J63*U63)*$L63, "") -> 0 | AI63: =IFERROR(($J63*V63)*$L63, "") -> 0 | ... AM63: =IFERROR(($J63*Z63)*$L63, "") -> 0 | AN63: =IFERROR(SUMIF($AB$4:$AM$4, "RDEC", AB63:AM63), "") -> 2332.554 | AO63: =IFERROR(SUMIF($AB$4:$AM$4, "SME", AB63:AM63), "") -> 4331.886 | AP63: =IFERROR(SUMIF($AB$4:$AM$4, "De Minimis", AB63:AM63), "") -> 0 | AR63: =IFERROR(($J63*O63)*$M63, "") -> 0 | AS63: =IFERROR(($J63*P63)*$M63, "") -> 0 | AT63: =IFERROR(($J63*Q63)*$M63, "") -> 0 | AU63: =IFERROR(($J63*R63)*$M63, "") -> 0 | AV63: =IFERROR(($J63*S63)*$M63, "") -> 0 | AW63: =IFERROR(($J63*T63)*$M63, "") -> 0 | AX63: =IFERROR(($J63*U63)*$M63, "") -> 0 | AY63: =IFERROR(($J63*V63)*$M63, "") -> 0 | ... BC63: =IFERROR(($J63*Z63)*$M63, "") -> 0 | BD63: =IFERROR(SUMIF($AB$4:$AM$4, "RDEC", AR63:BC63), "") -> 0 | BE63: =IFERROR(SUMIF($AB$4:$AM$4, "SME", AR63:BC63), "") -> 0 | BF63: =IFERROR(SUMIF($AB$4:$AM$4, "De Minimis", AR63:BC63), "") -> 0 | BH63: =IF((SUM(O63:Z63)>1),"ERROR","") | BJ63: =IF(C49>0, C49, "")
D64: =D48 -> 45536 | E64: 5595.81 | F64: 1510.87 | G64: 387 | H64: 667.57 | I64: 279.79 | J64: =E64+H64+I64 -> 6543.17 | L64: 1 | M64: =1-L64 -> 0 | P64: 0.4 | R64: 0.35 | S64: 0.25 | AB64: =IFERROR(($J64*O64)*$L64, "") -> 0 | AC64: =IFERROR(($J64*P64)*$L64, "") -> 2617.268 | AD64: =IFERROR(($J64*Q64)*$L64, "") -> 0 | AE64: =IFERROR(($J64*R64)*$L64, "") -> 2290.1095 | AF64: =IFERROR(($J64*S64)*$L64, "") -> 1635.7925 | AG64: =IFERROR(($J64*T64)*$L64, "") -> 0 | AH64: =IFERROR(($J64*U64)*$L64, "") -> 0 | AI64: =IFERROR(($J64*V64)*$L64, "") -> 0 | ... AM64: =IFERROR(($J64*Z64)*$L64, "") -> 0 | AN64: =IFERROR(SUMIF($AB$4:$AM$4, "RDEC", AB64:AM64), "") -> 2290.1095 | AO64: =IFERROR(SUMIF($AB$4:$AM$4, "SME", AB64:AM64), "") -> 4253.0605 | AP64: =IFERROR(SUMIF($AB$4:$AM$4, "De Minimis", AB64:AM64), "") -> 0 | AR64: =IFERROR(($J64*O64)*$M64, "") -> 0 | AS64: =IFERROR(($J64*P64)*$M64, "") -> 0 | AT64: =IFERROR(($J64*Q64)*$M64, "") -> 0 | AU64: =IFERROR(($J64*R64)*$M64, "") -> 0 | AV64: =IFERROR(($J64*S64)*$M64, "") -> 0 | AW64: =IFERROR(($J64*T64)*$M64, "") -> 0 | AX64: =IFERROR(($J64*U64)*$M64, "") -> 0 | AY64: =IFERROR(($J64*V64)*$M64, "") -> 0 | ... BC64: =IFERROR(($J64*Z64)*$M64, "") -> 0 | BD64: =IFERROR(SUMIF($AB$4:$AM$4, "RDEC", AR64:BC64), "") -> 0 | BE64: =IFERROR(SUMIF($AB$4:$AM$4, "SME", AR64:BC64), "") -> 0 | BF64: =IFERROR(SUMIF($AB$4:$AM$4, "De Minimis", AR64:BC64), "") -> 0 | BH64: =IF((SUM(O64:Z64)>1),"ERROR","") | BJ64: =IF(C50>0, C50, "")
D65: =D49 -> 45566 | E65: 5567.72 | F65: 1503.28 | G65: 384.75 | H65: 663.7 | I65: 278.39 | J65: =E65+H65+I65 -> 6509.81 | L65: 1 | M65: =1-L65 -> 0 | P65: 0.4 | R65: 0.35 | S65: 0.25 | AB65: =IFERROR(($J65*O65)*$L65, "") -> 0 | AC65: =IFERROR(($J65*P65)*$L65, "") -> 2603.924 | AD65: =IFERROR(($J65*Q65)*$L65, "") -> 0 | AE65: =IFERROR(($J65*R65)*$L65, "") -> 2278.4335 | AF65: =IFERROR(($J65*S65)*$L65, "") -> 1627.4525 | AG65: =IFERROR(($J65*T65)*$L65, "") -> 0 | AH65: =IFERROR(($J65*U65)*$L65, "") -> 0 | AI65: =IFERROR(($J65*V65)*$L65, "") -> 0 | ... AM65: =IFERROR(($J65*Z65)*$L65, "") -> 0 | AN65: =IFERROR(SUMIF($AB$4:$AM$4, "RDEC", AB65:AM65), "") -> 2278.4335 | AO65: =IFERROR(SUMIF($AB$4:$AM$4, "SME", AB65:AM65), "") -> 4231.3765 | AP65: =IFERROR(SUMIF($AB$4:$AM$4, "De Minimis", AB65:AM65), "") -> 0 | AR65: =IFERROR(($J65*O65)*$M65, "") -> 0 | AS65: =IFERROR(($J65*P65)*$M65, "") -> 0 | AT65: =IFERROR(($J65*Q65)*$M65, "") -> 0 | AU65: =IFERROR(($J65*R65)*$M65, "") -> 0 | AV65: =IFERROR(($J65*S65)*$M65, "") -> 0 | AW65: =IFERROR(($J65*T65)*$M65, "") -> 0 | AX65: =IFERROR(($J65*U65)*$M65, "") -> 0 | AY65: =IFERROR(($J65*V65)*$M65, "") -> 0 | ... BC65: =IFERROR(($J65*Z65)*$M65, "") -> 0 | BD65: =IFERROR(SUMIF($AB$4:$AM$4, "RDEC", AR65:BC65), "") -> 0 | BE65: =IFERROR(SUMIF($AB$4:$AM$4, "SME", AR65:BC65), "") -> 0 | BF65: =IFERROR(SUMIF($AB$4:$AM$4, "De Minimis", AR65:BC65), "") -> 0 | BH65: =IF((SUM(O65:Z65)>1),"ERROR","") | BJ65: =IF(C51>0, C51, "")
D66: =D50 -> 45597 | E66: 5678.24 | F66: 1533.12 | G66: 393.59 | H66: 678.95 | I66: 283.91 | J66: =E66+H66+I66 -> 6641.1 | L66: 1 | M66: =1-L66 -> 0 | P66: 0.4 | R66: 0.35 | S66: 0.25 | AB66: =IFERROR(($J66*O66)*$L66, "") -> 0 | AC66: =IFERROR(($J66*P66)*$L66, "") -> 2656.44 | AD66: =IFERROR(($J66*Q66)*$L66, "") -> 0 | AE66: =IFERROR(($J66*R66)*$L66, "") -> 2324.385 | AF66: =IFERROR(($J66*S66)*$L66, "") -> 1660.275 | AG66: =IFERROR(($J66*T66)*$L66, "") -> 0 | AH66: =IFERROR(($J66*U66)*$L66, "") -> 0 | AI66: =IFERROR(($J66*V66)*$L66, "") -> 0 | ... AM66: =IFERROR(($J66*Z66)*$L66, "") -> 0 | AN66: =IFERROR(SUMIF($AB$4:$AM$4, "RDEC", AB66:AM66), "") -> 2324.385 | AO66: =IFERROR(SUMIF($AB$4:$AM$4, "SME", AB66:AM66), "") -> 4316.715 | AP66: =IFERROR(SUMIF($AB$4:$AM$4, "De Minimis", AB66:AM66), "") -> 0 | AR66: =IFERROR(($J66*O66)*$M66, "") -> 0 | AS66: =IFERROR(($J66*P66)*$M66, "") -> 0 | AT66: =IFERROR(($J66*Q66)*$M66, "") -> 0 | AU66: =IFERROR(($J66*R66)*$M66, "") -> 0 | AV66: =IFERROR(($J66*S66)*$M66, "") -> 0 | AW66: =IFERROR(($J66*T66)*$M66, "") -> 0 | AX66: =IFERROR(($J66*U66)*$M66, "") -> 0 | AY66: =IFERROR(($J66*V66)*$M66, "") -> 0 | ... BC66: =IFERROR(($J66*Z66)*$M66, "") -> 0 | BD66: =IFERROR(SUMIF($AB$4:$AM$4, "RDEC", AR66:BC66), "") -> 0 | BE66: =IFERROR(SUMIF($AB$4:$AM$4, "SME", AR66:BC66), "") -> 0 | BF66: =IFERROR(SUMIF($AB$4:$AM$4, "De Minimis", AR66:BC66), "") -> 0 | BH66: =IF((SUM(O66:Z66)>1),"ERROR","") | BJ66: =IF(C52>0, C52, "")
D67: =D51 -> 45627 | E67: 5739.3 | F67: 1549.61 | G67: 398.48 | H67: 687.37 | I67: 286.97 | J67: =E67+H67+I67 -> 6713.64 | L67: 1 | M67: =1-L67 -> 0 | P67: 0.4 | R67: 0.35 | S67: 0.25 | AB67: =IFERROR(($J67*O67)*$L67, "") -> 0 | AC67: =IFERROR(($J67*P67)*$L67, "") -> 2685.456 | AD67: =IFERROR(($J67*Q67)*$L67, "") -> 0 | AE67: =IFERROR(($J67*R67)*$L67, "") -> 2349.774 | AF67: =IFERROR(($J67*S67)*$L67, "") -> 1678.41 | AG67: =IFERROR(($J67*T67)*$L67, "") -> 0 | AH67: =IFERROR(($J67*U67)*$L67, "") -> 0 | AI67: =IFERROR(($J67*V67)*$L67, "") -> 0 | ... AM67: =IFERROR(($J67*Z67)*$L67, "") -> 0 | AN67: =IFERROR(SUMIF($AB$4:$AM$4, "RDEC", AB67:AM67), "") -> 2349.774 | AO67: =IFERROR(SUMIF($AB$4:$AM$4, "SME", AB67:AM67), "") -> 4363.866 | AP67: =IFERROR(SUMIF($AB$4:$AM$4, "De Minimis", AB67:AM67), "") -> 0 | AR67: =IFERROR(($J67*O67)*$M67, "") -> 0 | AS67: =IFERROR(($J67*P67)*$M67, "") -> 0 | AT67: =IFERROR(($J67*Q67)*$M67, "") -> 0 | AU67: =IFERROR(($J67*R67)*$M67, "") -> 0 | AV67: =IFERROR(($J67*S67)*$M67, "") -> 0 | AW67: =IFERROR(($J67*T67)*$M67, "") -> 0 | AX67: =IFERROR(($J67*U67)*$M67, "") -> 0 | AY67: =IFERROR(($J67*V67)*$M67, "") -> 0 | ... BC67: =IFERROR(($J67*Z67)*$M67, "") -> 0 | BD67: =IFERROR(SUMIF($AB$4:$AM$4, "RDEC", AR67:BC67), "") -> 0 | BE67: =IFERROR(SUMIF($AB$4:$AM$4, "SME", AR67:BC67), "") -> 0 | BF67: =IFERROR(SUMIF($AB$4:$AM$4, "De Minimis", AR67:BC67), "") -> 0 | BH67: =IF((SUM(O67:Z67)>1),"ERROR","") | BJ67: =IF(C53>0, C53, "")
D68: Total | E68: =SUM(E55:E67) -> 67773.29 | F68: =SUM(F55:F67) -> 18298.77 | G68: =SUM(G55:G67) -> 4693.86 | H68: =SUM(H55:H67) -> 8096.92 | I68: =SUM(I55:I67) -> 3388.68 | J68: =SUM(J55:J67) -> 79258.89 | L68: =AVERAGE(L55:L67) -> 1 | M68: =AVERAGE(M55:M67) -> 0 | O68: =IF(SUM(O56:O67)>0,((AB68+AR68)/J68),0) -> 0 | P68: =IF(SUM(P56:P67)>0,((AC68+AS68)/J68),0) -> 0.4 | Q68: =IF(SUM(Q56:Q67)>0,((AD68+AT68)/J68),0) -> 0 | R68: =IF(SUM(R56:R67)>0,((AE68+AU68)/J68),0) -> 0.35 | S68: =IF(SUM(S56:S67)>0,((AF68+AV68)/J68),0) -> 0.25 | T68: =IF(SUM(T56:T67)>0,((AG68+AW68)/J68),0) -> 0 | U68: =IF(SUM(U56:U67)>0,((AH68+AX68)/J68),0) -> 0 | V68: =IF(SUM(V56:V67)>0,((AI68+AY68)/J68),0) -> 0 | W68: =IF(SUM(W56:W67)>0,((AJ68+AZ68)/J68),0) -> 0 | X68: =IF(SUM(X56:X67)>0,((AK68+BA68)/J68),0) -> 0 | Y68: =IF(SUM(Y56:Y67)>0,((AL68+BB68)/J68),0) -> 0 | Z68: =IF(SUM(Z56:Z67)>0,((AM68+BC68)/J68),0) -> 0 | AB68: =SUM(AB55:AB67) -> 0 | AC68: =SUM(AC55:AC67) -> 31703.556 | AD68: =SUM(AD55:AD67) -> 0 | AE68: =SUM(AE55:AE67) -> 27740.611 | AF68: =SUM(AF55:AF67) -> 19814.722 | AG68: =SUM(AG55:AG67) -> 0 | AH68: =SUM(AH55:AH67) -> 0 | AI68: =SUM(AI55:AI67) -> 0 | ... AP68: =SUM(AP55:AP67) -> 0 | AR68: =SUM(AR55:AR67) -> 0 | AS68: =SUM(AS55:AS67) -> 0 | AT68: =SUM(AT55:AT67) -> 0 | AU68: =SUM(AU55:AU67) -> 0 | AV68: =SUM(AV55:AV67) -> 0 | AW68: =SUM(AW55:AW67) -> 0 | AX68: =SUM(AX55:AX67) -> 0 | AY68: =SUM(AY55:AY67) -> 0 | ... BF68: =SUM(BF55:BF67) -> 0 | BJ68: =IF(C54>0, C54, "") -> Data Scientist | BK68: N | BL68: =IF($BK68="Y",J68,0) -> 0 | BM68: =IF(BK68="Y", AN68,0) -> 0 | BN68: =IF((BK68="Y"),AO68,0) -> 0
BJ69: =IF(C55>0, C55, "")
A70: 5 | B70: Raj Patel | C70: DevOps Engineer | BJ70: =IF(C57>0, C57, "")
D72: =D56 -> 45292 | E72: 4796.15 | F72: 1294.96 | G72: 323.03 | H72: 557.22 | I72: 191.85 | J72: =E72+H72+I72 -> 5545.22 | L72: 0.8 | M72: =1-L72 -> 0.2 | O72: 0.2 | P72: 0.3 | Q72: 0.15 | R72: 0.2 | S72: 0.15 | AB72: =IFERROR(($J72*O72)*$L72, "") -> 887.2352 | AC72: =IFERROR(($J72*P72)*$L72, "") -> 1330.8528 | AD72: =IFERROR(($J72*Q72)*$L72, "") -> 665.4264 | AE72: =IFERROR(($J72*R72)*$L72, "") -> 887.2352 | AF72: =IFERROR(($J72*S72)*$L72, "") -> 665.4264 | AG72: =IFERROR(($J72*T72)*$L72, "") -> 0 | AH72: =IFERROR(($J72*U72)*$L72, "") -> 0 | AI72: =IFERROR(($J72*V72)*$L72, "") -> 0 | ... AM72: =IFERROR(($J72*Z72)*$L72, "") -> 0 | AN72: =IFERROR(SUMIF($AB$4:$AM$4, "RDEC", AB72:AM72), "") -> 887.2352 | AO72: =IFERROR(SUMIF($AB$4:$AM$4, "SME", AB72:AM72), "") -> 3548.9408 | AP72: =IFERROR(SUMIF($AB$4:$AM$4, "De Minimis", AB72:AM72), "") -> 0 | AR72: =IFERROR(($J72*O72)*$M72, "") -> 221.8088 | AS72: =IFERROR(($J72*P72)*$M72, "") -> 332.7132 | AT72: =IFERROR(($J72*Q72)*$M72, "") -> 166.3566 | AU72: =IFERROR(($J72*R72)*$M72, "") -> 221.8088 | AV72: =IFERROR(($J72*S72)*$M72, "") -> 166.3566 | AW72: =IFERROR(($J72*T72)*$M72, "") -> 0 | AX72: =IFERROR(($J72*U72)*$M72, "") -> 0 | AY72: =IFERROR(($J72*V72)*$M72, "") -> 0 | ... BC72: =IFERROR(($J72*Z72)*$M72, "") -> 0 | BD72: =IFERROR(SUMIF($AB$4:$AM$4, "RDEC", AR72:BC72), "") -> 221.8088 | BE72: =IFERROR(SUMIF($AB$4:$AM$4, "SME", AR72:BC72), "") -> 887.2352 | BF72: =IFERROR(SUMIF($AB$4:$AM$4, "De Minimis", AR72:BC72), "") -> 0 | BH72: =IF((SUM(O72:Z72)>1),"ERROR","") | BJ72: =IF(C58>0, C58, "")
D73: =D57 -> 45323 | E73: 4832.88 | F73: 1304.88 | G73: 325.96 | H73: 562.29 | I73: 193.32 | J73: =E73+H73+I73 -> 5588.49 | L73: 0.8 | M73: =1-L73 -> 0.2 | O73: 0.2 | P73: 0.3 | Q73: 0.15 | R73: 0.2 | S73: 0.15 | AB73: =IFERROR(($J73*O73)*$L73, "") -> 894.1584 | AC73: =IFERROR(($J73*P73)*$L73, "") -> 1341.2376 | AD73: =IFERROR(($J73*Q73)*$L73, "") -> 670.6188 | AE73: =IFERROR(($J73*R73)*$L73, "") -> 894.1584 | AF73: =IFERROR(($J73*S73)*$L73, "") -> 670.6188 | AG73: =IFERROR(($J73*T73)*$L73, "") -> 0 | AH73: =IFERROR(($J73*U73)*$L73, "") -> 0 | AI73: =IFERROR(($J73*V73)*$L73, "") -> 0 | ... AM73: =IFERROR(($J73*Z73)*$L73, "") -> 0 | AN73: =IFERROR(SUMIF($AB$4:$AM$4, "RDEC", AB73:AM73), "") -> 894.1584 | AO73: =IFERROR(SUMIF($AB$4:$AM$4, "SME", AB73:AM73), "") -> 3576.6336 | AP73: =IFERROR(SUMIF($AB$4:$AM$4, "De Minimis", AB73:AM73), "") -> 0 | AR73: =IFERROR(($J73*O73)*$M73, "") -> 223.5396 | AS73: =IFERROR(($J73*P73)*$M73, "") -> 335.3094 | AT73: =IFERROR(($J73*Q73)*$M73, "") -> 167.6547 | AU73: =IFERROR(($J73*R73)*$M73, "") -> 223.5396 | AV73: =IFERROR(($J73*S73)*$M73, "") -> 167.6547 | AW73: =IFERROR(($J73*T73)*$M73, "") -> 0 | AX73: =IFERROR(($J73*U73)*$M73, "") -> 0 | AY73: =IFERROR(($J73*V73)*$M73, "") -> 0 | ... BC73: =IFERROR(($J73*Z73)*$M73, "") -> 0 | BD73: =IFERROR(SUMIF($AB$4:$AM$4, "RDEC", AR73:BC73), "") -> 223.5396 | BE73: =IFERROR(SUMIF($AB$4:$AM$4, "SME", AR73:BC73), "") -> 894.1584 | BF73: =IFERROR(SUMIF($AB$4:$AM$4, "De Minimis", AR73:BC73), "") -> 0 | BH73: =IF((SUM(O73:Z73)>1),"ERROR","") | BJ73: =IF(C59>0, C59, "")
D74: =D58 -> 45352 | E74: 4895.57 | F74: 1321.8 | G74: 330.98 | H74: 570.94 | I74: 195.82 | J74: =E74+H74+I74 -> 5662.33 | L74: 0.8 | M74: =1-L74 -> 0.2 | O74: 0.2 | P74: 0.3 | Q74: 0.15 | R74: 0.2 | S74: 0.15 | AB74: =IFERROR(($J74*O74)*$L74, "") -> 905.9728 | AC74: =IFERROR(($J74*P74)*$L74, "") -> 1358.9592 | AD74: =IFERROR(($J74*Q74)*$L74, "") -> 679.4796 | AE74: =IFERROR(($J74*R74)*$L74, "") -> 905.9728 | AF74: =IFERROR(($J74*S74)*$L74, "") -> 679.4796 | AG74: =IFERROR(($J74*T74)*$L74, "") -> 0 | AH74: =IFERROR(($J74*U74)*$L74, "") -> 0 | AI74: =IFERROR(($J74*V74)*$L74, "") -> 0 | ... AM74: =IFERROR(($J74*Z74)*$L74, "") -> 0 | AN74: =IFERROR(SUMIF($AB$4:$AM$4, "RDEC", AB74:AM74), "") -> 905.9728 | AO74: =IFERROR(SUMIF($AB$4:$AM$4, "SME", AB74:AM74), "") -> 3623.8912 | AP74: =IFERROR(SUMIF($AB$4:$AM$4, "De Minimis", AB74:AM74), "") -> 0 | AR74: =IFERROR(($J74*O74)*$M74, "") -> 226.4932 | AS74: =IFERROR(($J74*P74)*$M74, "") -> 339.7398 | AT74: =IFERROR(($J74*Q74)*$M74, "") -> 169.8699 | AU74: =IFERROR(($J74*R74)*$M74, "") -> 226.4932 | AV74: =IFERROR(($J74*S74)*$M74, "") -> 169.8699 | AW74: =IFERROR(($J74*T74)*$M74, "") -> 0 | AX74: =IFERROR(($J74*U74)*$M74, "") -> 0 | AY74: =IFERROR(($J74*V74)*$M74, "") -> 0 | ... BC74: =IFERROR(($J74*Z74)*$M74, "") -> 0 | BD74: =IFERROR(SUMIF($AB$4:$AM$4, "RDEC", AR74:BC74), "") -> 226.4932 | BE74: =IFERROR(SUMIF($AB$4:$AM$4, "SME", AR74:BC74), "") -> 905.9728 | BF74: =IFERROR(SUMIF($AB$4:$AM$4, "De Minimis", AR74:BC74), "") -> 0 | BH74: =IF((SUM(O74:Z74)>1),"ERROR","") | BJ74: =IF(C60>0, C60, "")
D75: =D59 -> 45383 | E75: 4784.93 | F75: 1291.93 | G75: 322.13 | H75: 555.67 | I75: 191.4 | J75: =E75+H75+I75 -> 5532 | L75: 0.8 | M75: =1-L75 -> 0.2 | O75: 0.2 | P75: 0.3 | Q75: 0.15 | R75: 0.2 | S75: 0.15 | AB75: =IFERROR(($J75*O75)*$L75, "") -> 885.12 | AC75: =IFERROR(($J75*P75)*$L75, "") -> 1327.68 | AD75: =IFERROR(($J75*Q75)*$L75, "") -> 663.84 | AE75: =IFERROR(($J75*R75)*$L75, "") -> 885.12 | AF75: =IFERROR(($J75*S75)*$L75, "") -> 663.84 | AG75: =IFERROR(($J75*T75)*$L75, "") -> 0 | AH75: =IFERROR(($J75*U75)*$L75, "") -> 0 | AI75: =IFERROR(($J75*V75)*$L75, "") -> 0 | ... AM75: =IFERROR(($J75*Z75)*$L75, "") -> 0 | AN75: =IFERROR(SUMIF($AB$4:$AM$4, "RDEC", AB75:AM75), "") -> 885.12 | AO75: =IFERROR(SUMIF($AB$4:$AM$4, "SME", AB75:AM75), "") -> 3540.48 | AP75: =IFERROR(SUMIF($AB$4:$AM$4, "De Minimis", AB75:AM75), "") -> 0 | AR75: =IFERROR(($J75*O75)*$M75, "") -> 221.28 | AS75: =IFERROR(($J75*P75)*$M75, "") -> 331.92 | AT75: =IFERROR(($J75*Q75)*$M75, "") -> 165.96 | AU75: =IFERROR(($J75*R75)*$M75, "") -> 221.28 | AV75: =IFERROR(($J75*S75)*$M75, "") -> 165.96 | AW75: =IFERROR(($J75*T75)*$M75, "") -> 0 | AX75: =IFERROR(($J75*U75)*$M75, "") -> 0 | AY75: =IFERROR(($J75*V75)*$M75, "") -> 0 | ... BC75: =IFERROR(($J75*Z75)*$M75, "") -> 0 | BD75: =IFERROR(SUMIF($AB$4:$AM$4, "RDEC", AR75:BC75), "") -> 221.28 | BE75: =IFERROR(SUMIF($AB$4:$AM$4, "SME", AR75:BC75), "") -> 885.12 | BF75: =IFERROR(SUMIF($AB$4:$AM$4, "De Minimis", AR75:BC75), "") -> 0 | BH75: =IF((SUM(O75:Z75)>1),"ERROR","") | BJ75: =IF(C61>0, C61, "")
D76: =D60 -> 45413 | E76: 4753.57 | F76: 1283.46 | G76: 319.62 | H76: 551.34 | I76: 190.14 | J76: =E76+H76+I76 -> 5495.05 | L76: 0.8 | M76: =1-L76 -> 0.2 | O76: 0.2 | P76: 0.3 | Q76: 0.15 | R76: 0.2 | S76: 0.15 | AB76: =IFERROR(($J76*O76)*$L76, "") -> 879.208 | AC76: =IFERROR(($J76*P76)*$L76, "") -> 1318.812 | AD76: =IFERROR(($J76*Q76)*$L76, "") -> 659.406 | AE76: =IFERROR(($J76*R76)*$L76, "") -> 879.208 | AF76: =IFERROR(($J76*S76)*$L76, "") -> 659.406 | AG76: =IFERROR(($J76*T76)*$L76, "") -> 0 | AH76: =IFERROR(($J76*U76)*$L76, "") -> 0 | AI76: =IFERROR(($J76*V76)*$L76, "") -> 0 | ... AM76: =IFERROR(($J76*Z76)*$L76, "") -> 0 | AN76: =IFERROR(SUMIF($AB$4:$AM$4, "RDEC", AB76:AM76), "") -> 879.208 | AO76: =IFERROR(SUMIF($AB$4:$AM$4, "SME", AB76:AM76), "") -> 3516.832 | AP76: =IFERROR(SUMIF($AB$4:$AM$4, "De Minimis", AB76:AM76), "") -> 0 | AR76: =IFERROR(($J76*O76)*$M76, "") -> 219.802 | AS76: =IFERROR(($J76*P76)*$M76, "") -> 329.703 | AT76: =IFERROR(($J76*Q76)*$M76, "") -> 164.8515 | AU76: =IFERROR(($J76*R76)*$M76, "") -> 219.802 | AV76: =IFERROR(($J76*S76)*$M76, "") -> 164.8515 | AW76: =IFERROR(($J76*T76)*$M76, "") -> 0 | AX76: =IFERROR(($J76*U76)*$M76, "") -> 0 | AY76: =IFERROR(($J76*V76)*$M76, "") -> 0 | ... BC76: =IFERROR(($J76*Z76)*$M76, "") -> 0 | BD76: =IFERROR(SUMIF($AB$4:$AM$4, "RDEC", AR76:BC76), "") -> 219.802 | BE76: =IFERROR(SUMIF($AB$4:$AM$4, "SME", AR76:BC76), "") -> 879.208 | BF76: =IFERROR(SUMIF($AB$4:$AM$4, "De Minimis", AR76:BC76), "") -> 0 | BH76: =IF((SUM(O76:Z76)>1),"ERROR","") | BJ76: =IF(C62>0, C62, "")
D77: =D61 -> 45444 | E77: 4745.08 | F77: 1281.17 | G77: 318.94 | H77: 550.17 | I77: 189.8 | J77: =E77+H77+I77 -> 5485.05 | L77: 0.8 | M77: =1-L77 -> 0.2 | O77: 0.2 | P77: 0.3 | Q77: 0.15 | R77: 0.2 | S77: 0.15 | AB77: =IFERROR(($J77*O77)*$L77, "") -> 877.608 | AC77: =IFERROR(($J77*P77)*$L77, "") -> 1316.412 | AD77: =IFERROR(($J77*Q77)*$L77, "") -> 658.206 | AE77: =IFERROR(($J77*R77)*$L77, "") -> 877.608 | AF77: =IFERROR(($J77*S77)*$L77, "") -> 658.206 | AG77: =IFERROR(($J77*T77)*$L77, "") -> 0 | AH77: =IFERROR(($J77*U77)*$L77, "") -> 0 | AI77: =IFERROR(($J77*V77)*$L77, "") -> 0 | ... AM77: =IFERROR(($J77*Z77)*$L77, "") -> 0 | AN77: =IFERROR(SUMIF($AB$4:$AM$4, "RDEC", AB77:AM77), "") -> 877.608 | AO77: =IFERROR(SUMIF($AB$4:$AM$4, "SME", AB77:AM77), "") -> 3510.432 | AP77: =IFERROR(SUMIF($AB$4:$AM$4, "De Minimis", AB77:AM77), "") -> 0 | AR77: =IFERROR(($J77*O77)*$M77, "") -> 219.402 | AS77: =IFERROR(($J77*P77)*$M77, "") -> 329.103 | AT77: =IFERROR(($J77*Q77)*$M77, "") -> 164.5515 | AU77: =IFERROR(($J77*R77)*$M77, "") -> 219.402 | AV77: =IFERROR(($J77*S77)*$M77, "") -> 164.5515 | AW77: =IFERROR(($J77*T77)*$M77, "") -> 0 | AX77: =IFERROR(($J77*U77)*$M77, "") -> 0 | AY77: =IFERROR(($J77*V77)*$M77, "") -> 0 | ... BC77: =IFERROR(($J77*Z77)*$M77, "") -> 0 | BD77: =IFERROR(SUMIF($AB$4:$AM$4, "RDEC", AR77:BC77), "") -> 219.402 | BE77: =IFERROR(SUMIF($AB$4:$AM$4, "SME", AR77:BC77), "") -> 877.608 | BF77: =IFERROR(SUMIF($AB$4:$AM$4, "De Minimis", AR77:BC77), "") -> 0 | BH77: =IF((SUM(O77:Z77)>1),"ERROR","") | BJ77: =IF(C63>0, C63, "")
D78: =D62 -> 45474 | E78: 4818.06 | F78: 1300.88 | G78: 324.78 | H78: 560.24 | I78: 192.72 | J78: =E78+H78+I78 -> 5571.02 | L78: 0.8 | M78: =1-L78 -> 0.2 | O78: 0.2 | P78: 0.3 | Q78: 0.15 | R78: 0.2 | S78: 0.15 | AB78: =IFERROR(($J78*O78)*$L78, "") -> 891.3632 | AC78: =IFERROR(($J78*P78)*$L78, "") -> 1337.0448 | AD78: =IFERROR(($J78*Q78)*$L78, "") -> 668.5224 | AE78: =IFERROR(($J78*R78)*$L78, "") -> 891.3632 | AF78: =IFERROR(($J78*S78)*$L78, "") -> 668.5224 | AG78: =IFERROR(($J78*T78)*$L78, "") -> 0 | AH78: =IFERROR(($J78*U78)*$L78, "") -> 0 | AI78: =IFERROR(($J78*V78)*$L78, "") -> 0 | ... AM78: =IFERROR(($J78*Z78)*$L78, "") -> 0 | AN78: =IFERROR(SUMIF($AB$4:$AM$4, "RDEC", AB78:AM78), "") -> 891.3632 | AO78: =IFERROR(SUMIF($AB$4:$AM$4, "SME", AB78:AM78), "") -> 3565.4528 | AP78: =IFERROR(SUMIF($AB$4:$AM$4, "De Minimis", AB78:AM78), "") -> 0 | AR78: =IFERROR(($J78*O78)*$M78, "") -> 222.8408 | AS78: =IFERROR(($J78*P78)*$M78, "") -> 334.2612 | AT78: =IFERROR(($J78*Q78)*$M78, "") -> 167.1306 | AU78: =IFERROR(($J78*R78)*$M78, "") -> 222.8408 | AV78: =IFERROR(($J78*S78)*$M78, "") -> 167.1306 | AW78: =IFERROR(($J78*T78)*$M78, "") -> 0 | AX78: =IFERROR(($J78*U78)*$M78, "") -> 0 | AY78: =IFERROR(($J78*V78)*$M78, "") -> 0 | ... BC78: =IFERROR(($J78*Z78)*$M78, "") -> 0 | BD78: =IFERROR(SUMIF($AB$4:$AM$4, "RDEC", AR78:BC78), "") -> 222.8408 | BE78: =IFERROR(SUMIF($AB$4:$AM$4, "SME", AR78:BC78), "") -> 891.3632 | BF78: =IFERROR(SUMIF($AB$4:$AM$4, "De Minimis", AR78:BC78), "") -> 0 | BH78: =IF((SUM(O78:Z78)>1),"ERROR","") | BJ78: =IF(C64>0, C64, "")
D79: =D63 -> 45505 | E79: 4863.93 | F79: 1313.26 | G79: 328.45 | H79: 566.57 | I79: 194.56 | J79: =E79+H79+I79 -> 5625.06 | L79: 0.8 | M79: =1-L79 -> 0.2 | O79: 0.2 | P79: 0.3 | Q79: 0.15 | R79: 0.2 | S79: 0.15 | AB79: =IFERROR(($J79*O79)*$L79, "") -> 900.0096 | AC79: =IFERROR(($J79*P79)*$L79, "") -> 1350.0144 | AD79: =IFERROR(($J79*Q79)*$L79, "") -> 675.0072 | AE79: =IFERROR(($J79*R79)*$L79, "") -> 900.0096 | AF79: =IFERROR(($J79*S79)*$L79, "") -> 675.0072 | AG79: =IFERROR(($J79*T79)*$L79, "") -> 0 | AH79: =IFERROR(($J79*U79)*$L79, "") -> 0 | AI79: =IFERROR(($J79*V79)*$L79, "") -> 0 | ... AM79: =IFERROR(($J79*Z79)*$L79, "") -> 0 | AN79: =IFERROR(SUMIF($AB$4:$AM$4, "RDEC", AB79:AM79), "") -> 900.0096 | AO79: =IFERROR(SUMIF($AB$4:$AM$4, "SME", AB79:AM79), "") -> 3600.0384 | AP79: =IFERROR(SUMIF($AB$4:$AM$4, "De Minimis", AB79:AM79), "") -> 0 | AR79: =IFERROR(($J79*O79)*$M79, "") -> 225.0024 | AS79: =IFERROR(($J79*P79)*$M79, "") -> 337.5036 | AT79: =IFERROR(($J79*Q79)*$M79, "") -> 168.7518 | AU79: =IFERROR(($J79*R79)*$M79, "") -> 225.0024 | AV79: =IFERROR(($J79*S79)*$M79, "") -> 168.7518 | AW79: =IFERROR(($J79*T79)*$M79, "") -> 0 | AX79: =IFERROR(($J79*U79)*$M79, "") -> 0 | AY79: =IFERROR(($J79*V79)*$M79, "") -> 0 | ... BC79: =IFERROR(($J79*Z79)*$M79, "") -> 0 | BD79: =IFERROR(SUMIF($AB$4:$AM$4, "RDEC", AR79:BC79), "") -> 225.0024 | BE79: =IFERROR(SUMIF($AB$4:$AM$4, "SME", AR79:BC79), "") -> 900.0096 | BF79: =IFERROR(SUMIF($AB$4:$AM$4, "De Minimis", AR79:BC79), "") -> 0 | BH79: =IF((SUM(O79:Z79)>1),"ERROR","") | BJ79: =IF(C65>0, C65, "")
D80: =D64 -> 45536 | E80: 4891.01 | F80: 1320.57 | G80: 330.61 | H80: 570.31 | I80: 195.64 | J80: =E80+H80+I80 -> 5656.96 | L80: 0.8 | M80: =1-L80 -> 0.2 | O80: 0.2 | P80: 0.3 | Q80: 0.15 | R80: 0.2 | S80: 0.15 | AB80: =IFERROR(($J80*O80)*$L80, "") -> 905.1136 | AC80: =IFERROR(($J80*P80)*$L80, "") -> 1357.6704 | AD80: =IFERROR(($J80*Q80)*$L80, "") -> 678.8352 | AE80: =IFERROR(($J80*R80)*$L80, "") -> 905.1136 | AF80: =IFERROR(($J80*S80)*$L80, "") -> 678.8352 | AG80: =IFERROR(($J80*T80)*$L80, "") -> 0 | AH80: =IFERROR(($J80*U80)*$L80, "") -> 0 | AI80: =IFERROR(($J80*V80)*$L80, "") -> 0 | ... AM80: =IFERROR(($J80*Z80)*$L80, "") -> 0 | AN80: =IFERROR(SUMIF($AB$4:$AM$4, "RDEC", AB80:AM80), "") -> 905.1136 | AO80: =IFERROR(SUMIF($AB$4:$AM$4, "SME", AB80:AM80), "") -> 3620.4544 | AP80: =IFERROR(SUMIF($AB$4:$AM$4, "De Minimis", AB80:AM80), "") -> 0 | AR80: =IFERROR(($J80*O80)*$M80, "") -> 226.2784 | AS80: =IFERROR(($J80*P80)*$M80, "") -> 339.4176 | AT80: =IFERROR(($J80*Q80)*$M80, "") -> 169.7088 | AU80: =IFERROR(($J80*R80)*$M80, "") -> 226.2784 | AV80: =IFERROR(($J80*S80)*$M80, "") -> 169.7088 | AW80: =IFERROR(($J80*T80)*$M80, "") -> 0 | AX80: =IFERROR(($J80*U80)*$M80, "") -> 0 | AY80: =IFERROR(($J80*V80)*$M80, "") -> 0 | ... BC80: =IFERROR(($J80*Z80)*$M80, "") -> 0 | BD80: =IFERROR(SUMIF($AB$4:$AM$4, "RDEC", AR80:BC80), "") -> 226.2784 | BE80: =IFERROR(SUMIF($AB$4:$AM$4, "SME", AR80:BC80), "") -> 905.1136 | BF80: =IFERROR(SUMIF($AB$4:$AM$4, "De Minimis", AR80:BC80), "") -> 0 | BH80: =IF((SUM(O80:Z80)>1),"ERROR","") | BJ80: =IF(C66>0, C66, "")
D81: =D65 -> 45566 | E81: 4896.34 | F81: 1322.01 | G81: 331.04 | H81: 571.05 | I81: 195.85 | J81: =E81+H81+I81 -> 5663.24 | L81: 0.8 | M81: =1-L81 -> 0.2 | O81: 0.2 | P81: 0.3 | Q81: 0.15 | R81: 0.2 | S81: 0.15 | AB81: =IFERROR(($J81*O81)*$L81, "") -> 906.1184 | AC81: =IFERROR(($J81*P81)*$L81, "") -> 1359.1776 | AD81: =IFERROR(($J81*Q81)*$L81, "") -> 679.5888 | AE81: =IFERROR(($J81*R81)*$L81, "") -> 906.1184 | AF81: =IFERROR(($J81*S81)*$L81, "") -> 679.5888 | AG81: =IFERROR(($J81*T81)*$L81, "") -> 0 | AH81: =IFERROR(($J81*U81)*$L81, "") -> 0 | AI81: =IFERROR(($J81*V81)*$L81, "") -> 0 | ... AM81: =IFERROR(($J81*Z81)*$L81, "") -> 0 | AN81: =IFERROR(SUMIF($AB$4:$AM$4, "RDEC", AB81:AM81), "") -> 906.1184 | AO81: =IFERROR(SUMIF($AB$4:$AM$4, "SME", AB81:AM81), "") -> 3624.4736 | AP81: =IFERROR(SUMIF($AB$4:$AM$4, "De Minimis", AB81:AM81), "") -> 0 | AR81: =IFERROR(($J81*O81)*$M81, "") -> 226.5296 | AS81: =IFERROR(($J81*P81)*$M81, "") -> 339.7944 | AT81: =IFERROR(($J81*Q81)*$M81, "") -> 169.8972 | AU81: =IFERROR(($J81*R81)*$M81, "") -> 226.5296 | AV81: =IFERROR(($J81*S81)*$M81, "") -> 169.8972 | AW81: =IFERROR(($J81*T81)*$M81, "") -> 0 | AX81: =IFERROR(($J81*U81)*$M81, "") -> 0 | AY81: =IFERROR(($J81*V81)*$M81, "") -> 0 | ... BC81: =IFERROR(($J81*Z81)*$M81, "") -> 0 | BD81: =IFERROR(SUMIF($AB$4:$AM$4, "RDEC", AR81:BC81), "") -> 226.5296 | BE81: =IFERROR(SUMIF($AB$4:$AM$4, "SME", AR81:BC81), "") -> 906.1184 | BF81: =IFERROR(SUMIF($AB$4:$AM$4, "De Minimis", AR81:BC81), "") -> 0 | BH81: =IF((SUM(O81:Z81)>1),"ERROR","") | BJ81: =IF(C67>0, C67, "")
D82: =D66 -> 45597 | E82: 4765.1 | F82: 1286.58 | G82: 320.54 | H82: 552.93 | I82: 190.6 | J82: =E82+H82+I82 -> 5508.63 | L82: 0.8 | M82: =1-L82 -> 0.2 | O82: 0.2 | P82: 0.3 | Q82: 0.15 | R82: 0.2 | S82: 0.15 | AB82: =IFERROR(($J82*O82)*$L82, "") -> 881.3808 | AC82: =IFERROR(($J82*P82)*$L82, "") -> 1322.0712 | AD82: =IFERROR(($J82*Q82)*$L82, "") -> 661.0356 | AE82: =IFERROR(($J82*R82)*$L82, "") -> 881.3808 | AF82: =IFERROR(($J82*S82)*$L82, "") -> 661.0356 | AG82: =IFERROR(($J82*T82)*$L82, "") -> 0 | AH82: =IFERROR(($J82*U82)*$L82, "") -> 0 | AI82: =IFERROR(($J82*V82)*$L82, "") -> 0 | ... AM82: =IFERROR(($J82*Z82)*$L82, "") -> 0 | AN82: =IFERROR(SUMIF($AB$4:$AM$4, "RDEC", AB82:AM82), "") -> 881.3808 | AO82: =IFERROR(SUMIF($AB$4:$AM$4, "SME", AB82:AM82), "") -> 3525.5232 | AP82: =IFERROR(SUMIF($AB$4:$AM$4, "De Minimis", AB82:AM82), "") -> 0 | AR82: =IFERROR(($J82*O82)*$M82, "") -> 220.3452 | AS82: =IFERROR(($J82*P82)*$M82, "") -> 330.5178 | AT82: =IFERROR(($J82*Q82)*$M82, "") -> 165.2589 | AU82: =IFERROR(($J82*R82)*$M82, "") -> 220.3452 | AV82: =IFERROR(($J82*S82)*$M82, "") -> 165.2589 | AW82: =IFERROR(($J82*T82)*$M82, "") -> 0 | AX82: =IFERROR(($J82*U82)*$M82, "") -> 0 | AY82: =IFERROR(($J82*V82)*$M82, "") -> 0 | ... BC82: =IFERROR(($J82*Z82)*$M82, "") -> 0 | BD82: =IFERROR(SUMIF($AB$4:$AM$4, "RDEC", AR82:BC82), "") -> 220.3452 | BE82: =IFERROR(SUMIF($AB$4:$AM$4, "SME", AR82:BC82), "") -> 881.3808 | BF82: =IFERROR(SUMIF($AB$4:$AM$4, "De Minimis", AR82:BC82), "") -> 0 | BH82: =IF((SUM(O82:Z82)>1),"ERROR","") | BJ82: =IF(C68>0, C68, "")
D83: =D67 -> 45627 | E83: 4778.52 | F83: 1290.2 | G83: 321.62 | H83: 554.79 | I83: 191.14 | J83: =E83+H83+I83 -> 5524.45 | L83: 0.8 | M83: =1-L83 -> 0.2 | O83: 0.2 | P83: 0.3 | Q83: 0.15 | R83: 0.2 | S83: 0.15 | AB83: =IFERROR(($J83*O83)*$L83, "") -> 883.912 | AC83: =IFERROR(($J83*P83)*$L83, "") -> 1325.868 | AD83: =IFERROR(($J83*Q83)*$L83, "") -> 662.934 | AE83: =IFERROR(($J83*R83)*$L83, "") -> 883.912 | AF83: =IFERROR(($J83*S83)*$L83, "") -> 662.934 | AG83: =IFERROR(($J83*T83)*$L83, "") -> 0 | AH83: =IFERROR(($J83*U83)*$L83, "") -> 0 | AI83: =IFERROR(($J83*V83)*$L83, "") -> 0 | ... AM83: =IFERROR(($J83*Z83)*$L83, "") -> 0 | AN83: =IFERROR(SUMIF($AB$4:$AM$4, "RDEC", AB83:AM83), "") -> 883.912 | AO83: =IFERROR(SUMIF($AB$4:$AM$4, "SME", AB83:AM83), "") -> 3535.648 | AP83: =IFERROR(SUMIF($AB$4:$AM$4, "De Minimis", AB83:AM83), "") -> 0 | AR83: =IFERROR(($J83*O83)*$M83, "") -> 220.978 | AS83: =IFERROR(($J83*P83)*$M83, "") -> 331.467 | AT83: =IFERROR(($J83*Q83)*$M83, "") -> 165.7335 | AU83: =IFERROR(($J83*R83)*$M83, "") -> 220.978 | AV83: =IFERROR(($J83*S83)*$M83, "") -> 165.7335 | AW83: =IFERROR(($J83*T83)*$M83, "") -> 0 | AX83: =IFERROR(($J83*U83)*$M83, "") -> 0 | AY83: =IFERROR(($J83*V83)*$M83, "") -> 0 | ... BC83: =IFERROR(($J83*Z83)*$M83, "") -> 0 | BD83: =IFERROR(SUMIF($AB$4:$AM$4, "RDEC", AR83:BC83), "") -> 220.978 | BE83: =IFERROR(SUMIF($AB$4:$AM$4, "SME", AR83:BC83), "") -> 883.912 | BF83: =IFERROR(SUMIF($AB$4:$AM$4, "De Minimis", AR83:BC83), "") -> 0 | BH83: =IF((SUM(O83:Z83)>1),"ERROR","") | BJ83: =IF(C69>0, C69, "")
D84: Total | E84: =SUM(E71:E83) -> 57821.14 | F84: =SUM(F71:F83) -> 15611.7 | G84: =SUM(G71:G83) -> 3897.7 | H84: =SUM(H71:H83) -> 6723.52 | I84: =SUM(I71:I83) -> 2312.84 | J84: =SUM(J71:J83) -> 66857.5 | L84: =AVERAGE(L71:L83) -> 0.8 | M84: =AVERAGE(M71:M83) -> 0.2 | O84: =IF(SUM(O72:O83)>0,((AB84+AR84)/J84),0) -> 0.2 | P84: =IF(SUM(P72:P83)>0,((AC84+AS84)/J84),0) -> 0.3 | Q84: =IF(SUM(Q72:Q83)>0,((AD84+AT84)/J84),0) -> 0.15 | R84: =IF(SUM(R72:R83)>0,((AE84+AU84)/J84),0) -> 0.2 | S84: =IF(SUM(S72:S83)>0,((AF84+AV84)/J84),0) -> 0.15 | T84: =IF(SUM(T72:T83)>0,((AG84+AW84)/J84),0) -> 0 | U84: =IF(SUM(U72:U83)>0,((AH84+AX84)/J84),0) -> 0 | V84: =IF(SUM(V72:V83)>0,((AI84+AY84)/J84),0) -> 0 | W84: =IF(SUM(W72:W83)>0,((AJ84+AZ84)/J84),0) -> 0 | X84: =IF(SUM(X72:X83)>0,((AK84+BA84)/J84),0) -> 0 | Y84: =IF(SUM(Y72:Y83)>0,((AL84+BB84)/J84),0) -> 0 | Z84: =IF(SUM(Z72:Z83)>0,((AM84+BC84)/J84),0) -> 0 | AB84: =SUM(AB71:AB83) -> 10697.2 | AC84: =SUM(AC71:AC83) -> 16045.8 | AD84: =SUM(AD71:AD83) -> 8022.9 | AE84: =SUM(AE71:AE83) -> 10697.2 | AF84: =SUM(AF71:AF83) -> 8022.9 | AG84: =SUM(AG71:AG83) -> 0 | AH84: =SUM(AH71:AH83) -> 0 | AI84: =SUM(AI71:AI83) -> 0 | ... AP84: =SUM(AP71:AP83) -> 0 | AR84: =SUM(AR71:AR83) -> 2674.3 | AS84: =SUM(AS71:AS83) -> 4011.45 | AT84: =SUM(AT71:AT83) -> 2005.725 | AU84: =SUM(AU71:AU83) -> 2674.3 | AV84: =SUM(AV71:AV83) -> 2005.725 | AW84: =SUM(AW71:AW83) -> 0 | AX84: =SUM(AX71:AX83) -> 0 | AY84: =SUM(AY71:AY83) -> 0 | ... BF84: =SUM(BF71:BF83) -> 0 | BJ84: =IF(C70>0, C70, "") -> DevOps Engineer | BK84: N | BL84: =IF($BK84="Y",J84,0) -> 0 | BM84: =IF(BK84="Y", AN84,0) -> 0 | BN84: =IF((BK84="Y"),AO84,0) -> 0
BJ85: =IF(C71>0, C71, "")
A86: 6 | B86: Olivia Martinez | C86: Frontend Developer | BJ86: =IF(C73>0, C73, "")
D88: =D72 -> 45292 | E88: 4637.84 | F88: 1252.22 | G88: 310.36 | H88: 535.37 | I88: 185.51 | J88: =E88+H88+I88 -> 5358.72 | L88: 1 | M88: =1-L88 -> 0 | O88: 0.3 | Q88: 0.5 | S88: 0.2 | AB88: =IFERROR(($J88*O88)*$L88, "") -> 1607.616 | AC88: =IFERROR(($J88*P88)*$L88, "") -> 0 | AD88: =IFERROR(($J88*Q88)*$L88, "") -> 2679.36 | AE88: =IFERROR(($J88*R88)*$L88, "") -> 0 | AF88: =IFERROR(($J88*S88)*$L88, "") -> 1071.744 | AG88: =IFERROR(($J88*T88)*$L88, "") -> 0 | AH88: =IFERROR(($J88*U88)*$L88, "") -> 0 | AI88: =IFERROR(($J88*V88)*$L88, "") -> 0 | ... AM88: =IFERROR(($J88*Z88)*$L88, "") -> 0 | AN88: =IFERROR(SUMIF($AB$4:$AM$4, "RDEC", AB88:AM88), "") -> 0 | AO88: =IFERROR(SUMIF($AB$4:$AM$4, "SME", AB88:AM88), "") -> 5358.72 | AP88: =IFERROR(SUMIF($AB$4:$AM$4, "De Minimis", AB88:AM88), "") -> 0 | AR88: =IFERROR(($J88*O88)*$M88, "") -> 0 | AS88: =IFERROR(($J88*P88)*$M88, "") -> 0 | AT88: =IFERROR(($J88*Q88)*$M88, "") -> 0 | AU88: =IFERROR(($J88*R88)*$M88, "") -> 0 | AV88: =IFERROR(($J88*S88)*$M88, "") -> 0 | AW88: =IFERROR(($J88*T88)*$M88, "") -> 0 | AX88: =IFERROR(($J88*U88)*$M88, "") -> 0 | AY88: =IFERROR(($J88*V88)*$M88, "") -> 0 | ... BC88: =IFERROR(($J88*Z88)*$M88, "") -> 0 | BD88: =IFERROR(SUMIF($AB$4:$AM$4, "RDEC", AR88:BC88), "") -> 0 | BE88: =IFERROR(SUMIF($AB$4:$AM$4, "SME", AR88:BC88), "") -> 0 | BF88: =IFERROR(SUMIF($AB$4:$AM$4, "De Minimis", AR88:BC88), "") -> 0 | BH88: =IF((SUM(O88:Z88)>1),"ERROR","") | BJ88: =IF(C74>0, C74, "")
D89: =D73 -> 45323 | E89: 4608.89 | F89: 1244.4 | G89: 308.04 | H89: 531.38 | I89: 184.36 | J89: =E89+H89+I89 -> 5324.63 | L89: 1 | M89: =1-L89 -> 0 | O89: 0.3 | Q89: 0.5 | S89: 0.2 | AB89: =IFERROR(($J89*O89)*$L89, "") -> 1597.389 | AC89: =IFERROR(($J89*P89)*$L89, "") -> 0 | AD89: =IFERROR(($J89*Q89)*$L89, "") -> 2662.315 | AE89: =IFERROR(($J89*R89)*$L89, "") -> 0 | AF89: =IFERROR(($J89*S89)*$L89, "") -> 1064.926 | AG89: =IFERROR(($J89*T89)*$L89, "") -> 0 | AH89: =IFERROR(($J89*U89)*$L89, "") -> 0 | AI89: =IFERROR(($J89*V89)*$L89, "") -> 0 | ... AM89: =IFERROR(($J89*Z89)*$L89, "") -> 0 | AN89: =IFERROR(SUMIF($AB$4:$AM$4, "RDEC", AB89:AM89), "") -> 0 | AO89: =IFERROR(SUMIF($AB$4:$AM$4, "SME", AB89:AM89), "") -> 5324.63 | AP89: =IFERROR(SUMIF($AB$4:$AM$4, "De Minimis", AB89:AM89), "") -> 0 | AR89: =IFERROR(($J89*O89)*$M89, "") -> 0 | AS89: =IFERROR(($J89*P89)*$M89, "") -> 0 | AT89: =IFERROR(($J89*Q89)*$M89, "") -> 0 | AU89: =IFERROR(($J89*R89)*$M89, "") -> 0 | AV89: =IFERROR(($J89*S89)*$M89, "") -> 0 | AW89: =IFERROR(($J89*T89)*$M89, "") -> 0 | AX89: =IFERROR(($J89*U89)*$M89, "") -> 0 | AY89: =IFERROR(($J89*V89)*$M89, "") -> 0 | ... BC89: =IFERROR(($J89*Z89)*$M89, "") -> 0 | BD89: =IFERROR(SUMIF($AB$4:$AM$4, "RDEC", AR89:BC89), "") -> 0 | BE89: =IFERROR(SUMIF($AB$4:$AM$4, "SME", AR89:BC89), "") -> 0 | BF89: =IFERROR(SUMIF($AB$4:$AM$4, "De Minimis", AR89:BC89), "") -> 0 | BH89: =IF((SUM(O89:Z89)>1),"ERROR","") | BJ89: =IF(C75>0, C75, "")
D90: =D74 -> 45352 | E90: 4584.34 | F90: 1237.77 | G90: 306.08 | H90: 527.99 | I90: 183.37 | J90: =E90+H90+I90 -> 5295.7 | L90: 1 | M90: =1-L90 -> 0 | O90: 0.3 | Q90: 0.5 | S90: 0.2 | AB90: =IFERROR(($J90*O90)*$L90, "") -> 1588.71 | AC90: =IFERROR(($J90*P90)*$L90, "") -> 0 | AD90: =IFERROR(($J90*Q90)*$L90, "") -> 2647.85 | AE90: =IFERROR(($J90*R90)*$L90, "") -> 0 | AF90: =IFERROR(($J90*S90)*$L90, "") -> 1059.14 | AG90: =IFERROR(($J90*T90)*$L90, "") -> 0 | AH90: =IFERROR(($J90*U90)*$L90, "") -> 0 | AI90: =IFERROR(($J90*V90)*$L90, "") -> 0 | ... AM90: =IFERROR(($J90*Z90)*$L90, "") -> 0 | AN90: =IFERROR(SUMIF($AB$4:$AM$4, "RDEC", AB90:AM90), "") -> 0 | AO90: =IFERROR(SUMIF($AB$4:$AM$4, "SME", AB90:AM90), "") -> 5295.7 | AP90: =IFERROR(SUMIF($AB$4:$AM$4, "De Minimis", AB90:AM90), "") -> 0 | AR90: =IFERROR(($J90*O90)*$M90, "") -> 0 | AS90: =IFERROR(($J90*P90)*$M90, "") -> 0 | AT90: =IFERROR(($J90*Q90)*$M90, "") -> 0 | AU90: =IFERROR(($J90*R90)*$M90, "") -> 0 | AV90: =IFERROR(($J90*S90)*$M90, "") -> 0 | AW90: =IFERROR(($J90*T90)*$M90, "") -> 0 | AX90: =IFERROR(($J90*U90)*$M90, "") -> 0 | AY90: =IFERROR(($J90*V90)*$M90, "") -> 0 | ... BC90: =IFERROR(($J90*Z90)*$M90, "") -> 0 | BD90: =IFERROR(SUMIF($AB$4:$AM$4, "RDEC", AR90:BC90), "") -> 0 | BE90: =IFERROR(SUMIF($AB$4:$AM$4, "SME", AR90:BC90), "") -> 0 | BF90: =IFERROR(SUMIF($AB$4:$AM$4, "De Minimis", AR90:BC90), "") -> 0 | BH90: =IF((SUM(O90:Z90)>1),"ERROR","") | BJ90: =IF(C76>0, C76, "")
D91: =D75 -> 45383 | E91: 4523.01 | F91: 1221.21 | G91: 301.17 | H91: 519.53 | I91: 180.92 | J91: =E91+H91+I91 -> 5223.46 | L91: 1 | M91: =1-L91 -> 0 | O91: 0.3 | Q91: 0.5 | S91: 0.2 | AB91: =IFERROR(($J91*O91)*$L91, "") -> 1567.038 | AC91: =IFERROR(($J91*P91)*$L91, "") -> 0 | AD91: =IFERROR(($J91*Q91)*$L91, "") -> 2611.73 | AE91: =IFERROR(($J91*R91)*$L91, "") -> 0 | AF91: =IFERROR(($J91*S91)*$L91, "") -> 1044.692 | AG91: =IFERROR(($J91*T91)*$L91, "") -> 0 | AH91: =IFERROR(($J91*U91)*$L91, "") -> 0 | AI91: =IFERROR(($J91*V91)*$L91, "") -> 0 | ... AM91: =IFERROR(($J91*Z91)*$L91, "") -> 0 | AN91: =IFERROR(SUMIF($AB$4:$AM$4, "RDEC", AB91:AM91), "") -> 0 | AO91: =IFERROR(SUMIF($AB$4:$AM$4, "SME", AB91:AM91), "") -> 5223.46 | AP91: =IFERROR(SUMIF($AB$4:$AM$4, "De Minimis", AB91:AM91), "") -> 0 | AR91: =IFERROR(($J91*O91)*$M91, "") -> 0 | AS91: =IFERROR(($J91*P91)*$M91, "") -> 0 | AT91: =IFERROR(($J91*Q91)*$M91, "") -> 0 | AU91: =IFERROR(($J91*R91)*$M91, "") -> 0 | AV91: =IFERROR(($J91*S91)*$M91, "") -> 0 | AW91: =IFERROR(($J91*T91)*$M91, "") -> 0 | AX91: =IFERROR(($J91*U91)*$M91, "") -> 0 | AY91: =IFERROR(($J91*V91)*$M91, "") -> 0 | ... BC91: =IFERROR(($J91*Z91)*$M91, "") -> 0 | BD91: =IFERROR(SUMIF($AB$4:$AM$4, "RDEC", AR91:BC91), "") -> 0 | BE91: =IFERROR(SUMIF($AB$4:$AM$4, "SME", AR91:BC91), "") -> 0 | BF91: =IFERROR(SUMIF($AB$4:$AM$4, "De Minimis", AR91:BC91), "") -> 0 | BH91: =IF((SUM(O91:Z91)>1),"ERROR","") | BJ91: =IF(C77>0, C77, "")
D92: =D76 -> 45413 | E92: 4576.53 | F92: 1235.66 | G92: 305.46 | H92: 526.91 | I92: 183.06 | J92: =E92+H92+I92 -> 5286.5 | L92: 1 | M92: =1-L92 -> 0 | O92: 0.3 | Q92: 0.5 | S92: 0.2 | AB92: =IFERROR(($J92*O92)*$L92, "") -> 1585.95 | AC92: =IFERROR(($J92*P92)*$L92, "") -> 0 | AD92: =IFERROR(($J92*Q92)*$L92, "") -> 2643.25 | AE92: =IFERROR(($J92*R92)*$L92, "") -> 0 | AF92: =IFERROR(($J92*S92)*$L92, "") -> 1057.3 | AG92: =IFERROR(($J92*T92)*$L92, "") -> 0 | AH92: =IFERROR(($J92*U92)*$L92, "") -> 0 | AI92: =IFERROR(($J92*V92)*$L92, "") -> 0 | ... AM92: =IFERROR(($J92*Z92)*$L92, "") -> 0 | AN92: =IFERROR(SUMIF($AB$4:$AM$4, "RDEC", AB92:AM92), "") -> 0 | AO92: =IFERROR(SUMIF($AB$4:$AM$4, "SME", AB92:AM92), "") -> 5286.5 | AP92: =IFERROR(SUMIF($AB$4:$AM$4, "De Minimis", AB92:AM92), "") -> 0 | AR92: =IFERROR(($J92*O92)*$M92, "") -> 0 | AS92: =IFERROR(($J92*P92)*$M92, "") -> 0 | AT92: =IFERROR(($J92*Q92)*$M92, "") -> 0 | AU92: =IFERROR(($J92*R92)*$M92, "") -> 0 | AV92: =IFERROR(($J92*S92)*$M92, "") -> 0 | AW92: =IFERROR(($J92*T92)*$M92, "") -> 0 | AX92: =IFERROR(($J92*U92)*$M92, "") -> 0 | AY92: =IFERROR(($J92*V92)*$M92, "") -> 0 | ... BC92: =IFERROR(($J92*Z92)*$M92, "") -> 0 | BD92: =IFERROR(SUMIF($AB$4:$AM$4, "RDEC", AR92:BC92), "") -> 0 | BE92: =IFERROR(SUMIF($AB$4:$AM$4, "SME", AR92:BC92), "") -> 0 | BF92: =IFERROR(SUMIF($AB$4:$AM$4, "De Minimis", AR92:BC92), "") -> 0 | BH92: =IF((SUM(O92:Z92)>1),"ERROR","") | BJ92: =IF(C78>0, C78, "")
D93: =D77 -> 45444 | E93: 4519.09 | F93: 1220.15 | G93: 300.86 | H93: 518.98 | I93: 180.76 | J93: =E93+H93+I93 -> 5218.83 | L93: 1 | M93: =1-L93 -> 0 | O93: 0.3 | Q93: 0.5 | S93: 0.2 | AB93: =IFERROR(($J93*O93)*$L93, "") -> 1565.649 | AC93: =IFERROR(($J93*P93)*$L93, "") -> 0 | AD93: =IFERROR(($J93*Q93)*$L93, "") -> 2609.415 | AE93: =IFERROR(($J93*R93)*$L93, "") -> 0 | AF93: =IFERROR(($J93*S93)*$L93, "") -> 1043.766 | AG93: =IFERROR(($J93*T93)*$L93, "") -> 0 | AH93: =IFERROR(($J93*U93)*$L93, "") -> 0 | AI93: =IFERROR(($J93*V93)*$L93, "") -> 0 | ... AM93: =IFERROR(($J93*Z93)*$L93, "") -> 0 | AN93: =IFERROR(SUMIF($AB$4:$AM$4, "RDEC", AB93:AM93), "") -> 0 | AO93: =IFERROR(SUMIF($AB$4:$AM$4, "SME", AB93:AM93), "") -> 5218.83 | AP93: =IFERROR(SUMIF($AB$4:$AM$4, "De Minimis", AB93:AM93), "") -> 0 | AR93: =IFERROR(($J93*O93)*$M93, "") -> 0 | AS93: =IFERROR(($J93*P93)*$M93, "") -> 0 | AT93: =IFERROR(($J93*Q93)*$M93, "") -> 0 | AU93: =IFERROR(($J93*R93)*$M93, "") -> 0 | AV93: =IFERROR(($J93*S93)*$M93, "") -> 0 | AW93: =IFERROR(($J93*T93)*$M93, "") -> 0 | AX93: =IFERROR(($J93*U93)*$M93, "") -> 0 | AY93: =IFERROR(($J93*V93)*$M93, "") -> 0 | ... BC93: =IFERROR(($J93*Z93)*$M93, "") -> 0 | BD93: =IFERROR(SUMIF($AB$4:$AM$4, "RDEC", AR93:BC93), "") -> 0 | BE93: =IFERROR(SUMIF($AB$4:$AM$4, "SME", AR93:BC93), "") -> 0 | BF93: =IFERROR(SUMIF($AB$4:$AM$4, "De Minimis", AR93:BC93), "") -> 0 | BH93: =IF((SUM(O93:Z93)>1),"ERROR","") | BJ93: =IF(C79>0, C79, "")
D94: =D78 -> 45474 | E94: 4630.52 | F94: 1250.24 | G94: 309.78 | H94: 534.36 | I94: 185.22 | J94: =E94+H94+I94 -> 5350.1 | L94: 1 | M94: =1-L94 -> 0 | O94: 0.3 | Q94: 0.5 | S94: 0.2 | AB94: =IFERROR(($J94*O94)*$L94, "") -> 1605.03 | AC94: =IFERROR(($J94*P94)*$L94, "") -> 0 | AD94: =IFERROR(($J94*Q94)*$L94, "") -> 2675.05 | AE94: =IFERROR(($J94*R94)*$L94, "") -> 0 | AF94: =IFERROR(($J94*S94)*$L94, "") -> 1070.02 | AG94: =IFERROR(($J94*T94)*$L94, "") -> 0 | AH94: =IFERROR(($J94*U94)*$L94, "") -> 0 | AI94: =IFERROR(($J94*V94)*$L94, "") -> 0 | ... AM94: =IFERROR(($J94*Z94)*$L94, "") -> 0 | AN94: =IFERROR(SUMIF($AB$4:$AM$4, "RDEC", AB94:AM94), "") -> 0 | AO94: =IFERROR(SUMIF($AB$4:$AM$4, "SME", AB94:AM94), "") -> 5350.1 | AP94: =IFERROR(SUMIF($AB$4:$AM$4, "De Minimis", AB94:AM94), "") -> 0 | AR94: =IFERROR(($J94*O94)*$M94, "") -> 0 | AS94: =IFERROR(($J94*P94)*$M94, "") -> 0 | AT94: =IFERROR(($J94*Q94)*$M94, "") -> 0 | AU94: =IFERROR(($J94*R94)*$M94, "") -> 0 | AV94: =IFERROR(($J94*S94)*$M94, "") -> 0 | AW94: =IFERROR(($J94*T94)*$M94, "") -> 0 | AX94: =IFERROR(($J94*U94)*$M94, "") -> 0 | AY94: =IFERROR(($J94*V94)*$M94, "") -> 0 | ... BC94: =IFERROR(($J94*Z94)*$M94, "") -> 0 | BD94: =IFERROR(SUMIF($AB$4:$AM$4, "RDEC", AR94:BC94), "") -> 0 | BE94: =IFERROR(SUMIF($AB$4:$AM$4, "SME", AR94:BC94), "") -> 0 | BF94: =IFERROR(SUMIF($AB$4:$AM$4, "De Minimis", AR94:BC94), "") -> 0 | BH94: =IF((SUM(O94:Z94)>1),"ERROR","") | BJ94: =IF(C80>0, C80, "")
D95: =D79 -> 45505 | E95: 4580.06 | F95: 1236.62 | G95: 305.74 | H95: 527.4 | I95: 183.2 | J95: =E95+H95+I95 -> 5290.66 | L95: 1 | M95: =1-L95 -> 0 | O95: 0.3 | Q95: 0.5 | S95: 0.2 | AB95: =IFERROR(($J95*O95)*$L95, "") -> 1587.198 | AC95: =IFERROR(($J95*P95)*$L95, "") -> 0 | AD95: =IFERROR(($J95*Q95)*$L95, "") -> 2645.33 | AE95: =IFERROR(($J95*R95)*$L95, "") -> 0 | AF95: =IFERROR(($J95*S95)*$L95, "") -> 1058.132 | AG95: =IFERROR(($J95*T95)*$L95, "") -> 0 | AH95: =IFERROR(($J95*U95)*$L95, "") -> 0 | AI95: =IFERROR(($J95*V95)*$L95, "") -> 0 | ... AM95: =IFERROR(($J95*Z95)*$L95, "") -> 0 | AN95: =IFERROR(SUMIF($AB$4:$AM$4, "RDEC", AB95:AM95), "") -> 0 | AO95: =IFERROR(SUMIF($AB$4:$AM$4, "SME", AB95:AM95), "") -> 5290.66 | AP95: =IFERROR(SUMIF($AB$4:$AM$4, "De Minimis", AB95:AM95), "") -> 0 | AR95: =IFERROR(($J95*O95)*$M95, "") -> 0 | AS95: =IFERROR(($J95*P95)*$M95, "") -> 0 | AT95: =IFERROR(($J95*Q95)*$M95, "") -> 0 | AU95: =IFERROR(($J95*R95)*$M95, "") -> 0 | AV95: =IFERROR(($J95*S95)*$M95, "") -> 0 | AW95: =IFERROR(($J95*T95)*$M95, "") -> 0 | AX95: =IFERROR(($J95*U95)*$M95, "") -> 0 | AY95: =IFERROR(($J95*V95)*$M95, "") -> 0 | ... BC95: =IFERROR(($J95*Z95)*$M95, "") -> 0 | BD95: =IFERROR(SUMIF($AB$4:$AM$4, "RDEC", AR95:BC95), "") -> 0 | BE95: =IFERROR(SUMIF($AB$4:$AM$4, "SME", AR95:BC95), "") -> 0 | BF95: =IFERROR(SUMIF($AB$4:$AM$4, "De Minimis", AR95:BC95), "") -> 0 | BH95: =IF((SUM(O95:Z95)>1),"ERROR","") | BJ95: =IF(C81>0, C81, "")
D96: =D80 -> 45536 | E96: 4591 | F96: 1239.57 | G96: 306.61 | H96: 528.91 | I96: 183.64 | J96: =E96+H96+I96 -> 5303.55 | L96: 1 | M96: =1-L96 -> 0 | O96: 0.3 | Q96: 0.5 | S96: 0.2 | AB96: =IFERROR(($J96*O96)*$L96, "") -> 1591.065 | AC96: =IFERROR(($J96*P96)*$L96, "") -> 0 | AD96: =IFERROR(($J96*Q96)*$L96, "") -> 2651.775 | AE96: =IFERROR(($J96*R96)*$L96, "") -> 0 | AF96: =IFERROR(($J96*S96)*$L96, "") -> 1060.71 | AG96: =IFERROR(($J96*T96)*$L96, "") -> 0 | AH96: =IFERROR(($J96*U96)*$L96, "") -> 0 | AI96: =IFERROR(($J96*V96)*$L96, "") -> 0 | ... AM96: =IFERROR(($J96*Z96)*$L96, "") -> 0 | AN96: =IFERROR(SUMIF($AB$4:$AM$4, "RDEC", AB96:AM96), "") -> 0 | AO96: =IFERROR(SUMIF($AB$4:$AM$4, "SME", AB96:AM96), "") -> 5303.55 | AP96: =IFERROR(SUMIF($AB$4:$AM$4, "De Minimis", AB96:AM96), "") -> 0 | AR96: =IFERROR(($J96*O96)*$M96, "") -> 0 | AS96: =IFERROR(($J96*P96)*$M96, "") -> 0 | AT96: =IFERROR(($J96*Q96)*$M96, "") -> 0 | AU96: =IFERROR(($J96*R96)*$M96, "") -> 0 | AV96: =IFERROR(($J96*S96)*$M96, "") -> 0 | AW96: =IFERROR(($J96*T96)*$M96, "") -> 0 | AX96: =IFERROR(($J96*U96)*$M96, "") -> 0 | AY96: =IFERROR(($J96*V96)*$M96, "") -> 0 | ... BC96: =IFERROR(($J96*Z96)*$M96, "") -> 0 | BD96: =IFERROR(SUMIF($AB$4:$AM$4, "RDEC", AR96:BC96), "") -> 0 | BE96: =IFERROR(SUMIF($AB$4:$AM$4, "SME", AR96:BC96), "") -> 0 | BF96: =IFERROR(SUMIF($AB$4:$AM$4, "De Minimis", AR96:BC96), "") -> 0 | BH96: =IF((SUM(O96:Z96)>1),"ERROR","") | BJ96: =IF(C82>0, C82, "")
D97: =D81 -> 45566 | E97: 4620.87 | F97: 1247.63 | G97: 309 | H97: 533.03 | I97: 184.83 | J97: =E97+H97+I97 -> 5338.73 | L97: 1 | M97: =1-L97 -> 0 | O97: 0.3 | Q97: 0.5 | S97: 0.2 | AB97: =IFERROR(($J97*O97)*$L97, "") -> 1601.619 | AC97: =IFERROR(($J97*P97)*$L97, "") -> 0 | AD97: =IFERROR(($J97*Q97)*$L97, "") -> 2669.365 | AE97: =IFERROR(($J97*R97)*$L97, "") -> 0 | AF97: =IFERROR(($J97*S97)*$L97, "") -> 1067.746 | AG97: =IFERROR(($J97*T97)*$L97, "") -> 0 | AH97: =IFERROR(($J97*U97)*$L97, "") -> 0 | AI97: =IFERROR(($J97*V97)*$L97, "") -> 0 | ... AM97: =IFERROR(($J97*Z97)*$L97, "") -> 0 | AN97: =IFERROR(SUMIF($AB$4:$AM$4, "RDEC", AB97:AM97), "") -> 0 | AO97: =IFERROR(SUMIF($AB$4:$AM$4, "SME", AB97:AM97), "") -> 5338.73 | AP97: =IFERROR(SUMIF($AB$4:$AM$4, "De Minimis", AB97:AM97), "") -> 0 | AR97: =IFERROR(($J97*O97)*$M97, "") -> 0 | AS97: =IFERROR(($J97*P97)*$M97, "") -> 0 | AT97: =IFERROR(($J97*Q97)*$M97, "") -> 0 | AU97: =IFERROR(($J97*R97)*$M97, "") -> 0 | AV97: =IFERROR(($J97*S97)*$M97, "") -> 0 | AW97: =IFERROR(($J97*T97)*$M97, "") -> 0 | AX97: =IFERROR(($J97*U97)*$M97, "") -> 0 | AY97: =IFERROR(($J97*V97)*$M97, "") -> 0 | ... BC97: =IFERROR(($J97*Z97)*$M97, "") -> 0 | BD97: =IFERROR(SUMIF($AB$4:$AM$4, "RDEC", AR97:BC97), "") -> 0 | BE97: =IFERROR(SUMIF($AB$4:$AM$4, "SME", AR97:BC97), "") -> 0 | BF97: =IFERROR(SUMIF($AB$4:$AM$4, "De Minimis", AR97:BC97), "") -> 0 | BH97: =IF((SUM(O97:Z97)>1),"ERROR","") | BJ97: =IF(C83>0, C83, "")
D98: =D82 -> 45597 | E98: 4617.17 | F98: 1246.64 | G98: 308.71 | H98: 532.52 | I98: 184.69 | J98: =E98+H98+I98 -> 5334.38 | L98: 1 | M98: =1-L98 -> 0 | O98: 0.3 | Q98: 0.5 | S98: 0.2 | AB98: =IFERROR(($J98*O98)*$L98, "") -> 1600.314 | AC98: =IFERROR(($J98*P98)*$L98, "") -> 0 | AD98: =IFERROR(($J98*Q98)*$L98, "") -> 2667.19 | AE98: =IFERROR(($J98*R98)*$L98, "") -> 0 | AF98: =IFERROR(($J98*S98)*$L98, "") -> 1066.876 | AG98: =IFERROR(($J98*T98)*$L98, "") -> 0 | AH98: =IFERROR(($J98*U98)*$L98, "") -> 0 | AI98: =IFERROR(($J98*V98)*$L98, "") -> 0 | ... AM98: =IFERROR(($J98*Z98)*$L98, "") -> 0 | AN98: =IFERROR(SUMIF($AB$4:$AM$4, "RDEC", AB98:AM98), "") -> 0 | AO98: =IFERROR(SUMIF($AB$4:$AM$4, "SME", AB98:AM98), "") -> 5334.38 | AP98: =IFERROR(SUMIF($AB$4:$AM$4, "De Minimis", AB98:AM98), "") -> 0 | AR98: =IFERROR(($J98*O98)*$M98, "") -> 0 | AS98: =IFERROR(($J98*P98)*$M98, "") -> 0 | AT98: =IFERROR(($J98*Q98)*$M98, "") -> 0 | AU98: =IFERROR(($J98*R98)*$M98, "") -> 0 | AV98: =IFERROR(($J98*S98)*$M98, "") -> 0 | AW98: =IFERROR(($J98*T98)*$M98, "") -> 0 | AX98: =IFERROR(($J98*U98)*$M98, "") -> 0 | AY98: =IFERROR(($J98*V98)*$M98, "") -> 0 | ... BC98: =IFERROR(($J98*Z98)*$M98, "") -> 0 | BD98: =IFERROR(SUMIF($AB$4:$AM$4, "RDEC", AR98:BC98), "") -> 0 | BE98: =IFERROR(SUMIF($AB$4:$AM$4, "SME", AR98:BC98), "") -> 0 | BF98: =IFERROR(SUMIF($AB$4:$AM$4, "De Minimis", AR98:BC98), "") -> 0 | BH98: =IF((SUM(O98:Z98)>1),"ERROR","") | BJ98: =IF(C84>0, C84, "")
D99: =D83 -> 45627 | E99: 4511.55 | F99: 1218.12 | G99: 300.26 | H99: 517.94 | I99: 180.46 | J99: =E99+H99+I99 -> 5209.95 | L99: 1 | M99: =1-L99 -> 0 | O99: 0.3 | Q99: 0.5 | S99: 0.2 | AB99: =IFERROR(($J99*O99)*$L99, "") -> 1562.985 | AC99: =IFERROR(($J99*P99)*$L99, "") -> 0 | AD99: =IFERROR(($J99*Q99)*$L99, "") -> 2604.975 | AE99: =IFERROR(($J99*R99)*$L99, "") -> 0 | AF99: =IFERROR(($J99*S99)*$L99, "") -> 1041.99 | AG99: =IFERROR(($J99*T99)*$L99, "") -> 0 | AH99: =IFERROR(($J99*U99)*$L99, "") -> 0 | AI99: =IFERROR(($J99*V99)*$L99, "") -> 0 | ... AM99: =IFERROR(($J99*Z99)*$L99, "") -> 0 | AN99: =IFERROR(SUMIF($AB$4:$AM$4, "RDEC", AB99:AM99), "") -> 0 | AO99: =IFERROR(SUMIF($AB$4:$AM$4, "SME", AB99:AM99), "") -> 5209.95 | AP99: =IFERROR(SUMIF($AB$4:$AM$4, "De Minimis", AB99:AM99), "") -> 0 | AR99: =IFERROR(($J99*O99)*$M99, "") -> 0 | AS99: =IFERROR(($J99*P99)*$M99, "") -> 0 | AT99: =IFERROR(($J99*Q99)*$M99, "") -> 0 | AU99: =IFERROR(($J99*R99)*$M99, "") -> 0 | AV99: =IFERROR(($J99*S99)*$M99, "") -> 0 | AW99: =IFERROR(($J99*T99)*$M99, "") -> 0 | AX99: =IFERROR(($J99*U99)*$M99, "") -> 0 | AY99: =IFERROR(($J99*V99)*$M99, "") -> 0 | ... BC99: =IFERROR(($J99*Z99)*$M99, "") -> 0 | BD99: =IFERROR(SUMIF($AB$4:$AM$4, "RDEC", AR99:BC99), "") -> 0 | BE99: =IFERROR(SUMIF($AB$4:$AM$4, "SME", AR99:BC99), "") -> 0 | BF99: =IFERROR(SUMIF($AB$4:$AM$4, "De Minimis", AR99:BC99), "") -> 0 | BH99: =IF((SUM(O99:Z99)>1),"ERROR","") | BJ99: =IF(C85>0, C85, "")
D100: Total | E100: =SUM(E87:E99) -> 55000.87 | F100: =SUM(F87:F99) -> 14850.23 | G100: =SUM(G87:G99) -> 3672.07 | H100: =SUM(H87:H99) -> 6334.32 | I100: =SUM(I87:I99) -> 2200.02 | J100: =SUM(J87:J99) -> 63535.21 | L100: =AVERAGE(L87:L99) -> 1 | M100: =AVERAGE(M87:M99) -> 0 | O100: =IF(SUM(O88:O99)>0,((AB100+AR100)/J100),0) -> 0.3 | P100: =IF(SUM(P88:P99)>0,((AC100+AS100)/J100),0) -> 0 | Q100: =IF(SUM(Q88:Q99)>0,((AD100+AT100)/J100),0) -> 0.5 | R100: =IF(SUM(R88:R99)>0,((AE100+AU100)/J100),0) -> 0 | S100: =IF(SUM(S88:S99)>0,((AF100+AV100)/J100),0) -> 0.2 | T100: =IF(SUM(T88:T99)>0,((AG100+AW100)/J100),0) -> 0 | U100: =IF(SUM(U88:U99)>0,((AH100+AX100)/J100),0) -> 0 | V100: =IF(SUM(V88:V99)>0,((AI100+AY100)/J100),0) -> 0 | W100: =IF(SUM(W88:W99)>0,((AJ100+AZ100)/J100),0) -> 0 | X100: =IF(SUM(X88:X99)>0,((AK100+BA100)/J100),0) -> 0 | Y100: =IF(SUM(Y88:Y99)>0,((AL100+BB100)/J100),0) -> 0 | Z100: =IF(SUM(Z88:Z99)>0,((AM100+BC100)/J100),0) -> 0 | AB100: =SUM(AB87:AB99) -> 19060.563 | AC100: =SUM(AC87:AC99) -> 0 | AD100: =SUM(AD87:AD99) -> 31767.605 | AE100: =SUM(AE87:AE99) -> 0 | AF100: =SUM(AF87:AF99) -> 12707.042 | AG100: =SUM(AG87:AG99) -> 0 | AH100: =SUM(AH87:AH99) -> 0 | AI100: =SUM(AI87:AI99) -> 0 | ... AP100: =SUM(AP87:AP99) -> 0 | AR100: =SUM(AR87:AR99) -> 0 | AS100: =SUM(AS87:AS99) -> 0 | AT100: =SUM(AT87:AT99) -> 0 | AU100: =SUM(AU87:AU99) -> 0 | AV100: =SUM(AV87:AV99) -> 0 | AW100: =SUM(AW87:AW99) -> 0 | AX100: =SUM(AX87:AX99) -> 0 | AY100: =SUM(AY87:AY99) -> 0 | ... BF100: =SUM(BF87:BF99) -> 0 | BJ100: =IF(C86>0, C86, "") -> Frontend Developer | BK100: N | BL100: =IF($BK100="Y",J100,0) -> 0 | BM100: =IF(BK100="Y", AN100,0) -> 0 | BN100: =IF((BK100="Y"),AO100,0) -> 0
BJ101: =IF(C87>0, C87, "")
A102: 7 | B102: Tom Baker | C102: QA Engineer | BJ102: =IF(C89>0, C89, "")
D104: =D88 -> 45292 | E104: 4070.49 | F104: 895.51 | G104: 264.97 | H104: 457.08 | I104: 162.82 | J104: =E104+H104+I104 -> 4690.39 | L104: 1 | M104: =1-L104 -> 0 | O104: 0.25 | P104: 0.25 | Q104: 0.25 | R104: 0.25 | AB104: =IFERROR(($J104*O104)*$L104, "") -> 1172.5975 | AC104: =IFERROR(($J104*P104)*$L104, "") -> 1172.5975 | AD104: =IFERROR(($J104*Q104)*$L104, "") -> 1172.5975 | AE104: =IFERROR(($J104*R104)*$L104, "") -> 1172.5975 | AF104: =IFERROR(($J104*S104)*$L104, "") -> 0 | AG104: =IFERROR(($J104*T104)*$L104, "") -> 0 | AH104: =IFERROR(($J104*U104)*$L104, "") -> 0 | AI104: =IFERROR(($J104*V104)*$L104, "") -> 0 | ... AM104: =IFERROR(($J104*Z104)*$L104, "") -> 0 | AN104: =IFERROR(SUMIF($AB$4:$AM$4, "RDEC", AB104:AM104), "") -> 1172.5975 | AO104: =IFERROR(SUMIF($AB$4:$AM$4, "SME", AB104:AM104), "") -> 3517.7925 | AP104: =IFERROR(SUMIF($AB$4:$AM$4, "De Minimis", AB104:AM104), "") -> 0 | AR104: =IFERROR(($J104*O104)*$M104, "") -> 0 | AS104: =IFERROR(($J104*P104)*$M104, "") -> 0 | AT104: =IFERROR(($J104*Q104)*$M104, "") -> 0 | AU104: =IFERROR(($J104*R104)*$M104, "") -> 0 | AV104: =IFERROR(($J104*S104)*$M104, "") -> 0 | AW104: =IFERROR(($J104*T104)*$M104, "") -> 0 | AX104: =IFERROR(($J104*U104)*$M104, "") -> 0 | AY104: =IFERROR(($J104*V104)*$M104, "") -> 0 | ... BC104: =IFERROR(($J104*Z104)*$M104, "") -> 0 | BD104: =IFERROR(SUMIF($AB$4:$AM$4, "RDEC", AR104:BC104), "") -> 0 | BE104: =IFERROR(SUMIF($AB$4:$AM$4, "SME", AR104:BC104), "") -> 0 | BF104: =IFERROR(SUMIF($AB$4:$AM$4, "De Minimis", AR104:BC104), "") -> 0 | BH104: =IF((SUM(O104:Z104)>1),"ERROR","") | BJ104: =IF(C90>0, C90, "")
D105: =D89 -> 45323 | E105: 3950.83 | F105: 869.18 | G105: 255.4 | H105: 440.57 | I105: 158.03 | J105: =E105+H105+I105 -> 4549.43 | L105: 1 | M105: =1-L105 -> 0 | O105: 0.25 | P105: 0.25 | Q105: 0.25 | R105: 0.25 | AB105: =IFERROR(($J105*O105)*$L105, "") -> 1137.3575 | AC105: =IFERROR(($J105*P105)*$L105, "") -> 1137.3575 | AD105: =IFERROR(($J105*Q105)*$L105, "") -> 1137.3575 | AE105: =IFERROR(($J105*R105)*$L105, "") -> 1137.3575 | AF105: =IFERROR(($J105*S105)*$L105, "") -> 0 | AG105: =IFERROR(($J105*T105)*$L105, "") -> 0 | AH105: =IFERROR(($J105*U105)*$L105, "") -> 0 | AI105: =IFERROR(($J105*V105)*$L105, "") -> 0 | ... AM105: =IFERROR(($J105*Z105)*$L105, "") -> 0 | AN105: =IFERROR(SUMIF($AB$4:$AM$4, "RDEC", AB105:AM105), "") -> 1137.3575 | AO105: =IFERROR(SUMIF($AB$4:$AM$4, "SME", AB105:AM105), "") -> 3412.0725 | AP105: =IFERROR(SUMIF($AB$4:$AM$4, "De Minimis", AB105:AM105), "") -> 0 | AR105: =IFERROR(($J105*O105)*$M105, "") -> 0 | AS105: =IFERROR(($J105*P105)*$M105, "") -> 0 | AT105: =IFERROR(($J105*Q105)*$M105, "") -> 0 | AU105: =IFERROR(($J105*R105)*$M105, "") -> 0 | AV105: =IFERROR(($J105*S105)*$M105, "") -> 0 | AW105: =IFERROR(($J105*T105)*$M105, "") -> 0 | AX105: =IFERROR(($J105*U105)*$M105, "") -> 0 | AY105: =IFERROR(($J105*V105)*$M105, "") -> 0 | ... BC105: =IFERROR(($J105*Z105)*$M105, "") -> 0 | BD105: =IFERROR(SUMIF($AB$4:$AM$4, "RDEC", AR105:BC105), "") -> 0 | BE105: =IFERROR(SUMIF($AB$4:$AM$4, "SME", AR105:BC105), "") -> 0 | BF105: =IFERROR(SUMIF($AB$4:$AM$4, "De Minimis", AR105:BC105), "") -> 0 | BH105: =IF((SUM(O105:Z105)>1),"ERROR","") | BJ105: =IF(C91>0, C91, "")
D106: =D90 -> 45352 | E106: 3984.2 | F106: 876.52 | G106: 258.07 | H106: 445.17 | I106: 159.37 | J106: =E106+H106+I106 -> 4588.74 | L106: 1 | M106: =1-L106 -> 0 | O106: 0.25 | P106: 0.25 | Q106: 0.25 | R106: 0.25 | AB106: =IFERROR(($J106*O106)*$L106, "") -> 1147.185 | AC106: =IFERROR(($J106*P106)*$L106, "") -> 1147.185 | AD106: =IFERROR(($J106*Q106)*$L106, "") -> 1147.185 | AE106: =IFERROR(($J106*R106)*$L106, "") -> 1147.185 | AF106: =IFERROR(($J106*S106)*$L106, "") -> 0 | AG106: =IFERROR(($J106*T106)*$L106, "") -> 0 | AH106: =IFERROR(($J106*U106)*$L106, "") -> 0 | AI106: =IFERROR(($J106*V106)*$L106, "") -> 0 | ... AM106: =IFERROR(($J106*Z106)*$L106, "") -> 0 | AN106: =IFERROR(SUMIF($AB$4:$AM$4, "RDEC", AB106:AM106), "") -> 1147.185 | AO106: =IFERROR(SUMIF($AB$4:$AM$4, "SME", AB106:AM106), "") -> 3441.555 | AP106: =IFERROR(SUMIF($AB$4:$AM$4, "De Minimis", AB106:AM106), "") -> 0 | AR106: =IFERROR(($J106*O106)*$M106, "") -> 0 | AS106: =IFERROR(($J106*P106)*$M106, "") -> 0 | AT106: =IFERROR(($J106*Q106)*$M106, "") -> 0 | AU106: =IFERROR(($J106*R106)*$M106, "") -> 0 | AV106: =IFERROR(($J106*S106)*$M106, "") -> 0 | AW106: =IFERROR(($J106*T106)*$M106, "") -> 0 | AX106: =IFERROR(($J106*U106)*$M106, "") -> 0 | AY106: =IFERROR(($J106*V106)*$M106, "") -> 0 | ... BC106: =IFERROR(($J106*Z106)*$M106, "") -> 0 | BD106: =IFERROR(SUMIF($AB$4:$AM$4, "RDEC", AR106:BC106), "") -> 0 | BE106: =IFERROR(SUMIF($AB$4:$AM$4, "SME", AR106:BC106), "") -> 0 | BF106: =IFERROR(SUMIF($AB$4:$AM$4, "De Minimis", AR106:BC106), "") -> 0 | BH106: =IF((SUM(O106:Z106)>1),"ERROR","") | BJ106: =IF(C92>0, C92, "")
D107: =D91 -> 45383 | E107: 3946.37 | F107: 868.2 | G107: 255.04 | H107: 439.95 | I107: 157.85 | J107: =E107+H107+I107 -> 4544.17 | L107: 1 | M107: =1-L107 -> 0 | O107: 0.25 | P107: 0.25 | Q107: 0.25 | R107: 0.25 | AB107: =IFERROR(($J107*O107)*$L107, "") -> 1136.0425 | AC107: =IFERROR(($J107*P107)*$L107, "") -> 1136.0425 | AD107: =IFERROR(($J107*Q107)*$L107, "") -> 1136.0425 | AE107: =IFERROR(($J107*R107)*$L107, "") -> 1136.0425 | AF107: =IFERROR(($J107*S107)*$L107, "") -> 0 | AG107: =IFERROR(($J107*T107)*$L107, "") -> 0 | AH107: =IFERROR(($J107*U107)*$L107, "") -> 0 | AI107: =IFERROR(($J107*V107)*$L107, "") -> 0 | ... AM107: =IFERROR(($J107*Z107)*$L107, "") -> 0 | AN107: =IFERROR(SUMIF($AB$4:$AM$4, "RDEC", AB107:AM107), "") -> 1136.0425 | AO107: =IFERROR(SUMIF($AB$4:$AM$4, "SME", AB107:AM107), "") -> 3408.1275 | AP107: =IFERROR(SUMIF($AB$4:$AM$4, "De Minimis", AB107:AM107), "") -> 0 | AR107: =IFERROR(($J107*O107)*$M107, "") -> 0 | AS107: =IFERROR(($J107*P107)*$M107, "") -> 0 | AT107: =IFERROR(($J107*Q107)*$M107, "") -> 0 | AU107: =IFERROR(($J107*R107)*$M107, "") -> 0 | AV107: =IFERROR(($J107*S107)*$M107, "") -> 0 | AW107: =IFERROR(($J107*T107)*$M107, "") -> 0 | AX107: =IFERROR(($J107*U107)*$M107, "") -> 0 | AY107: =IFERROR(($J107*V107)*$M107, "") -> 0 | ... BC107: =IFERROR(($J107*Z107)*$M107, "") -> 0 | BD107: =IFERROR(SUMIF($AB$4:$AM$4, "RDEC", AR107:BC107), "") -> 0 | BE107: =IFERROR(SUMIF($AB$4:$AM$4, "SME", AR107:BC107), "") -> 0 | BF107: =IFERROR(SUMIF($AB$4:$AM$4, "De Minimis", AR107:BC107), "") -> 0 | BH107: =IF((SUM(O107:Z107)>1),"ERROR","") | BJ107: =IF(C93>0, C93, "")
...

Sheet Overseas Staff
A1: Overseas Staff Costs
I2: CLIENT INPUT | L2: CLIENT INPUT | Y2: DIRECT OVERSEAS STAFF COSTS | AO2: INDIRECT OVERSEAS STAFF COSTS
B3: Name | C3: Position / Job Title | D3: Month | E3: Gross Salary | G3: Total Cost | I3: Direct % | J3: Indirect % | L3: =IF(Summary!$B$15>0,Summary!$B$15,"") -> Automated Document Intelligence Platform | M3: =IF(Summary!$B$16>0,Summary!$B$16,"") -> Real-Time Anomaly Detection Engine | N3: =IF(Summary!$B$17>0,Summary!$B$17,"") -> Natural Language Query Interface | O3: =IF(Summary!$B$18>0,Summary!$B$18,"") -> Predictive Maintenance ML Pipeline | P3: =IF(Summary!$B$19>0,Summary!$B$19,"") -> Privacy-Preserving Data Linkage | Q3: =IF(Summary!$B$20>0,Summary!$B$20,"") | R3: =IF(Summary!$B$21>0,Summary!$B$21,"") | S3: =IF(Summary!$B$22>0,Summary!$B$22,"") | T3: =IF(Summary!$B$23>0,Summary!$B$23,"") | U3: =IF(Summary!$B$24>0,Summary!$B$24,"") | V3: =IF(Summary!$B$25>0,Summary!$B$25,"") | W3: =IF(Summary!$B$26>0,Summary!$B$26,"") | Y3: =IF(Summary!$B$15>0,Summary!$B$15,"") -> Automated Document Intelligence Platform | Z3: =IF(Summary!$B$16>0,Summary!$B$16,"") -> Real-Time Anomaly Detection Engine | AA3: =IF(Summary!$B$17>0,Summary!$B$17,"") -> Natural Language Query Interface | AB3: =IF(Summary!$B$18>0,Summary!$B$18,"") -> Predictive Maintenance ML Pipeline | AC3: =IF(Summary!$B$19>0,Summary!$B$19,"") -> Privacy-Preserving Data Linkage | AD3: =IF(Summary!$B$20>0,Summary!$B$20,"") | AE3: =IF(Summary!$B$21>0,Summary!$B$21,"") | AF3: =IF(Summary!$B$22>0,Summary!$B$22,"") | AG3: =IF(Summary!$B$23>0,Summary!$B$23,"") | AH3: =IF(Summary!$B$24>0,Summary!$B$24,"") | AI3: =IF(Summary!$B$25>0,Summary!$B$25,"") | AJ3: =IF(Summary!$B$26>0,Summary!$B$26,"") | AK3: RDEC | AL3: SME | AM3: De Minimis | AO3: =IF(Summary!$B$15>0,Summary!$B$15,"") -> Automated Document Intelligence Platform | AP3: =IF(Summary!$B$16>0,Summary!$B$16,"") -> Real-Time Anomaly Detection Engine | AQ3: =IF(Summary!$B$17>0,Summary!$B$17,"") -> Natural Language Query Interface | AR3: =IF(Summary!$B$18>0,Summary!$B$18,"") -> Predictive Maintenance ML Pipeline | AS3: =IF(Summary!$B$19>0,Summary!$B$19,"") -> Privacy-Preserving Data Linkage | AT3: =IF(Summary!$B$20>0,Summary!$B$20,"") | AU3: =IF(Summary!$B$21>0,Summary!$B$21,"") | AV3: =IF(Summary!$B$22>0,Summary!$B$22,"") | AW3: =IF(Summary!$B$23>0,Summary!$B$23,"") | AX3: =IF(Summary!$B$24>0,Summary!$B$24,"") | AY3: =IF(Summary!$B$25>0,Summary!$B$25,"") | AZ3: =IF(Summary!$B$26>0,Summary!$B$26,"") | BA3: RDEC | BB3: SME | BC3: De Minimis | BE3: Check
L4: =IF(ISBLANK(Summary!$C$15),"", IF(Summary!$C$15="No", "SME", IF(AND(Summary!$C$15="Yes", Summary!$D$15="Yes"), "De Minimis", "RDEC"))) -> SME | M4: =IF(ISBLANK(Summary!$C$16),"", IF(Summary!$C$16="No", "SME", IF(AND(Summary!$C$16="Yes", Summary!$D$16="Yes"), "De Minimis", "RDEC"))) -> SME | N4: =IF(ISBLANK(Summary!$C$17),"", IF(Summary!$C$17="No", "SME", IF(AND(Summary!$C$17="Yes", Summary!$D$17="Yes"), "De Minimis", "RDEC"))) -> SME | O4: =IF(ISBLANK(Summary!$C$18),"", IF(Summary!$C$18="No", "SME", IF(AND(Summary!$C$18="Yes", Summary!$D$18="Yes"), "De Minimis", "RDEC"))) -> RDEC | P4: =IF(ISBLANK(Summary!$C$19),"", IF(Summary!$C$19="No", "SME", IF(AND(Summary!$C$19="Yes", Summary!$D$19="Yes"), "De Minimis", "RDEC"))) -> SME | Q4: =IF(ISBLANK(Summary!$C$20),"", IF(Summary!$C$20="No", "SME", IF(AND(Summary!$C$20="Yes", Summary!$D$20="Yes"), "De Minimis", "RDEC"))) | R4: =IF(ISBLANK(Summary!$C$21),"", IF(Summary!$C$21="No", "SME", IF(AND(Summary!$C$21="Yes", Summary!$D$21="Yes"), "De Minimis", "RDEC"))) | S4: =IF(ISBLANK(Summary!$C$22),"", IF(Summary!$C$22="No", "SME", IF(AND(Summary!$C$22="Yes", Summary!$D$22="Yes"), "De Minimis", "RDEC"))) | T4: =IF(ISBLANK(Summary!$C$23),"", IF(Summary!$C$23="No", "SME", IF(AND(Summary!$C$23="Yes", Summary!$D$23="Yes"), "De Minimis", "RDEC"))) | U4: =IF(ISBLANK(Summary!$C$24),"", IF(Summary!$C$24="No", "SME", IF(AND(Summary!$C$24="Yes", Summary!$D$24="Yes"), "De Minimis", "RDEC"))) | V4: =IF(ISBLANK(Summary!$C$25),"", IF(Summary!$C$25="No", "SME", IF(AND(Summary!$C$25="Yes", Summary!$D$25="Yes"), "De Minimis", "RDEC"))) | W4: =IF(ISBLANK(Summary!$C$26),"", IF(Summary!$C$26="No", "SME", IF(AND(Summary!$C$26="Yes", Summary!$D$26="Yes"), "De Minimis", "RDEC"))) | Y4: =IF(ISBLANK(Summary!$C$15),"", IF(Summary!$C$15="No", "SME", IF(AND(Summary!$C$15="Yes", Summary!$D$15="Yes"), "De Minimis", "RDEC"))) -> SME | Z4: =IF(ISBLANK(Summary!$C$16),"", IF(Summary!$C$16="No", "SME", IF(AND(Summary!$C$16="Yes", Summary!$D$16="Yes"), "De Minimis", "RDEC"))) -> SME | AA4: =IF(ISBLANK(Summary!$C$17),"", IF(Summary!$C$17="No", "SME", IF(AND(Summary!$C$17="Yes", Summary!$D$17="Yes"), "De Minimis", "RDEC"))) -> SME | AB4: =IF(ISBLANK(Summary!$C$18),"", IF(Summary!$C$18="No", "SME", IF(AND(Summary!$C$18="Yes", Summary!$D$18="Yes"), "De Minimis", "RDEC"))) -> RDEC | AC4: =IF(ISBLANK(Summary!$C$19),"", IF(Summary!$C$19="No", "SME", IF(AND(Summary!$C$19="Yes", Summary!$D$19="Yes"), "De Minimis", "RDEC"))) -> SME | AD4: =IF(ISBLANK(Summary!$C$20),"", IF(Summary!$C$20="No", "SME", IF(AND(Summary!$C$20="Yes", Summary!$D$20="Yes"), "De Minimis", "RDEC"))) | AE4: =IF(ISBLANK(Summary!$C$21),"", IF(Summary!$C$21="No", "SME", IF(AND(Summary!$C$21="Yes", Summary!$D$21="Yes"), "De Minimis", "RDEC"))) | AF4: =IF(ISBLANK(Summary!$C$22),"", IF(Summary!$C$22="No", "SME", IF(AND(Summary!$C$22="Yes", Summary!$D$22="Yes"), "De Minimis", "RDEC"))) | AG4: =IF(ISBLANK(Summary!$C$23),"", IF(Summary!$C$23="No", "SME", IF(AND(Summary!$C$23="Yes", Summary!$D$23="Yes"), "De Minimis", "RDEC"))) | AH4: =IF(ISBLANK(Summary!$C$24),"", IF(Summary!$C$24="No", "SME", IF(AND(Summary!$C$24="Yes", Summary!$D$24="Yes"), "De Minimis", "RDEC"))) | AI4: =IF(ISBLANK(Summary!$C$25),"", IF(Summary!$C$25="No", "SME", IF(AND(Summary!$C$25="Yes", Summary!$D$25="Yes"), "De Minimis", "RDEC"))) | AJ4: =IF(ISBLANK(Summary!$C$26),"", IF(Summary!$C$26="No", "SME", IF(AND(Summary!$C$26="Yes", Summary!$D$26="Yes"), "De Minimis", "RDEC"))) | AO4: =IF(ISBLANK(Summary!$C$15),"", IF(Summary!$C$15="No", "SME", IF(AND(Summary!$C$15="Yes", Summary!$D$15="Yes"), "De Minimis", "RDEC"))) -> SME | AP4: =IF(ISBLANK(Summary!$C$16),"", IF(Summary!$C$16="No", "SME", IF(AND(Summary!$C$16="Yes", Summary!$D$16="Yes"), "De Minimis", "RDEC"))) -> SME | AQ4: =IF(ISBLANK(Summary!$C$17),"", IF(Summary!$C$17="No", "SME", IF(AND(Summary!$C$17="Yes", Summary!$D$17="Yes"), "De Minimis", "RDEC"))) -> SME | AR4: =IF(ISBLANK(Summary!$C$18),"", IF(Summary!$C$18="No", "SME", IF(AND(Summary!$C$18="Yes", Summary!$D$18="Yes"), "De Minimis", "RDEC"))) -> RDEC | AS4: =IF(ISBLANK(Summary!$C$19),"", IF(Summary!$C$19="No", "SME", IF(AND(Summary!$C$19="Yes", Summary!$D$19="Yes"), "De Minimis", "RDEC"))) -> SME | AT4: =IF(ISBLANK(Summary!$C$20),"", IF(Summary!$C$20="No", "SME", IF(AND(Summary!$C$20="Yes", Summary!$D$20="Yes"), "De Minimis", "RDEC"))) | AU4: =IF(ISBLANK(Summary!$C$21),"", IF(Summary!$C$21="No", "SME", IF(AND(Summary!$C$21="Yes", Summary!$D$21="Yes"), "De Minimis", "RDEC"))) | AV4: =IF(ISBLANK(Summary!$C$22),"", IF(Summary!$C$22="No", "SME", IF(AND(Summary!$C$22="Yes", Summary!$D$22="Yes"), "De Minimis", "RDEC"))) | AW4: =IF(ISBLANK(Summary!$C$23),"", IF(Summary!$C$23="No", "SME", IF(AND(Summary!$C$23="Yes", Summary!$D$23="Yes"), "De Minimis", "RDEC"))) | AX4: =IF(ISBLANK(Summary!$C$24),"", IF(Summary!$C$24="No", "SME", IF(AND(Summary!$C$24="Yes", Summary!$D$24="Yes"), "De Minimis", "RDEC"))) | AY4: =IF(ISBLANK(Summary!$C$25),"", IF(Summary!$C$25="No", "SME", IF(AND(Summary!$C$25="Yes", Summary!$D$25="Yes"), "De Minimis", "RDEC"))) | AZ4: =IF(ISBLANK(Summary!$C$26),"", IF(Summary!$C$26="No", "SME", IF(AND(Summary!$C$26="Yes", Summary!$D$26="Yes"), "De Minimis", "RDEC")))
L5: R&D % | M5: R&D % | N5: R&D % | O5: R&D % | P5: R&D % | Q5: R&D % | R5: R&D % | S5: R&D % | T5: R&D % | U5: R&D % | V5: R&D % | W5: R&D % | Y5: R&D £ | Z5: R&D £ | AA5: R&D £ | AB5: R&D £ | AC5: R&D £ | AD5: R&D £ | AE5: R&D £ | AF5: R&D £ | AG5: R&D £ | AH5: R&D £ | AI5: R&D £ | AJ5: R&D £ | AK5: R&D £ | AL5: R&D £ | AM5: R&D £ | AO5: R&D £ | AP5: R&D £ | AQ5: R&D £ | AR5: R&D £ | AS5: R&D £ | AT5: R&D £ | AU5: R&D £ | AV5: R&D £ | AW5: R&D £ | AX5: R&D £ | AY5: R&D £ | AZ5: R&D £ | BA5: R&D £ | BB5: R&D £ | BC5: R&D £ | BE5: %
A7: 1 | B7: TBA | C7: TBA
D9: =+Summary!B8 -> 45292 | E9: 0 | F9: 0 | G9: =SUM(E9:F9) -> 0 | I9: 1 | J9: =1-I9 -> 0 | Y9: =IFERROR(L9*$G9*I$9, "") -> 0 | Z9: =IFERROR(M9*$G9*$I9, "") -> 0 | AA9: =IFERROR(N9*$G9*$I9, "") -> 0 | AB9: =IFERROR(O9*$G9*$I9, "") -> 0 | AC9: =IFERROR(P9*$G9*$I9, "") -> 0 | AD9: =IFERROR(Q9*$G9*$I9, "") -> 0 | AE9: =IFERROR(R9*$G9*$I9, "") -> 0 | AF9: =IFERROR(S9*$G9*$I9, "") -> 0 | AG9: =IFERROR(T9*$G9*$I9, "") -> 0 | ... AJ9: =IFERROR(W9*$G9*$I9, "") -> 0 | AK9: =IFERROR(SUMIF($Y$4:$AJ$4, "RDEC", Y9:AJ9), "") -> 0 | AL9: =IFERROR(SUMIF($Y$4:$AJ$4, "SME", Y9:AJ9), "") -> 0 | AM9: =IFERROR(SUMIF($Y$4:$AJ$4, "De Minimis", Y9:AJ9), "") -> 0 | AO9: =IFERROR($G9*$J9*L9, "") -> 0 | AP9: =IFERROR($G9*$J9*M9, "") -> 0 | AQ9: =IFERROR($G9*$J9*N9, "") -> 0 | AR9: =IFERROR($G9*$J9*O9, "") -> 0 | AS9: =IFERROR($G9*$J9*P9, "") -> 0 | AT9: =IFERROR($G9*$J9*Q9, "") -> 0 | AU9: =IFERROR($G9*$J9*R9, "") -> 0 | AV9: =IFERROR($G9*$J9*S9, "") -> 0 | ... AZ9: =IFERROR($G9*$J9*W9, "") -> 0 | BA9: =IFERROR(SUMIF($AO$4:$AZ$4, "RDEC", AO9:AZ9), "") -> 0 | BB9: =IFERROR(SUMIF($AO$4:$AZ$4, "SME", AO9:AZ9), "") -> 0 | BC9: =IFERROR(SUMIF($AO$4:$AZ$4, "De Minimis", AO9:AZ9), "") -> 0 | BE9: =IF((SUM(L9:W9)>1),"ERROR","")
D10: =EDATE(D9, 1) -> 45323 | E10: 0 | F10: 0 | G10: =SUM(E10:F10) -> 0 | I10: 1 | J10: =1-I10 -> 0 | Y10: =IFERROR(L10*$G10*I$9, "") -> 0 | Z10: =IFERROR(M10*$G10*$I10, "") -> 0 | AA10: =IFERROR(N10*$G10*$I10, "") -> 0 | AB10: =IFERROR(O10*$G10*$I10, "") -> 0 | AC10: =IFERROR(P10*$G10*$I10, "") -> 0 | AD10: =IFERROR(Q10*$G10*$I10, "") -> 0 | AE10: =IFERROR(R10*$G10*$I10, "") -> 0 | AF10: =IFERROR(S10*$G10*$I10, "") -> 0 | AG10: =IFERROR(T10*$G10*$I10, "") -> 0 | ... AJ10: =IFERROR(W10*$G10*$I10, "") -> 0 | AK10: =IFERROR(SUMIF($Y$4:$AJ$4, "RDEC", Y10:AJ10), "") -> 0 | AL10: =IFERROR(SUMIF($Y$4:$AJ$4, "SME", Y10:AJ10), "") -> 0 | AM10: =IFERROR(SUMIF($Y$4:$AJ$4, "De Minimis", Y10:AJ10), "") -> 0 | AO10: =IFERROR($G10*$J10*L10, "") -> 0 | AP10: =IFERROR($G10*$J10*M10, "") -> 0 | AQ10: =IFERROR($G10*$J10*N10, "") -> 0 | AR10: =IFERROR($G10*$J10*O10, "") -> 0 | AS10: =IFERROR($G10*$J10*P10, "") -> 0 | AT10: =IFERROR($G10*$J10*Q10, "") -> 0 | AU10: =IFERROR($G10*$J10*R10, "") -> 0 | AV10: =IFERROR($G10*$J10*S10, "") -> 0 | ... AZ10: =IFERROR($G10*$J10*W10, "") -> 0 | BA10: =IFERROR(SUMIF($AO$4:$AZ$4, "RDEC", AO10:AZ10), "") -> 0 | BB10: =IFERROR(SUMIF($AO$4:$AZ$4, "SME", AO10:AZ10), "") -> 0 | BC10: =IFERROR(SUMIF($Y$4:$AJ$4, "De Minimis", AO10:AZ10), "") -> 0 | BE10: =IF((SUM(L10:W10)>1),"ERROR","")
D11: =EDATE(D10, 1) -> 45352 | E11: 0 | F11: 0 | G11: =SUM(E11:F11) -> 0 | I11: 1 | J11: =1-I11 -> 0 | Y11: =IFERROR(L11*$G11*I$9, "") -> 0 | Z11: =IFERROR(M11*$G11*$I11, "") -> 0 | AA11: =IFERROR(N11*$G11*$I11, "") -> 0 | AB11: =IFERROR(O11*$G11*$I11, "") -> 0 | AC11: =IFERROR(P11*$G11*$I11, "") -> 0 | AD11: =IFERROR(Q11*$G11*$I11, "") -> 0 | AE11: =IFERROR(R11*$G11*$I11, "") -> 0 | AF11: =IFERROR(S11*$G11*$I11, "") -> 0 | AG11: =IFERROR(T11*$G11*$I11, "") -> 0 | ... AJ11: =IFERROR(W11*$G11*$I11, "") -> 0 | AK11: =IFERROR(SUMIF($Y$4:$AJ$4, "RDEC", Y11:AJ11), "") -> 0 | AL11: =IFERROR(SUMIF($Y$4:$AJ$4, "SME", Y11:AJ11), "") -> 0 | AM11: =IFERROR(SUMIF($Y$4:$AJ$4, "De Minimis", Y11:AJ11), "") -> 0 | AO11: =IFERROR($G11*$J11*L11, "") -> 0 | AP11: =IFERROR($G11*$J11*M11, "") -> 0 | AQ11: =IFERROR($G11*$J11*N11, "") -> 0 | AR11: =IFERROR($G11*$J11*O11, "") -> 0 | AS11: =IFERROR($G11*$J11*P11, "") -> 0 | AT11: =IFERROR($G11*$J11*Q11, "") -> 0 | AU11: =IFERROR($G11*$J11*R11, "") -> 0 | AV11: =IFERROR($G11*$J11*S11, "") -> 0 | ... AZ11: =IFERROR($G11*$J11*W11, "") -> 0 | BA11: =IFERROR(SUMIF($AO$4:$AZ$4, "RDEC", AO11:AZ11), "") -> 0 | BB11: =IFERROR(SUMIF($AO$4:$AZ$4, "SME", AO11:AZ11), "") -> 0 | BC11: =IFERROR(SUMIF($Y$4:$AJ$4, "De Minimis", AO11:AZ11), "") -> 0 | BE11: =IF((SUM(L11:W11)>1),"ERROR","")
D12: =EDATE(D11, 1) -> 45383 | E12: 0 | F12: 0 | G12: =SUM(E12:F12) -> 0 | I12: 1 | J12: =1-I12 -> 0 | Y12: =IFERROR(L12*$G12*I$9, "") -> 0 | Z12: =IFERROR(M12*$G12*$I12, "") -> 0 | AA12: =IFERROR(N12*$G12*$I12, "") -> 0 | AB12: =IFERROR(O12*$G12*$I12, "") -> 0 | AC12: =IFERROR(P12*$G12*$I12, "") -> 0 | AD12: =IFERROR(Q12*$G12*$I12, "") -> 0 | AE12: =IFERROR(R12*$G12*$I12, "") -> 0 | AF12: =IFERROR(S12*$G12*$I12, "") -> 0 | AG12: =IFERROR(T12*$G12*$I12, "") -> 0 | ... AJ12: =IFERROR(W12*$G12*$I12, "") -> 0 | AK12: =IFERROR(SUMIF($Y$4:$AJ$4, "RDEC", Y12:AJ12), "") -> 0 | AL12: =IFERROR(SUMIF($Y$4:$AJ$4, "SME", Y12:AJ12), "") -> 0 | AM12: =IFERROR(SUMIF($Y$4:$AJ$4, "De Minimis", Y12:AJ12), "") -> 0 | AO12: =IFERROR($G12*$J12*L12, "") -> 0 | AP12: =IFERROR($G12*$J12*M12, "") -> 0 | AQ12: =IFERROR($G12*$J12*N12, "") -> 0 | AR12: =IFERROR($G12*$J12*O12, "") -> 0 | AS12: =IFERROR($G12*$J12*P12, "") -> 0 | AT12: =IFERROR($G12*$J12*Q12, "") -> 0 | AU12: =IFERROR($G12*$J12*R12, "") -> 0 | AV12: =IFERROR($G12*$J12*S12, "") -> 0 | ... AZ12: =IFERROR($G12*$J12*W12, "") -> 0 | BA12: =IFERROR(SUMIF($AO$4:$AZ$4, "RDEC", AO12:AZ12), "") -> 0 | BB12: =IFERROR(SUMIF($AO$4:$AZ$4, "SME", AO12:AZ12), "") -> 0 | BC12: =IFERROR(SUMIF($Y$4:$AJ$4, "De Minimis", AO12:AZ12), "") -> 0 | BE12: =IF((SUM(L12:W12)>1),"ERROR","")
D13: =EDATE(D12, 1) -> 45413 | E13: 0 | F13: 0 | G13: =SUM(E13:F13) -> 0 | I13: 1 | J13: =1-I13 -> 0 | Y13: =IFERROR(L13*$G13*I$9, "") -> 0 | Z13: =IFERROR(M13*$G13*$I13, "") -> 0 | AA13: =IFERROR(N13*$G13*$I13, "") -> 0 | AB13: =IFERROR(O13*$G13*$I13, "") -> 0 | AC13: =IFERROR(P13*$G13*$I13, "") -> 0 | AD13: =IFERROR(Q13*$G13*$I13, "") -> 0 | AE13: =IFERROR(R13*$G13*$I13, "") -> 0 | AF13: =IFERROR(S13*$G13*$I13, "") -> 0 | AG13: =IFERROR(T13*$G13*$I13, "") -> 0 | ... AJ13: =IFERROR(W13*$G13*$I13, "") -> 0 | AK13: =IFERROR(SUMIF($Y$4:$AJ$4, "RDEC", Y13:AJ13), "") -> 0 | AL13: =IFERROR(SUMIF($Y$4:$AJ$4, "SME", Y13:AJ13), "") -> 0 | AM13: =IFERROR(SUMIF($Y$4:$AJ$4, "De Minimis", Y13:AJ13), "") -> 0 | AO13: =IFERROR($G13*$J13*L13, "") -> 0 | AP13: =IFERROR($G13*$J13*M13, "") -> 0 | AQ13: =IFERROR($G13*$J13*N13, "") -> 0 | AR13: =IFERROR($G13*$J13*O13, "") -> 0 | AS13: =IFERROR($G13*$J13*P13, "") -> 0 | AT13: =IFERROR($G13*$J13*Q13, "") -> 0 | AU13: =IFERROR($G13*$J13*R13, "") -> 0 | AV13: =IFERROR($G13*$J13*S13, "") -> 0 | ... AZ13: =IFERROR($G13*$J13*W13, "") -> 0 | BA13: =IFERROR(SUMIF($AO$4:$AZ$4, "RDEC", AO13:AZ13), "") -> 0 | BB13: =IFERROR(SUMIF($AO$4:$AZ$4, "SME", AO13:AZ13), "") -> 0 | BC13: =IFERROR(SUMIF($Y$4:$AJ$4, "De Minimis", AO13:AZ13), "") -> 0 | BE13: =IF((SUM(L13:W13)>1),"ERROR","")
D14: =EDATE(D13, 1) -> 45444 | E14: 0 | F14: 0 | G14: =SUM(E14:F14) -> 0 | I14: 1 | J14: =1-I14 -> 0 | Y14: =IFERROR(L14*$G14*I$9, "") -> 0 | Z14: =IFERROR(M14*$G14*$I14, "") -> 0 | AA14: =IFERROR(N14*$G14*$I14, "") -> 0 | AB14: =IFERROR(O14*$G14*$I14, "") -> 0 | AC14: =IFERROR(P14*$G14*$I14, "") -> 0 | AD14: =IFERROR(Q14*$G14*$I14, "") -> 0 | AE14: =IFERROR(R14*$G14*$I14, "") -> 0 | AF14: =IFERROR(S14*$G14*$I14, "") -> 0 | AG14: =IFERROR(T14*$G14*$I14, "") -> 0 | ... AJ14: =IFERROR(W14*$G14*$I14, "") -> 0 | AK14: =IFERROR(SUMIF($Y$4:$AJ$4, "RDEC", Y14:AJ14), "") -> 0 | AL14: =IFERROR(SUMIF($Y$4:$AJ$4, "SME", Y14:AJ14), "") -> 0 | AM14: =IFERROR(SUMIF($Y$4:$AJ$4, "De Minimis", Y14:AJ14), "") -> 0 | AO14: =IFERROR($G14*$J14*L14, "") -> 0 | AP14: =IFERROR($G14*$J14*M14, "") -> 0 | AQ14: =IFERROR($G14*$J14*N14, "") -> 0 | AR14: =IFERROR($G14*$J14*O14, "") -> 0 | AS14: =IFERROR($G14*$J14*P14, "") -> 0 | AT14: =IFERROR($G14*$J14*Q14, "") -> 0 | AU14: =IFERROR($G14*$J14*R14, "") -> 0 | AV14: =IFERROR($G14*$J14*S14, "") -> 0 | ... AZ14: =IFERROR($G14*$J14*W14, "") -> 0 | BA14: =IFERROR(SUMIF($AO$4:$AZ$4, "RDEC", AO14:AZ14), "") -> 0 | BB14: =IFERROR(SUMIF($AO$4:$AZ$4, "SME", AO14:AZ14), "") -> 0 | BC14: =IFERROR(SUMIF($Y$4:$AJ$4, "De Minimis", AO14:AZ14), "") -> 0 | BE14: =IF((SUM(L14:W14)>1),"ERROR","")
D15: =EDATE(D14, 1) -> 45474 | E15: 0 | F15: 0 | G15: =SUM(E15:F15) -> 0 | I15: 1 | J15: =1-I15 -> 0 | Y15: =IFERROR(L15*$G15*I$9, "") -> 0 | Z15: =IFERROR(M15*$G15*$I15, "") -> 0 | AA15: =IFERROR(N15*$G15*$I15, "") -> 0 | AB15: =IFERROR(O15*$G15*$I15, "") -> 0 | AC15: =IFERROR(P15*$G15*$I15, "") -> 0 | AD15: =IFERROR(Q15*$G15*$I15, "") -> 0 | AE15: =IFERROR(R15*$G15*$I15, "") -> 0 | AF15: =IFERROR(S15*$G15*$I15, "") -> 0 | AG15: =IFERROR(T15*$G15*$I15, "") -> 0 | ... AJ15: =IFERROR(W15*$G15*$I15, "") -> 0 | AK15: =IFERROR(SUMIF($Y$4:$AJ$4, "RDEC", Y15:AJ15), "") -> 0 | AL15: =IFERROR(SUMIF($Y$4:$AJ$4, "SME", Y15:AJ15), "") -> 0 | AM15: =IFERROR(SUMIF($Y$4:$AJ$4, "De Minimis", Y15:AJ15), "") -> 0 | AO15: =IFERROR($G15*$J15*L15, "") -> 0 | AP15: =IFERROR($G15*$J15*M15, "") -> 0 | AQ15: =IFERROR($G15*$J15*N15, "") -> 0 | AR15: =IFERROR($G15*$J15*O15, "") -> 0 | AS15: =IFERROR($G15*$J15*P15, "") -> 0 | AT15: =IFERROR($G15*$J15*Q15, "") -> 0 | AU15: =IFERROR($G15*$J15*R15, "") -> 0 | AV15: =IFERROR($G15*$J15*S15, "") -> 0 | ... AZ15: =IFERROR($G15*$J15*W15, "") -> 0 | BA15: =IFERROR(SUMIF($AO$4:$AZ$4, "RDEC", AO15:AZ15), "") -> 0 | BB15: =IFERROR(SUMIF($AO$4:$AZ$4, "SME", AO15:AZ15), "") -> 0 | BC15: =IFERROR(SUMIF($Y$4:$AJ$4, "De Minimis", AO15:AZ15), "") -> 0 | BE15: =IF((SUM(L15:W15)>1),"ERROR","")
D16: =EDATE(D15, 1) -> 45505 | E16: 0 | F16: 0 | G16: =SUM(E16:F16) -> 0 | I16: 1 | J16: =1-I16 -> 0 | Y16: =IFERROR(L16*$G16*I$9, "") -> 0 | Z16: =IFERROR(M16*$G16*$I16, "") -> 0 | AA16: =IFERROR(N16*$G16*$I16, "") -> 0 | AB16: =IFERROR(O16*$G16*$I16, "") -> 0 | AC16: =IFERROR(P16*$G16*$I16, "") -> 0 | AD16: =IFERROR(Q16*$G16*$I16, "") -> 0 | AE16: =IFERROR(R16*$G16*$I16, "") -> 0 | AF16: =IFERROR(S16*$G16*$I16, "") -> 0 | AG16: =IFERROR(T16*$G16*$I16, "") -> 0 | ... AJ16: =IFERROR(W16*$G16*$I16, "") -> 0 | AK16: =IFERROR(SUMIF($Y$4:$AJ$4, "RDEC", Y16:AJ16), "") -> 0 | AL16: =IFERROR(SUMIF($Y$4:$AJ$4, "SME", Y16:AJ16), "") -> 0 | AM16: =IFERROR(SUMIF($Y$4:$AJ$4, "De Minimis", Y16:AJ16), "") -> 0 | AO16: =IFERROR($G16*$J16*L16, "") -> 0 | AP16: =IFERROR($G16*$J16*M16, "") -> 0 | AQ16: =IFERROR($G16*$J16*N16, "") -> 0 | AR16: =IFERROR($G16*$J16*O16, "") -> 0 | AS16: =IFERROR($G16*$J16*P16, "") -> 0 | AT16: =IFERROR($G16*$J16*Q16, "") -> 0 | AU16: =IFERROR($G16*$J16*R16, "") -> 0 | AV16: =IFERROR($G16*$J16*S16, "") -> 0 | ... AZ16: =IFERROR($G16*$J16*W16, "") -> 0 | BA16: =IFERROR(SUMIF($AO$4:$AZ$4, "RDEC", AO16:AZ16), "") -> 0 | BB16: =IFERROR(SUMIF($AO$4:$AZ$4, "SME", AO16:AZ16), "") -> 0 | BC16: =IFERROR(SUMIF($Y$4:$AJ$4, "De Minimis", AO16:AZ16), "") -> 0 | BE16: =IF((SUM(L16:W16)>1),"ERROR","")
D17: =EDATE(D16, 1) -> 45536 | E17: 0 | F17: 0 | G17: =SUM(E17:F17) -> 0 | I17: 1 | J17: =1-I17 -> 0 | Y17: =IFERROR(L17*$G17*I$9, "") -> 0 | Z17: =IFERROR(M17*$G17*$I17, "") -> 0 | AA17: =IFERROR(N17*$G17*$I17, "") -> 0 | AB17: =IFERROR(O17*$G17*$I17, "") -> 0 | AC17: =IFERROR(P17*$G17*$I17, "") -> 0 | AD17: =IFERROR(Q17*$G17*$I17, "") -> 0 | AE17: =IFERROR(R17*$G17*$I17, "") -> 0 | AF17: =IFERROR(S17*$G17*$I17, "") -> 0 | AG17: =IFERROR(T17*$G17*$I17, "") -> 0 | ... AJ17: =IFERROR(W17*$G17*$I17, "") -> 0 | AK17: =IFERROR(SUMIF($Y$4:$AJ$4, "RDEC", Y17:AJ17), "") -> 0 | AL17: =IFERROR(SUMIF($Y$4:$AJ$4, "SME", Y17:AJ17), "") -> 0 | AM17: =IFERROR(SUMIF($Y$4:$AJ$4, "De Minimis", Y17:AJ17), "") -> 0 | AO17: =IFERROR($G17*$J17*L17, "") -> 0 | AP17: =IFERROR($G17*$J17*M17, "") -> 0 | AQ17: =IFERROR($G17*$J17*N17, "") -> 0 | AR17: =IFERROR($G17*$J17*O17, "") -> 0 | AS17: =IFERROR($G17*$J17*P17, "") -> 0 | AT17: =IFERROR($G17*$J17*Q17, "") -> 0 | AU17: =IFERROR($G17*$J17*R17, "") -> 0 | AV17: =IFERROR($G17*$J17*S17, "") -> 0 | ... AZ17: =IFERROR($G17*$J17*W17, "") -> 0 | BA17: =IFERROR(SUMIF($AO$4:$AZ$4, "RDEC", AO17:AZ17), "") -> 0 | BB17: =IFERROR(SUMIF($AO$4:$AZ$4, "SME", AO17:AZ17), "") -> 0 | BC17: =IFERROR(SUMIF($Y$4:$AJ$4, "De Minimis", AO17:AZ17), "") -> 0 | BE17: =IF((SUM(L17:W17)>1),"ERROR","")
